Workbook

Sheet Formulario
A1: Datos Generales
A2: Area Techada (m2) | B2: Area del terreno (m2) | C2: Plazo de ejecución (meses) | D2: Area Techada Escalera (m2)
A5: Opciones Adicionales
A6: INCLUIR DEMOLICIONES | B6: INCLUIR COLUMNETAS Y VIGUETAS DE CONFINAMIENTO
A7: SI | B7: SI
A8: NO | B8: NO
A12: Cimentación
A13: TIPO DE CIMENTACION | B13: Numero de pisos | C13: Área de cimentación (m2)
A14: ZAPATAS Y VIGAS DE CIMENTACION | B14: 1
A15: PLATEA DE CIMENTACIÓN | B15: 2
B16: 3
B17: 4
A24: Ambientes
B25: Cantidad | C25: Area (m2)
A26: BIBLIOTECA
A27: LABORATORIO
A28: ALMACÉN MAT. DEP.
A29: SUM
A30: MÓDULO DE CONECTIVIDAD
A31: DIRECCIÓN ADM.
A32: SUBDIRECCIÓN
A33: SALA DE REUNIONES
A34: SECRETARÍA
A35: ÁREA DE ESPERA
A36: COORDINACIÓN ADMINISTRATIVA
A37: ARCHIVO
... A83: Exteriores
B84: Cantidad | C84: Area
A85: AREAS VERDES | B85: Cantidad | C85: Area
A86: LOSA DEPORTIVA | B86: Cantidad | C86: Area
A87: COBERTURA DE LOSA DEPORTIVA | B87: Cantidad | C87: Area
A88: PATIO DE INICIAL | B88: Cantidad | C88: Area
A89: COBERTURA PATIO DE INICIAL | B89: Cantidad | C89: Area
A90: VEREDAS Y RAMPAS DE CONCRETO | B90: Cantidad | C90: Area
A91: PAVIMENTO RIGIDO VEHICULAR | B91: Cantidad | C91: Area
A92: CERCO PERIMETRICO H=3.00M | B92: Cantidad | C92: Area
A93: Adicionales
A94: ASTA DE BANDERA | B94: Cantidad
A95: ESTACIONAMIENTO DE BICICLETAS | B95: Cantidad
A96: PORTADA DE INGRESO (PORTON METALICO) | B96: Cantidad
A97: LAMAS EN PASADIZOS | B97: Cantidad | C97: ML

Sheet Datos iniciales 
A1: Categoría
A2: Obras provisionales | B2: Area Techada | C2: Area del terreno | D2: Plazo de ejecución | E2: Incluye demoliciones | F2: CT
B3: 300 | C3: 1000 | D3: 12 | E3: SI | F3: {=_xlfn.IFS(E3="SI",PROVISIONALES!K3,E3="NO",PROVISIONALES!K3-SUM(PROVISIONALES!J24:J25))} -> 218226.19
A4: Cimentación | B4: Área de cimentación | C4: #pisos | D4: Tipo de cimentacion | E4: Área de cimentación | F4: #pisos | G4: Tipo de cimentacion
B5: 200 | C5: 1 | D5: zapatas y vigas de cimentación | F5: 1 | G5: platea de cimentación
B6: 200 | C6: 2 | D6: zapatas y vigas de cimentación | E6: 100 | F6: 2 | G6: platea de cimentación
B7: 100 | C7: 3 | D7: zapatas y vigas de cimentación | F7: 3 | G7: platea de cimentación
B8: 100 | C8: 4 | D8: zapatas y vigas de cimentación | F8: 4 | G8: platea de cimentación
A10: Estructura | B10: Area Techada | D10: Incluye columnetas y viguetas | E10: Costo x m2 | F10: CT
B11: 300 | D11: SI | E11: {=_xlfn.IFS(D11="NO",'Estructura 1'!M4,D11="SI",'Estructura 1'!M4+'Estructura 2'!M4)} -> 858.86574 | F11: =B11*E11 -> 257659.72
B12: Area Techada escalera | E12: Costo x m2 | F12: CT
B13: 15 | E13: {=_xlfn.IFS(B13=0,0,B13>0,Escalera!N4)} -> 601.62699 | F13: =B13*E13 -> 9024.4049
A14: Ambientes
C15: Area | D15: Total Area
A16: BIBLIOTECA | B16: 2 | C16: 10 | D16: =ROUND(B16*C16,2) -> 20
A17: LABORATORIO | B17: 2 | C17: 10 | D17: =ROUND(B17*C17,2) -> 20
A18: ALMACÉN MAT. DEP. | B18: 2 | C18: 10 | D18: =ROUND(B18*C18,2) -> 20
A19: SUM | B19: 2 | C19: 10 | D19: =ROUND(B19*C19,2) -> 20
A20: MÓDULO DE CONECTIVIDAD | B20: 2 | C20: 10 | D20: =ROUND(B20*C20,2) -> 20
A21: DIRECCIÓN ADM. | B21: 2 | C21: 10 | D21: =ROUND(B21*C21,2) -> 20
A22: SUBDIRECCIÓN | B22: 2 | C22: 10 | D22: =ROUND(B22*C22,2) -> 20
A23: SALA DE REUNIONES | B23: 2 | C23: 10 | D23: =ROUND(B23*C23,2) -> 20
A24: SECRETARÍA | B24: 2 | C24: 10 | D24: =ROUND(B24*C24,2) -> 20
A25: ÁREA DE ESPERA | B25: 2 | C25: 10 | D25: =ROUND(B25*C25,2) -> 20
A26: COORDINACIÓN ADMINISTRATIVA | B26: 2 | C26: 10 | D26: =ROUND(B26*C26,2) -> 20
A27: ARCHIVO | B27: 2 | C27: 10 | D27: =ROUND(B27*C27,2) -> 20
... A68: AREA DE INGRESO | B68: 2 | C68: 10 | D68: =ROUND(B68*C68,2) -> 20
A69: #AMBIENTES | B69: =SUM(B16:B68) -> 106
A71: Exteriores | B71: Cantidad | C71: Area | D71: ML | E71: Area total
A72: AREAS VERDES | B72: 2 | C72: 10 | E72: =ROUND(B72*C72,2) -> 20
A73: LOSA DEPORTIVA | B73: 2 | C73: 10 | E73: =ROUND(B73*C73,2) -> 20
A74: COBERTURA LOSA DEPORTIVA | B74: 2 | C74: 10 | E74: =ROUND(B74*C74,2) -> 20
A75: PATIO DE INICIAL | B75: 2 | C75: 10 | E75: =ROUND(B75*C75,2) -> 20
A76: COBERTURA PATIO DE INICIAL | B76: 2 | C76: 10 | E76: =ROUND(B76*C76,2) -> 20
A77: ASTA DE BANDERA | B77: 2 | E77: =B77 -> 2
A78: VEREDAS Y RAMPAS DE CONCRETO | B78: 2 | C78: 10 | E78: =ROUND(B78*C78,2) -> 20
A79: PAVIMENTO RIGIDO VEHICULAR | B79: 2 | C79: 10 | E79: =ROUND(B79*C79,2) -> 20
A80: LAMAS EN PASADIZOS | B80: 2 | C80: 10 | E80: =ROUND(B80*C80,2) -> 20
A81: ESTACIONAMIENTO DE BICICLETAS | B81: 2 | E81: =B81 -> 2
A82: CERCO PERIMETRICO H=3.00m | B82: 2 | D82: 10 | E82: =ROUND(B82*D82,2) -> 20
A83: PORTADA DE INGRESO (PORTON METALICO) | B83: 2 | E83: =B83 -> 2
A85: INSTALACIONES EXTERIORES | B85: Cantidad | C85: CT
A86: SISTEMA DE BOMBEO DE PRESIÓN CONSTANTE | B86: 1 | C86: ='Obras exteriores '!E72 -> 2867.4
A87: INSTALACIONES SANITARIAS EXTERIORES INC. CANALETAS DE EVACUACIÓN PLUVIAL | B87: 1 | C87: ='Obras exteriores '!E73 -> 6500
A88: SISTEMA DE AGUA CONTRA INCENDIOS (RED CONTRA INCENDIOS, GABINETES) | B88: 1 | C88: ='Obras exteriores '!E74 -> 6600
B91: Obras provisionales | C91: =SUM(PROVISIONALES!J6:J13)+SUM(PROVISIONALES!J15:J18)+SUM(PROVISIONALES!J21:J22)+SUM(PROVISIONALES!J27:J28)+PROVISIONALES!J29+PROVISIONALES!J38+IF(E3="SI",PROVISIONALES!J66,0) -> 209494.99 | D91: =ROUND(C91+0.25%*D98,2) -> 218226.19 | E91: COSTO DIRECTO | F91: =SUM(D91:D97) -> 3492480.9
B92: Estructura | C92: =ESTRUCTURA!K3 -> 1179659.2 | D92: =C92 -> 1179659.2
B93: Arquitectura | C93: =ARQUITECTURA!K3 -> 1039120.6 | D93: =C93 -> 1039120.6
B94: Sanitarias | C94: =SANITARIAS!K3 -> 647777.59 | D94: =C94 -> 647777.59
B95: Electricas | C95: =ELECTRICAS!K3 -> 266619.99 | D95: =C95 -> 266619.99 | H95: =
B96: Comunicaciones | C96: =COMUNICACIONES!K3 -> 141077.34 | D96: =C96 -> 141077.34
B97: Exteriores
C98: =SUM(C91:C97) -> 3483749.7 | D98: =ROUND(C98+(C98*0.0025/0.9975),2) -> 3492480.9

Sheet RESUMEN
B3: Cant. | C3: meta | D3: Costo | E3: Unidad
A4: BIBLIOTECA | B4: ='Datos iniciales '!B16 -> 2 | C4: ='Datos iniciales '!D16 -> 20 | D4: =ROUND('calculo r'!L4,2) -> 52920.75 | E4: M2
A5: LABORATORIO | B5: ='Datos iniciales '!B17 -> 2 | C5: ='Datos iniciales '!D17 -> 20 | D5: =ROUND('calculo r'!L5,2) -> 60200.07 | E5: M2
A6: ALMACÉN MAT. DEP. | B6: ='Datos iniciales '!B18 -> 2 | C6: ='Datos iniciales '!D18 -> 20 | D6: =ROUND('calculo r'!L6,2) -> 50547.69 | E6: M2
A7: SUM | B7: ='Datos iniciales '!B19 -> 2 | C7: ='Datos iniciales '!D19 -> 20 | D7: =ROUND('calculo r'!L7,2) -> 54280.68 | E7: M2
A8: MÓDULO DE CONECTIVIDAD | B8: ='Datos iniciales '!B20 -> 2 | C8: ='Datos iniciales '!D20 -> 20 | D8: =ROUND('calculo r'!L8,2) -> 58963.68 | E8: M2
A9: DIRECCIÓN ADM. | B9: ='Datos iniciales '!B21 -> 2 | C9: ='Datos iniciales '!D21 -> 20 | D9: =ROUND('calculo r'!L9,2) -> 75790.51 | E9: M2
A10: SUBDIRECCIÓN | B10: ='Datos iniciales '!B22 -> 2 | C10: ='Datos iniciales '!D22 -> 20 | D10: =ROUND('calculo r'!L10,2) -> 75790.51 | E10: M2
A11: SALA DE REUNIONES | B11: ='Datos iniciales '!B23 -> 2 | C11: ='Datos iniciales '!D23 -> 20 | D11: =ROUND('calculo r'!L11,2) -> 61511.16 | E11: M2
A12: SECRETARÍA | B12: ='Datos iniciales '!B24 -> 2 | C12: ='Datos iniciales '!D24 -> 20 | D12: =ROUND('calculo r'!L12,2) -> 58931.23 | E12: M2
A13: ÁREA DE ESPERA | B13: ='Datos iniciales '!B25 -> 2 | C13: ='Datos iniciales '!D25 -> 20 | D13: =ROUND('calculo r'!L13,2) -> 58931.23 | E13: M2
A14: COORDINACIÓN ADMINISTRATIVA | B14: ='Datos iniciales '!B26 -> 2 | C14: ='Datos iniciales '!D26 -> 20 | D14: =ROUND('calculo r'!L14,2) -> 48572.12 | E14: M2
A15: ARCHIVO | B15: ='Datos iniciales '!B27 -> 2 | C15: ='Datos iniciales '!D27 -> 20 | D15: =ROUND('calculo r'!L15,2) -> 71181.3 | E15: M2
... A56: AREA DE INGRESO | B56: ='Datos iniciales '!B68 -> 2 | C56: ='Datos iniciales '!D68 -> 20 | D56: =ROUND('calculo r'!L56,2) -> 34994.74 | E56: M2
A57: EXTERIORES
A58: AREAS VERDES | B58: ='Datos iniciales '!B72 -> 2 | C58: ='Datos iniciales '!C72 -> 10 | D58: =ROUND('calculo r'!L58,2) -> 9520.08 | E58: M2
A59: LOSA DEPORTIVA | B59: ='Datos iniciales '!B73 -> 2 | C59: ='Datos iniciales '!C73 -> 10 | D59: =ROUND('calculo r'!L59,2) -> 10610.77 | E59: M2
A60: COBERTURA LOSA DEPORTIVA | B60: ='Datos iniciales '!B74 -> 2 | C60: ='Datos iniciales '!C74 -> 10 | D60: =ROUND('calculo r'!L60,2) -> 3389.8 | E60: M2
A61: PATIO DE INICIAL | B61: ='Datos iniciales '!B75 -> 2 | C61: ='Datos iniciales '!C75 -> 10 | D61: =ROUND('calculo r'!L61,2) -> 10610.77 | E61: M2
A62: COBERTURA PATIO DE INICIAL | B62: ='Datos iniciales '!B76 -> 2 | C62: ='Datos iniciales '!C76 -> 10 | D62: =ROUND('calculo r'!L62,2) -> 3389.8 | E62: M2
A63: VEREDAS Y RAMPAS DE CONCRETO | B63: ='Datos iniciales '!B78 -> 2 | C63: ='Datos iniciales '!C78 -> 10 | D63: =ROUND('calculo r'!L64,2) -> 10084.8 | E63: M2
A64: PAVIMENTO RIGIDO VEHICULAR | B64: ='Datos iniciales '!B79 -> 2 | C64: ='Datos iniciales '!C79 -> 10 | D64: =ROUND('calculo r'!L65,2) -> 10786.91 | E64: M2
A65: CERCO PERIMETRICO H=3.00m | B65: ='Datos iniciales '!B82 -> 2 | C65: ='Datos iniciales '!C82 -> 0 | D65: =ROUND('calculo r'!L68,2) -> 70735.58 | E65: ML
A66: Adicionales
A67: ASTA DE BANDERA | B67: ='Datos iniciales '!B77 -> 2 | C67: ='Datos iniciales '!C77 -> 0 | D67: =ROUND('calculo r'!L63,2) -> 4225.7 | E67: UND
A68: LAMAS EN PASADIZOS | B68: ='Datos iniciales '!B80 -> 2 | C68: ='Datos iniciales '!C80 -> 10 | D68: =ROUND('calculo r'!L66,2) -> 1509.2 | E68: M2
A69: ESTACIONAMIENTO DE BICICLETAS | B69: ='Datos iniciales '!B81 -> 2 | C69: ='Datos iniciales '!C81 -> 0 | D69: =ROUND('calculo r'!L67,2) -> 138.82 | E69: UND
A70: PORTADA DE INGRESO (PORTON METALICO) | B70: ='Datos iniciales '!B83 -> 2 | C70: ='Datos iniciales '!C83 -> 0 | D70: =ROUND('calculo r'!L69,2) -> 59161.18 | E70: UND

Sheet PROVISIONALES
G2: Unidad | H2: Metrado | I2: C.U | J2: Parcial | K2: Total
A3: 1 | B3: OBRAS PROVISIONALES, PRELIMINARES, SEGURIDAD Y SALUD EN EL TRABAJO Y PLAN DE CONTINGENCIA | K3: =J4+J19+J29+J38+J66 -> 218226.19
A4: 1.1 | B4: OBRAS PROVISIONALES | J4: =J5+J14 -> 41975.92
A5: 1.1.1 | B5: CONSTRUCCIONES PROVISIONALES | J5: =SUM(J6:J13) -> 36286.56
A6: 1.1.1.1 | B6: OFICINAS DE RESIDENCIA Y SUPERVISIÓN | G6: m2 | H6: =ROUND('Obras provisionales'!H9,2) -> 50 | I6: =ROUND('APU PROVISIONALES'!J3,2) -> 158.9 | J6: =ROUND(H6*I6,2) -> 7945
A7: 1.1.1.2 | B7: ALMACENES DE OBRA | G7: m2 | H7: =ROUND('Obras provisionales'!H10,2) -> 3 | I7: =ROUND('APU PROVISIONALES'!J28,2) -> 144.65 | J7: =ROUND(H7*I7,2) -> 433.95
A8: 1.1.1.3 | B8: CASETAS DE GUARDIANÍA | G8: m2 | H8: =ROUND('Obras provisionales'!H11,2) -> 8 | I8: =ROUND('APU PROVISIONALES'!J52,2) -> 148.04 | J8: =ROUND(H8*I8,2) -> 1184.32
A9: 1.1.1.4 | B9: COMEDOR PARA PERSONAL DE OBRA | G9: m2 | H9: =ROUND('Obras provisionales'!H12,2) -> 50 | I9: =ROUND('APU PROVISIONALES'!J76,2) -> 152.57 | J9: =ROUND(H9*I9,2) -> 7628.5
A10: 1.1.1.5 | B10: VESTUARIO PARA PERSONAL DE OBRA | G10: m2 | H10: =ROUND('Obras provisionales'!H13,2) -> 25 | I10: =ROUND('APU PROVISIONALES'!J100,2) -> 206.2 | J10: =ROUND(H10*I10,2) -> 5155
A11: 1.1.1.6 | B11: CERCO PERIMÉTRICO DE MALLA ARPILLERA | G11: m | H11: =ROUND('Obras provisionales'!H14,2) -> 126.49 | I11: =ROUND('APU PROVISIONALES'!J124,2) -> 43.81 | J11: =ROUND(H11*I11,2) -> 5541.53
A12: 1.1.1.7 | B12: SERVICIOS HIGIÉNICOS | G12: m2 | H12: =ROUND('Obras provisionales'!H15,2) -> 16 | I12: =ROUND('APU PROVISIONALES'!J140,2) -> 343.17 | J12: =ROUND(H12*I12,2) -> 5490.72
A13: 1.1.1.8 | B13: CARTEL DE IDENTIFICACIÓN DE LA OBRA | G13: und | H13: =ROUND('Obras provisionales'!H16,2) -> 2 | I13: =ROUND('APU PROVISIONALES'!J170,2) -> 1453.77 | J13: =ROUND(H13*I13,2) -> 2907.54
A14: 1.1.2 | B14: INSTALACIONES PROVISIONALES | J14: =SUM(J15:J18) -> 5689.36
A15: 1.1.2.1 | B15: CONEXIÓN E INSTALACIÓN DE AGUA | G15: glb | H15: =ROUND('Obras provisionales'!H18,2) -> 1 | I15: =ROUND('APU PROVISIONALES'!J193,2) -> 251.61 | J15: =ROUND(H15*I15,2) -> 251.61
A16: 1.1.2.2 | B16: CONSUMO Y MANTENIMIENTO DE AGUA PARA LA CONSTRUCCIÓN | G16: mes | H16: =ROUND('Obras provisionales'!H19,2) -> 12 | I16: =ROUND('APU PROVISIONALES'!J200,2) -> 185.89 | J16: =ROUND(H16*I16,2) -> 2230.68
A17: 1.1.2.3 | B17: CONEXIÓN E INSTALACIÓN DE ENERGÍA ELÉCTRICA | G17: glb | H17: =ROUND('Obras provisionales'!H20,2) -> 1 | I17: =ROUND('APU PROVISIONALES'!J207,2) -> 976.39 | J17: =ROUND(H17*I17,2) -> 976.39
A18: 1.1.2.4 | B18: CONSUMO Y MANTENIMIENTO DE ENERGÍA ELÉCTRICA | G18: mes | H18: =ROUND('Obras provisionales'!H21,2) -> 12 | I18: =ROUND('APU PROVISIONALES'!J214,2) -> 185.89 | J18: =ROUND(H18*I18,2) -> 2230.68
A19: 1.2 | B19: TRABAJOS PRELIMINARES | J19: =J20+J23+J26 -> 19481.2
A20: 1.2.1 | B20: LIMPIEZA DEL TERRENO | J20: =SUM(J21:J22) -> 2490
A21: 1.2.1.1 | B21: LIMPIEZA DEL TERRENO MANUAL | G21: m2 | H21: =ROUND('Obras provisionales'!H27,2) -> 1000 | I21: =ROUND('APU PROVISIONALES'!J221,2) -> 1.14 | J21: =ROUND(H21*I21,2) -> 1140
A22: 1.2.1.2 | B22: ELIMINACIÓN DE OBSTRUCCIONES | G22: m2 | H22: =ROUND('Obras provisionales'!H28,2) -> 1000 | I22: =ROUND('APU PROVISIONALES'!J231,2) -> 1.35 | J22: =ROUND(H22*I22,2) -> 1350
A23: 1.2.2 | B23: MOVILIZACIÓN DE CAMPAMENTO, MAQUINARIA Y HERRAMIENTAS | J23: =SUM(J24:J25) -> 8731.2
A24: 1.2.2.1 | B24: MOVILIZACIÓN DE EQUIPOS Y HERRAMIENTAS | G24: glb | H24: =ROUND('Obras provisionales'!H30,2) -> 1 | I24: =ROUND('APU PROVISIONALES'!J242,2) -> 1746.24 | J24: =ROUND(H24*I24,2) -> 1746.24
A25: 1.2.2.2 | B25: TRANSPORTE DE MATERIALES A LA OBRA | G25: glb | H25: =ROUND('Obras provisionales'!H31,2) -> 1 | I25: =ROUND('APU PROVISIONALES'!J253,2) -> 6984.96 | J25: =ROUND(H25*I25,2) -> 6984.96
A26: 1.2.3 | B26: TRAZOS, NIVELES Y REPLANTEO | J26: =SUM(J27:J28) -> 8260
A27: 1.2.3.1 | B27: TRAZO Y REPLANTEO PRELIMINAR | G27: m2 | H27: =ROUND('Obras provisionales'!H33,2) -> 1000 | I27: =ROUND('APU PROVISIONALES'!J256,2) -> 3.99 | J27: =ROUND(H27*I27,2) -> 3990
A28: 1.2.3.2 | B28: TRAZO NIVELACIÓN Y REPLANTEO DURANTE EL PROCESO | G28: m2 | H28: =ROUND('Obras provisionales'!H34,2) -> 1000 | I28: =ROUND('APU PROVISIONALES'!J276,2) -> 4.27 | J28: =ROUND(H28*I28,2) -> 4270
A29: 1.3 | B29: PLAN DE SEGURIDAD Y SALUD EN EL TRABAJO | J29: =J30 -> 108478.24
A30: 1.3.1 | B30: Equipo de seguridad y salud | J30: =SUM(J31:J37) -> 108478.24
A31: 1.3.1.1 | B31: EQUIPOS DE PROTECCIÓN INDIVIDUAL | G31: glb | H31: =ROUND('Obras provisionales'!H37,2) -> 1 | I31: =ROUND('APU PROVISIONALES'!J295,2) -> 41043.35 | J31: =ROUND(H31*I31,2) -> 41043.35
A32: 1.3.1.2 | B32: EQUIPOS DE PROTECCIÓN COLECTIVA | G32: glb | H32: =ROUND('Obras provisionales'!H38,2) -> 1 | I32: =ROUND('APU PROVISIONALES'!J321,2) -> 3824.87 | J32: =ROUND(H32*I32,2) -> 3824.87
A33: 1.3.1.3 | B33: SEÑALIZACIÓN TEMPORAL DE SEGURIDAD | G33: glb | H33: =ROUND('Obras provisionales'!H39,2) -> 1 | I33: =ROUND('APU PROVISIONALES'!J333,2) -> 6076.5 | J33: =ROUND(H33*I33,2) -> 6076.5
A34: 1.3.1.4 | B34: PROGRAMA DE CAPACITACIÓN EN SEGURIDAD Y SALUD | G34: glb | H34: =ROUND('Obras provisionales'!H40,2) -> 1 | I34: =ROUND('APU PROVISIONALES'!J347,2) -> 18386.64 | J34: =ROUND(H34*I34,2) -> 18386.64
A35: 1.3.1.5 | B35: RECURSOS PARA RESPUESTA ANTE EMERGENCIAS | G35: glb | H35: =ROUND('Obras provisionales'!H41,2) -> 1 | I35: =ROUND('APU PROVISIONALES'!J356,2) -> 1478.8 | J35: =ROUND(H35*I35,2) -> 1478.8
A36: 1.3.1.6 | B36: PROGRAMA DE PREVENCIÓN Y CONTROL | G36: und | H36: =ROUND('Obras provisionales'!H42,2) -> 1 | I36: =ROUND('APU PROVISIONALES'!J368,2) -> 8515.8 | J36: =ROUND(H36*I36,2) -> 8515.8
A37: 1.3.1.7 | B37: EXAMEN MÉDICO GENERAL | G37: und | H37: =ROUND('Obras provisionales'!H43,2) -> 1 | I37: =ROUND('APU PROVISIONALES'!J376,2) -> 29152.28 | J37: =ROUND(H37*I37,2) -> 29152.28
A38: 1.4 | B38: PLAN DE MANEJO AMBIENTAL | J38: =J39+J42+J44+J46+J59+J61 -> 45872.44
A39: 1.4.1 | B39: PROGRAMA DE PREVENCIÓN Y MITIGACIÓN AMBIENTAL | J39: =SUM(J40:J41) -> 21696.42
A40: 1.4.1.1 | B40: PREVENCIÓN Y MITIGACIÓN DE IMPACTOS | G40: m3 | H40: =ROUND('Obras provisionales'!H46,2) -> 609.6 | I40: =ROUND('APU PROVISIONALES'!J384,2) -> 32.56 | J40: =ROUND(H40*I40,2) -> 19848.58
A41: 1.4.1.2 | B41: IMPLEMENTACIÓN DE ÁREA DE SEÑALIZACIÓN | G41: und | H41: =ROUND('Obras provisionales'!H47,2) -> 16 | I41: =ROUND('APU PROVISIONALES'!J397,2) -> 115.49 | J41: =ROUND(H41*I41,2) -> 1847.84
A42: 1.4.2 | B42: PROGRAMA DE EDUCACIÓN Y CAPACITACIÓN AMBIENTAL | J42: =SUM(J43) -> 1631.52
A43: 1.4.2.1 | B43: CHARLAS DE SENSIBILIZACIÓN AMBIENTAL | G43: glb | H43: =ROUND('Obras provisionales'!H49,2) -> 12 | I43: =ROUND('APU PROVISIONALES'!J414,2) -> 135.96 | J43: =ROUND(H43*I43,2) -> 1631.52
A44: 1.4.3 | B44: PROGRAMA DE SEGUIMIENTO, CONTROL Y VIGILANCIA AMBIENTAL | J44: =SUM(J45) -> 11491.5
A45: 1.4.3.1 | B45: MONITOREO DE CALIDAD AMBIENTAL | G45: pto | H45: =ROUND('Obras provisionales'!H51,2) -> 6 | I45: =ROUND('APU PROVISIONALES'!J423,2) -> 1915.25 | J45: =ROUND(H45*I45,2) -> 11491.5
A46: 1.4.4 | B46: PROGRAMA DE MANEJO DE RESIDUOS SÓLIDOS | J46: =J47+J51+J56 -> 10420.44
A47: 1.4.4.1 | B47: Manejo de residuos peligrosos | J47: =SUM(J48:J50) -> 5630.85
A48: 1.4.4.1.1 | B48: ADQUISICIÓN DE CONTENEDORES PARA RESIDUOS PELIGROSOS | G48: und | H48: =ROUND('Obras provisionales'!H54,2) -> 3 | I48: =ROUND('APU PROVISIONALES'!J430,2) -> 167.04 | J48: =ROUND(H48*I48,2) -> 501.12
A49: 1.4.4.1.2 | B49: RECOLECCIÓN DE RESIDUOS PELIGROSOS | G49: m3 | H49: =ROUND('Obras provisionales'!H55,2) -> 9 | I49: =ROUND('APU PROVISIONALES'!J443,2) -> 163.19 | J49: =ROUND(H49*I49,2) -> 1468.71
A50: 1.4.4.1.3 | B50: ELIMINACIÓN Y TRANSPORTE DE RESIDUOS PELIGROSOS | G50: m3 | H50: =ROUND('Obras provisionales'!H56,2) -> 9 | I50: =ROUND('APU PROVISIONALES'!J461,2) -> 406.78 | J50: =ROUND(H50*I50,2) -> 3661.02
A51: 1.4.4.2 | B51: Manejo de residuos no peligrosos | J51: =SUM(J52:J55) -> 3837.97
A52: 1.4.4.2.1 | B52: ACONDICIONAMIENTO | G52: m2 | H52: =ROUND('Obras provisionales'!H58,2) -> 1 | I52: =ROUND('APU PROVISIONALES'!J468,2) -> 80.2 | J52: =ROUND(H52*I52,2) -> 80.2
A53: 1.4.4.2.2 | B53: ADQUISICIÓN DE CONTENEDORES PARA RESIDUOS NO PELIGROSOS | G53: und | H53: =ROUND('Obras provisionales'!H59,2) -> 15 | I53: =ROUND('APU PROVISIONALES'!J488,2) -> 148.27 | J53: =ROUND(H53*I53,2) -> 2224.05
A54: 1.4.4.2.3 | B54: RECOLECCIÓN DE RESIDUOS NO PELIGROSOS | G54: m3 | H54: =ROUND('Obras provisionales'!H60,2) -> 24 | I54: =ROUND('APU PROVISIONALES'!J501,2) -> 43.22 | J54: =ROUND(H54*I54,2) -> 1037.28
A55: 1.4.4.2.4 | B55: DISPOSICIÓN FINAL DE RESIDUOS NO PELIGROSOS | G55: m3 | H55: =ROUND('Obras provisionales'!H61,2) -> 36 | I55: =ROUND('APU PROVISIONALES'!J519,2) -> 13.79 | J55: =ROUND(H55*I55,2) -> 496.44
A56: 1.4.4.3 | B56: Manejo de residuos valorizables | J56: =SUM(J57:J58) -> 951.62
A57: 1.4.4.3.1 | B57: CLASIFICACIÓN DE RESIDUOS VALORIZABLES | G57: mes | H57: =ROUND('Obras provisionales'!H63,2) -> 12 | I57: =ROUND('APU PROVISIONALES'!J534,2) -> 68.27 | J57: =ROUND(H57*I57,2) -> 819.24
A58: 1.4.4.3.2 | B58: DISPOSICIÓN FINAL | G58: m3 | H58: =ROUND('Obras provisionales'!H64,2) -> 9.6 | I58: =ROUND('APU PROVISIONALES'!J548,2) -> 13.79 | J58: =ROUND(H58*I58,2) -> 132.38
A59: 1.4.5 | B59: PROGRAMA DE CONTINGENCIA | J59: =SUM(J60) -> 402.01
A60: 1.4.5.1 | B60: CONTINGENCIA ANTE DERRAMES | G60: und | H60: =ROUND('Obras provisionales'!H66,2) -> 1 | I60: =ROUND('APU PROVISIONALES'!J563,2) -> 402.01 | J60: =ROUND(H60*I60,2) -> 402.01
A61: 1.4.6 | B61: PROGRAMA DE CIERRE Y ABANDONO | J61: =SUM(J62:J65) -> 230.55
A62: 1.4.6.1 | B62: MANEJO DE RESIDUOS DE DESINSTALACIÓN | G62: m2 | H62: =ROUND('Obras provisionales'!H68,2) -> 20 | I62: =ROUND('APU PROVISIONALES'!J579,2) -> 6.96 | J62: =ROUND(H62*I62,2) -> 139.2
A63: 1.4.6.2 | B63: TRASLADO Y DISPOSICIÓN FINAL DE RESIDUOS | G63: m3 | H63: =ROUND('Obras provisionales'!H69,2) -> 1.5 | I63: =ROUND('APU PROVISIONALES'!J591,2) -> 24.08 | J63: =ROUND(H63*I63,2) -> 36.12
A64: 1.4.6.3 | B64: REHABILITACIÓN DE SUELOS AFECTADOS | G64: m2 | H64: =ROUND('Obras provisionales'!H70,2) -> 3 | I64: =ROUND('APU PROVISIONALES'!J607,2) -> 7.69 | J64: =ROUND(H64*I64,2) -> 23.07
A65: 1.4.6.4 | B65: NIVELACIÓN Y COMPACTACIÓN | G65: m2 | H65: =ROUND('Obras provisionales'!H71,2) -> 4 | I65: =ROUND('APU PROVISIONALES'!J621,2) -> 8.04 | J65: =ROUND(H65*I65,2) -> 32.16
A66: 1.5 | B66: DEMOLICIONES | J66: =J67+J75 -> 2418.39
A67: 1.5.1 | B67: DESMONTAJE | J67: =SUM(J68:J74) -> 1026.37
A68: 1.5.1.1 | B68: DESMONTAJE DE TECHO DE TEJA ANDINA + ESTRUCTURA DE MADERA | G68: m2 | H68: =IF('Datos iniciales '!$E$3="SI",ROUND('Obras provisionales'!H74,2),0) -> 10.2 | I68: =ROUND('APU PROVISIONALES'!J636,2) -> 16.07 | J68: =ROUND(H68*I68,2) -> 163.91
A69: 1.5.1.2 | B69: DESMONTAJE DE TECHO DE CALAMINA + ESTRUCTURA DE MADERA | G69: m2 | H69: =IF('Datos iniciales '!$E$3="SI",ROUND('Obras provisionales'!H75,2),0) -> 15.6 | I69: =ROUND('APU PROVISIONALES'!J643,2) -> 20.09 | J69: =ROUND(H69*I69,2) -> 313.4
A70: 1.5.1.3 | B70: DESMONTAJE DE CIELORRASO EXISTENTE | G70: m2 | H70: =IF('Datos iniciales '!$E$3="SI",ROUND('Obras provisionales'!H76,2),0) -> 14.1 | I70: =ROUND('APU PROVISIONALES'!J650,2) -> 20.09 | J70: =ROUND(H70*I70,2) -> 283.27
A71: 1.5.1.4 | B71: DESMONTAJE DE PUERTAS METÁLICAS EXISTENTES | G71: m2 | H71: =IF('Datos iniciales '!$E$3="SI",ROUND('Obras provisionales'!H77,2),0) -> 0.3 | I71: =ROUND('APU PROVISIONALES'!J657,2) -> 20.09 | J71: =ROUND(H71*I71,2) -> 6.03
A72: 1.5.1.5 | B72: DESMONTAJE DE PUERTAS DE MADERA EXISTENTES | G72: m2 | H72: =IF('Datos iniciales '!$E$3="SI",ROUND('Obras provisionales'!H78,2),0) -> 0.69 | I72: =ROUND('APU PROVISIONALES'!J664,2) -> 20.09 | J72: =ROUND(H72*I72,2) -> 13.86
A73: 1.5.1.6 | B73: DESMONTAJE DE VENTANAS EXISTENTES | G73: m2 | H73: =IF('Datos iniciales '!$E$3="SI",ROUND('Obras provisionales'!H79,2),0) -> 1.14 | I73: =ROUND('APU PROVISIONALES'!J671,2) -> 20.09 | J73: =ROUND(H73*I73,2) -> 22.9
A74: 1.5.1.7 | B74: DESMONTAJE DE PISO DE MADERA | G74: m2 | H74: =IF('Datos iniciales '!$E$3="SI",ROUND('Obras provisionales'!H80,2),0) -> 11.1 | I74: =ROUND('APU PROVISIONALES'!J678,2) -> 20.09 | J74: =ROUND(H74*I74,2) -> 223
A75: 1.5.2 | B75: DEMOLICIONES | J75: =SUM(J76:J77) -> 1392.02
A76: 1.5.2.1 | B76: DEMOLICIÓN MANUAL DE PISO DE CONCRETO | G76: m2 | H76: =IF('Datos iniciales '!$E$3="SI",ROUND('Obras provisionales'!H82,2),0) -> 15.9 | I76: =ROUND('APU PROVISIONALES'!J685,2) -> 54.2 | J76: =ROUND(H76*I76,2) -> 861.78
A77: 1.5.2.2 | B77: DEMOLICIÓN MANUAL DE MURO DE TAPIAL | G77: m3 | H77: =IF('Datos iniciales '!$E$3="SI",ROUND('Obras provisionales'!H83,2),0) -> 13.2 | I77: =ROUND('APU PROVISIONALES'!J692,2) -> 40.17 | J77: =ROUND(H77*I77,2) -> 530.24

Sheet APU PROVISIONALES
A2: Partida | B2: =PROVISIONALES!A6 -> 1.1.1.1 | C2: OFICINAS DE RESIDENCIA Y SUPERVISIÓN
A3: Rendimiento m2/día | B3: m2/dia | C3: M.O | D3: 25 | E3: EQ | F3: =D3 -> 25 | G3: Costo unitario directo | I3: und | J3: =J10++J22+J25 -> 158.9
A4: Código | B4: Descripción Recurso | F4: Unidad | G4: Cuadrilla | H4: Cantidad | I4: Precio (S/.) | J4: Parcial (S/.)
B5: Mano de Obra
B7: OPERARIO | F7: hh | G7: 1 | H7: =ROUND(G7*8/$D$3,4) -> 0.32 | I7: 28.94 | J7: =ROUND(H7*I7,2) -> 9.26 | K7: 47
B8: OFICIAL | F8: hh | G8: 1 | H8: =ROUND(G8*8/$D$3,4) -> 0.32 | I8: 22.66 | J8: =ROUND(H8*I8,2) -> 7.25 | K8: 47
B9: PEON | F9: hh | G9: 3 | H9: =ROUND(G9*8/$D$3,4) -> 0.96 | I9: 20.51 | J9: =ROUND(H9*I9,2) -> 19.69 | K9: 47
J10: =ROUND(SUM(J6:J9),2) -> 36.2
B11: Materiales
B12: ALAMBRE NEGRO RECOCIDO BWG N 16 | F12: kg | H12: 1.25 | I12: 2.64 | J12: =ROUND(H12*I12,2) -> 3.3 | K12: 2
B13: CALAMINA | F13: pln | H13: 1.8 | I13: 14.15 | J13: =ROUND(H13*I13,2) -> 25.47 | K13: 56
B14: CERRADURA CLÁSICA ADOSADA BK 233 | F14: und | H14: 0.2 | I14: 55 | J14: =ROUND(H14*I14,2) -> 11 | K14: 26
B15: CLAVOS PARA CALAMINA | F15: kg | H15: 0.06 | I15: 10.93 | J15: =ROUND(H15*I15,2) -> 0.66 | K15: 2
B16: CLAVO C/CABEZA P/CONSTRUCCION D.PROMEDIO | F16: kg | H16: 0.071 | I16: 5.51 | J16: =ROUND(H16*I16,2) -> 0.39 | K16: 2
B17: HORMIGON | F17: m3 | H17: 0.19 | I17: 70.92 | J17: =ROUND(H17*I17,2) -> 13.47 | K17: 38
B18: TRIPLAY ENCHAPE CEDRO 4' x 8' x 4mm | F18: pln | H18: 0.53 | I18: 27.88 | J18: =ROUND(H18*I18,2) -> 14.78 | K18: 44
B19: VIDRIO CLARO 4MM | F19: p2 | H19: 0.2374 | I19: 32.2 | J19: =ROUND(H19*I19,2) -> 7.64 | K19: 30
B20: CEMENTO PORTLAND TIPO I (42.5 kg) | F20: bls | H20: 1.092 | I20: 24.52 | J20: =ROUND(H20*I20,2) -> 26.78 | K20: 21
B21: MADERA TORNILLO | F21: p2 | H21: 3 | I21: 5.8 | J21: =ROUND(H21*I21,2) -> 17.4 | K21: 43
J22: =ROUND(SUM(J12:J21),2) -> 120.89
B23: Equipos
B24: HERRAMIENTAS MANUALES | F24: %mo | H24: 5 | I24: =ROUND(J10,2) -> 36.2 | J24: =ROUND(H24%*I24,2) -> 1.81 | K24: 37
J25: =ROUND(SUM(J24),2) -> 1.81
A27: Partida | B27: =PROVISIONALES!A7 -> 1.1.1.2 | C27: ALMACENES DE OBRA
A28: Rendimiento m2/día | B28: m2/dia | C28: M.O | D28: 40 | E28: EQ | F28: =D28 -> 40 | G28: Costo unitario directo | I28: und | J28: =J34++J46+J49 -> 144.65
A29: Código | B29: Descripción Recurso | F29: Unidad | G29: Cuadrilla | H29: Cantidad | I29: Precio (S/.) | J29: Parcial (S/.)
B30: Mano de Obra
B31: OPERARIO | F31: hh | G31: 1 | H31: =ROUND(G31*8/$D$28,4) -> 0.2 | I31: 28.94 | J31: =ROUND(H31*I31,2) -> 5.79 | K31: 47
B32: OFICIAL | F32: hh | G32: 1 | H32: =ROUND(G32*8/$D$28,4) -> 0.2 | I32: 22.66 | J32: =ROUND(H32*I32,2) -> 4.53 | K32: 47
B33: PEON | F33: hh | G33: 3 | H33: =ROUND(G33*8/$D$28,4) -> 0.6 | I33: 20.51 | J33: =ROUND(H33*I33,2) -> 12.31 | K33: 47
J34: =ROUND(SUM(J31:J33),2) -> 22.63
B35: Materiales
B36: ALAMBRE NEGRO RECOCIDO BWG N 16 | F36: kg | H36: 1.25 | I36: 2.64 | J36: =ROUND(H36*I36,2) -> 3.3 | K36: 2
B37: CALAMINA | F37: pln | H37: 1.8 | I37: 14.15 | J37: =ROUND(H37*I37,2) -> 25.47 | K37: 56
B38: CERRADURA CLÁSICA ADOSADA BK 233 | F38: und | H38: 0.2 | I38: 55 | J38: =ROUND(H38*I38,2) -> 11 | K38: 26
B39: CLAVOS PARA CALAMINA | F39: kg | H39: 0.06 | I39: 10.93 | J39: =ROUND(H39*I39,2) -> 0.66 | K39: 2
B40: CLAVO C/CABEZA P/CONSTRUCCION D.PROMEDIO | F40: kg | H40: 0.071 | I40: 5.51 | J40: =ROUND(H40*I40,2) -> 0.39 | K40: 2
B41: HORMIGON | F41: m3 | H41: 0.19 | I41: 70.92 | J41: =ROUND(H41*I41,2) -> 13.47 | K41: 38
B42: TRIPLAY ENCHAPE CEDRO 4' x 8' x 4mm | F42: pln | H42: 0.53 | I42: 27.88 | J42: =ROUND(H42*I42,2) -> 14.78 | K42: 44
B43: VIDRIO CLARO 4MM | F43: p2 | H43: 0.2374 | I43: 32.2 | J43: =ROUND(H43*I43,2) -> 7.64 | K43: 30
B44: CEMENTO PORTLAND TIPO I (42.5 kg) | F44: bls | H44: 1.092 | I44: 24.52 | J44: =ROUND(H44*I44,2) -> 26.78 | K44: 21
B45: MADERA TORNILLO | F45: p2 | H45: 3 | I45: 5.8 | J45: =ROUND(H45*I45,2) -> 17.4 | K45: 43
J46: =ROUND(SUM(J36:J45),2) -> 120.89
B47: Equipos
B48: HERRAMIENTAS MANUALES | F48: %mo | H48: 5 | I48: =ROUND(J34,2) -> 22.63 | J48: =ROUND(H48%*I48,2) -> 1.13 | K48: 37
J49: =ROUND(SUM(J48),2) -> 1.13
A51: Partida | B51: =PROVISIONALES!A8 -> 1.1.1.3 | C51: CASETAS DE GUARDIANÍA
A52: Rendimiento m2/día | B52: m2/dia | C52: M.O | D52: 35 | E52: EQ | F52: =D52 -> 35 | G52: Costo unitario directo | I52: und | J52: =J58++J70+J73 -> 148.04
A53: Código | B53: Descripción Recurso | F53: Unidad | G53: Cuadrilla | H53: Cantidad | I53: Precio (S/.) | J53: Parcial (S/.)
B54: Mano de Obra
B55: OPERARIO | F55: hh | G55: 1 | H55: =ROUND(G55*8/$D$52,4) -> 0.2286 | I55: 28.94 | J55: =ROUND(H55*I55,2) -> 6.62 | K55: 47
B56: OFICIAL | F56: hh | G56: 1 | H56: =ROUND(G56*8/$D$52,4) -> 0.2286 | I56: 22.66 | J56: =ROUND(H56*I56,2) -> 5.18 | K56: 47
B57: PEON | F57: hh | G57: 3 | H57: =ROUND(G57*8/$D$52,4) -> 0.6857 | I57: 20.51 | J57: =ROUND(H57*I57,2) -> 14.06 | K57: 47
J58: =ROUND(SUM(J55:J57),2) -> 25.86
B59: Materiales
B60: ALAMBRE NEGRO RECOCIDO BWG N 16 | F60: kg | H60: 1.25 | I60: 2.64 | J60: =ROUND(H60*I60,2) -> 3.3 | K60: 2
B61: CALAMINA | F61: pln | H61: 1.8 | I61: 14.15 | J61: =ROUND(H61*I61,2) -> 25.47 | K61: 56
B62: CERRADURA CLÁSICA ADOSADA BK 233 | F62: und | H62: 0.2 | I62: 55 | J62: =ROUND(H62*I62,2) -> 11 | K62: 26
B63: CLAVOS PARA CALAMINA | F63: kg | H63: 0.06 | I63: 10.93 | J63: =ROUND(H63*I63,2) -> 0.66 | K63: 2
B64: CLAVO C/CABEZA P/CONSTRUCCION D.PROMEDIO | F64: kg | H64: 0.071 | I64: 5.51 | J64: =ROUND(H64*I64,2) -> 0.39 | K64: 2
B65: HORMIGON | F65: m3 | H65: 0.19 | I65: 70.92 | J65: =ROUND(H65*I65,2) -> 13.47 | K65: 38
B66: TRIPLAY ENCHAPE CEDRO 4' x 8' x 4mm | F66: pln | H66: 0.53 | I66: 27.88 | J66: =ROUND(H66*I66,2) -> 14.78 | K66: 44
B67: VIDRIO CLARO 4MM | F67: p2 | H67: 0.2374 | I67: 32.2 | J67: =ROUND(H67*I67,2) -> 7.64 | K67: 30
B68: CEMENTO PORTLAND TIPO I (42.5 kg) | F68: bls | H68: 1.092 | I68: 24.52 | J68: =ROUND(H68*I68,2) -> 26.78 | K68: 21
B69: MADERA TORNILLO | F69: p2 | H69: 3 | I69: 5.8 | J69: =ROUND(H69*I69,2) -> 17.4 | K69: 43
J70: =ROUND(SUM(J60:J69),2) -> 120.89
B71: Equipos
B72: HERRAMIENTAS MANUALES | F72: %mo | H72: 5 | I72: =ROUND(J58,2) -> 25.86 | J72: =ROUND(H72%*I72,2) -> 1.29 | K72: 37
J73: =ROUND(SUM(J72),2) -> 1.29
A75: Partida | B75: =PROVISIONALES!A9 -> 1.1.1.4 | C75: COMEDOR PARA PERSONAL DE OBRA
A76: Rendimiento m2/día | B76: m2/dia | C76: M.O | D76: 30 | E76: EQ | F76: =D76 -> 30 | G76: Costo unitario directo | I76: und | J76: =J82+J94+J97 -> 152.57
A77: Código | B77: Descripción Recurso | F77: Unidad | G77: Cuadrilla | H77: Cantidad | I77: Precio (S/.) | J77: Parcial (S/.)
B78: Mano de Obra
B79: OPERARIO | F79: hh | G79: 1 | H79: =ROUND(G79*8/$D$76,4) -> 0.2667 | I79: 28.94 | J79: =ROUND(H79*I79,2) -> 7.72 | K79: 47
B80: OFICIAL | F80: hh | G80: 1 | H80: =ROUND(G80*8/$D$76,4) -> 0.2667 | I80: 22.66 | J80: =ROUND(H80*I80,2) -> 6.04 | K80: 47
B81: PEON | F81: hh | G81: 3 | H81: =ROUND(G81*8/$D$76,4) -> 0.8 | I81: 20.51 | J81: =ROUND(H81*I81,2) -> 16.41 | K81: 47
J82: =ROUND(SUM(J79:J81),2) -> 30.17
B83: Materiales
B84: ALAMBRE NEGRO RECOCIDO BWG N 16 | F84: kg | H84: 1.25 | I84: 2.64 | J84: =ROUND(H84*I84,2) -> 3.3 | K84: 2
B85: CALAMINA | F85: pln | H85: 1.8 | I85: 14.15 | J85: =ROUND(H85*I85,2) -> 25.47 | K85: 56
B86: CERRADURA CLÁSICA ADOSADA BK 233 | F86: und | H86: 0.2 | I86: 55 | J86: =ROUND(H86*I86,2) -> 11 | K86: 26
B87: CLAVOS PARA CALAMINA | F87: kg | H87: 0.06 | I87: 10.93 | J87: =ROUND(H87*I87,2) -> 0.66 | K87: 2
B88: CLAVO C/CABEZA P/CONSTRUCCION D.PROMEDIO | F88: kg | H88: 0.071 | I88: 5.51 | J88: =ROUND(H88*I88,2) -> 0.39 | K88: 2
B89: HORMIGON | F89: m3 | H89: 0.19 | I89: 70.92 | J89: =ROUND(H89*I89,2) -> 13.47 | K89: 38
B90: TRIPLAY ENCHAPE CEDRO 4' x 8' x 4mm | F90: pln | H90: 0.53 | I90: 27.88 | J90: =ROUND(H90*I90,2) -> 14.78 | K90: 44
B91: VIDRIO CLARO 4MM | F91: p2 | H91: 0.2374 | I91: 32.2 | J91: =ROUND(H91*I91,2) -> 7.64 | K91: 30
B92: CEMENTO PORTLAND TIPO I (42.5 kg) | F92: bls | H92: 1.092 | I92: 24.52 | J92: =ROUND(H92*I92,2) -> 26.78 | K92: 21
B93: MADERA TORNILLO | F93: p2 | H93: 3 | I93: 5.8 | J93: =ROUND(H93*I93,2) -> 17.4 | K93: 43
J94: =ROUND(SUM(J84:J93),2) -> 120.89
B95: Equipos
B96: HERRAMIENTAS MANUALES | F96: %mo | H96: 5 | I96: =ROUND(J82,2) -> 30.17 | J96: =ROUND(H96%*I96,2) -> 1.51 | K96: 37
J97: =ROUND(SUM(J96),2) -> 1.51
A99: Partida | B99: =PROVISIONALES!A10 -> 1.1.1.5 | C99: VESTUARIO PARA PERSONAL DE OBRA
A100: Rendimiento m2/día | B100: m2/dia | C100: M.O | D100: 32 | E100: EQ | F100: =D100 -> 32 | G100: Costo unitario directo | I100: und | J100: =J106++J118+J121 -> 206.2
A101: Código | B101: Descripción Recurso | F101: Unidad | G101: Cuadrilla | H101: Cantidad | I101: Precio (S/.) | J101: Parcial (S/.)
B102: Mano de Obra
B103: OPERARIO | F103: hh | G103: 1 | H103: =ROUND(G103*8/$D$100,4) -> 0.25 | I103: 28.94 | J103: =ROUND(H103*I103,2) -> 7.24 | K103: 47
B104: OFICIAL | F104: hh | G104: 1 | H104: =ROUND(G104*8/$D$100,4) -> 0.25 | I104: 22.66 | J104: =ROUND(H104*I104,2) -> 5.67 | K104: 47
B105: PEON | F105: hh | G105: 3 | H105: =ROUND(G105*8/$D$100,4) -> 0.75 | I105: 20.51 | J105: =ROUND(H105*I105,2) -> 15.38 | K105: 47
J106: =ROUND(SUM(J103:J105),2) -> 28.29
...

Sheet ESTRUCTURA
G2: Unidad | H2: Metrado | I2: C.U | J2: Parcial | K2: Total
A3: 2 | B3: ESTRUCTURA | K3: =J4+J14+J23+J72 -> 1179659.2
A4: 2.01 | B4: MOVIMIENTO DE TIERRAS | J4: =SUM(J5:J13) -> 138561.14
A5: 02.01.01 | B5: EXCAVACIÓN LOCALIZADA CON MAQUINARIA | G5: m3 | H5: =ROUND('Cimentación 1 piso'!H9+'Cimentación 2 pisos '!H9+'Cimentación 3 pisos'!H9+'Cimentación 4 pisos'!H9+'Platea de Cimentacion'!H9,2) -> 2961.86 | I5: =ROUND('APU ESTRUCTURAS'!J2,2) -> 8.46 | J5: =ROUND(H5*I5,2) -> 25057.34
A6: 02.01.02 | B6: EXCAVACIÓN MANUAL | G6: m3 | H6: =ROUND('Cimentación 1 piso'!H10+'Cimentación 2 pisos '!H10+'Cimentación 3 pisos'!H10+'Cimentación 4 pisos'!H10+'Platea de Cimentacion'!H10,2) -> 38.29 | I6: =ROUND('APU ESTRUCTURAS'!J18,2) -> 49.41 | J6: =ROUND(H6*I6,2) -> 1891.91
A7: 02.01.03 | B7: RELLENO COMPACTADO C/PLANCHA COMPACTADORA C/MATERIAL DE PRÉSTAMO | G7: m3 | H7: =ROUND('Cimentación 1 piso'!H11+'Cimentación 2 pisos '!H11+'Cimentación 3 pisos'!H11+'Cimentación 4 pisos'!H11+'Platea de Cimentacion'!H11,2) -> 176.72 | I7: =ROUND('APU ESTRUCTURAS'!J29,2) -> 66.23 | J7: =ROUND(H7*I7,2) -> 11704.17
A8: 02.01.04 | B8: RELLENO COMPACTADO C/PLANCHA COMPACTADORA C/MATERIAL PROPIO | G8: m3 | H8: =ROUND('Cimentación 1 piso'!H12+'Cimentación 2 pisos '!H12+'Cimentación 3 pisos'!H12+'Cimentación 4 pisos'!H12+'Platea de Cimentacion'!H12,2) -> 1827.84 | I8: =ROUND('APU ESTRUCTURAS'!J46,2) -> 19.77 | J8: =ROUND(H8*I8,2) -> 36136.4
A9: 02.01.05 | B9: FORMACION Y COMPACTACION DE SUBRASANTE | G9: m2 | H9: =ROUND('Cimentación 1 piso'!H13+'Cimentación 2 pisos '!H13+'Cimentación 3 pisos'!H13+'Cimentación 4 pisos'!H13+'Platea de Cimentacion'!H13,2) -> 1332.21 | I9: =ROUND('APU ESTRUCTURAS'!J63,2) -> 7.99 | J9: =ROUND(H9*I9,2) -> 10644.36
A10: 02.01.06 | B10: ACARREO DE MATERIAL EXCEDENTE | G10: m2 | H10: =ROUND('Cimentación 1 piso'!H14+'Cimentación 2 pisos '!H14+'Cimentación 3 pisos'!H14+'Cimentación 4 pisos'!H14+'Platea de Cimentacion'!H14,2) -> 1446.64 | I10: =ROUND('APU ESTRUCTURAS'!J78,2) -> 12.11 | J10: =ROUND(H10*I10,2) -> 17518.81
A11: 02.01.07 | B11: ELIMINACIÓN DE MATERIAL EXCEDENTE HASTA D=10 KM | G11: m3 | H11: =ROUND('Cimentación 1 piso'!H15+'Cimentación 2 pisos '!H15+'Cimentación 3 pisos'!H15+'Cimentación 4 pisos'!H15+'Platea de Cimentacion'!H15,2) -> 1446.64 | I11: =ROUND('APU ESTRUCTURAS'!J89,2) -> 22.88 | J11: =ROUND(H11*I11,2) -> 33099.12
A12: 02.01.08 | B12: COMPACTACION DE SUBRASANTE LOSA DEPORTIVA | G12: m3 | H12: =ROUND('Obras exteriores '!D11+'Obras exteriores '!D27+'Obras exteriores '!D45,2) -> 60 | I12: =ROUND('APU ESTRUCTURAS'!J102,2) -> 7.99 | J12: =ROUND(H12*I12,2) -> 479.4
A13: 02.01.09 | B13: AFIRMADO DE e=0.30m PARA LOSA DEPORTIVA | G13: m3 | H13: =ROUND('Obras exteriores '!D12+'Obras exteriores '!D28+'Obras exteriores '!D46+'Obras exteriores '!D59,2) -> 26.4 | I13: =ROUND('APU ESTRUCTURAS'!J117,2) -> 76.88 | J13: =ROUND(H13*I13,2) -> 2029.63
A14: 2.02 | B14: CONCRETO SIMPLE | J14: =J15+J17+J19+J21 -> 177094.62
A15: 02.02.01 | B15: CONCRETO CICLOPEO -PLATEA DE CIMENTACION | J15: =SUM(J16) -> 23735
A16: 02.02.01.01 | B16: CONCRETO CICLOPEO F’C=100 KG/CM² + PIEDRA GRANDE DE 8" E=0.80 M | G16: m2 | H16: =ROUND('Platea de Cimentacion'!H17,2) -> 100 | I16: =ROUND('APU ESTRUCTURAS'!J139,2) -> 237.35 | J16: =ROUND(H16*I16,2) -> 23735
A17: 02.02.02 | B17: FALSA ZAPATA | J17: =SUM(J18) -> 132037.81
A18: 02.02.02.01 | B18: FALSA ZAPATA F’C=100 KG/CM² + PIEDRA GRANDE DE 8" E=0.80 M | G18: m2 | H18: =ROUND('Cimentación 1 piso'!H17+'Cimentación 2 pisos '!H17+'Cimentación 3 pisos'!H17+'Cimentación 4 pisos'!H17+Escalera!D7,2) -> 556.3 | I18: =ROUND('APU ESTRUCTURAS'!J161,2) -> 237.35 | J18: =ROUND(H18*I18,2) -> 132037.81
A19: 02.02.03 | B19: FALSO PISO | J19: =SUM(J20) -> 20540.99
A20: 02.02.03.01 | B20: FALSO PISO E = 4" FC = 175 KG/CM2 | G20: m2 | H20: =ROUND('Cimentación 1 piso'!H19+'Cimentación 2 pisos '!H19+'Cimentación 3 pisos'!H19+'Cimentación 4 pisos'!H19+Escalera!D8,2) -> 524.54 | I20: =ROUND('APU ESTRUCTURAS'!J183,2) -> 39.16 | J20: =ROUND(H20*I20,2) -> 20540.99
A21: 02.02.04 | B21: SOLADOS | J21: =SUM(J22) -> 780.82
A22: 02.02.04.01 | B22: SOLADO PARA VIGA DE CIMENTACIÓN FC=100 KG/CM2 E=4" | G22: m2 | H22: =ROUND('Cimentación 1 piso'!H21+'Cimentación 2 pisos '!H21+'Cimentación 3 pisos'!H21+'Cimentación 4 pisos'!H21,2) -> 29.31 | I22: =ROUND('APU ESTRUCTURAS'!J202,2) -> 26.64 | J22: =ROUND(H22*I22,2) -> 780.82
A23: 2.03 | B23: CONCRETO ARMADO | J23: =J24+J27+J31+J35+J39+J43+J47+J51+J55+J60+J64+J68 -> 732208.41
A24: 02.03.01 | B24: ZAPATAS | J24: =SUM(J25:J26) -> 219679.09
A25: 02.03.01.01 | B25: ZAPATAS.- CONCRETO f'c=210 Kg/cm2 | G25: m3 | H25: =ROUND('Cimentación 1 piso'!H24+'Cimentación 2 pisos '!H24+'Cimentación 3 pisos'!H24+'Cimentación 4 pisos'!H24,2) -> 355.99 | I25: =ROUND('APU ESTRUCTURAS'!J221,2) -> 424.08 | J25: =ROUND(H25*I25,2) -> 150968.24
A26: 02.03.01.02 | B26: ZAPATAS.- ACERO DE REFUERZO fy=4,200 Kg/cm2 | G26: kg | H26: =ROUND('Cimentación 1 piso'!H25+'Cimentación 2 pisos '!H25+'Cimentación 3 pisos'!H25+'Cimentación 4 pisos'!H25,2) -> 12402.68 | I26: =ROUND('APU ESTRUCTURAS'!J244,2) -> 5.54 | J26: =ROUND(H26*I26,2) -> 68710.85
A27: 02.03.02 | B27: PLATEA DE CIMENTACION | J27: =SUM(J28:J30) -> 108928.3
A28: 02.03.02.01 | B28: PLATEA DE CIMENTACION. – CONCRETO f'c=210 | G28: m3 | H28: =ROUND('Platea de Cimentacion'!H24,2) -> 60 | I28: =ROUND('APU ESTRUCTURAS'!J260,2) -> 424.08 | J28: =ROUND(H28*I28,2) -> 25444.8
A29: 02.03.02.02 | B29: PLATEA DE CIMENTACION. – ENCOFRADO Y DESENCOFRADO | G29: m2 | H29: =ROUND('Platea de Cimentacion'!H25,2) -> 50 | I29: =ROUND('APU ESTRUCTURAS'!J282,2) -> 74.15 | J29: =ROUND(H29*I29,2) -> 3707.5
A30: 02.03.02.03 | B30: PLATEA DE CIMENTACION.- ACERO DE REFUERZO fy=4,200 Kg/cm2 | G30: kg | H30: =ROUND('Platea de Cimentacion'!H26,2) -> 14400 | I30: =ROUND('APU ESTRUCTURAS'!J298,2) -> 5.54 | J30: =ROUND(H30*I30,2) -> 79776
A31: 02.03.03 | B31: SOBRECIMIENTOS ARMADO | J31: =SUM(J32:J34) -> 85022.38
A32: 02.03.03.01 | B32: SOBRECIMIENTO REFORZADO.- CONCRETO 210 KG/CM2 | G32: m3 | H32: =ROUND('Cimentación 1 piso'!H27+'Cimentación 2 pisos '!H27+'Cimentación 3 pisos'!H27+'Cimentación 4 pisos'!H27+'Platea de Cimentacion'!H28,2) -> 80.78 | I32: =ROUND('APU ESTRUCTURAS'!J314,2) -> 435.71 | J32: =ROUND(H32*I32,2) -> 35196.65
A33: 02.03.03.02 | B33: SOBRECIMIENTOS REFORZADOS.- ENCOFRADO Y DESENCOFRADO | G33: m2 | H33: =ROUND('Cimentación 1 piso'!H28+'Cimentación 2 pisos '!H28+'Cimentación 3 pisos'!H28+'Cimentación 4 pisos'!H28+'Platea de Cimentacion'!H29,2) -> 443.33 | I33: =ROUND('APU ESTRUCTURAS'!J336,2) -> 63.25 | J33: =ROUND(H33*I33,2) -> 28040.62
A34: 02.03.03.03 | B34: SOBRECIMIENTO ARMADO.- ACERO DE REFUERZO fy=4,200 Kg/cm2 | G34: kg | H34: =ROUND('Cimentación 1 piso'!H29+'Cimentación 2 pisos '!H29+'Cimentación 3 pisos'!H29+'Cimentación 4 pisos'!H29+'Platea de Cimentacion'!H30,2) -> 3932.33 | I34: =ROUND('APU ESTRUCTURAS'!J352,2) -> 5.54 | J34: =ROUND(H34*I34,2) -> 21785.11
A35: 02.03.04 | B35: VIGAS DE CIMENTACIÓN | J35: =SUM(J36:J38) -> 53867.06
A36: 02.03.04.01 | B36: VIGAS DE CIMENTACIÓN.- CONCRETO 210 KG/CM2 | G36: m3 | H36: =ROUND('Cimentación 1 piso'!H31+'Cimentación 2 pisos '!H31+'Cimentación 3 pisos'!H31+'Cimentación 4 pisos'!H31+Escalera!D11,2) -> 45.93 | I36: =ROUND('APU ESTRUCTURAS'!J370,2) -> 421.12 | J36: =ROUND(H36*I36,2) -> 19342.04
A37: 02.03.04.02 | B37: VIGAS DE CIMENTACIÓN.- ENCOFRADO Y DESENCOFRADO | G37: m2 | H37: =ROUND('Cimentación 1 piso'!H32+'Cimentación 2 pisos '!H32+'Cimentación 3 pisos'!H32+'Cimentación 4 pisos'!H32+Escalera!D12,2) -> 234.31 | I37: =ROUND('APU ESTRUCTURAS'!J391,2) -> 42.26 | J37: =ROUND(H37*I37,2) -> 9901.94
A38: 02.03.04.03 | B38: VIGAS DE CIMENTACIÓN.- ACERO DE REFUERZO fy=4,200 Kg/cm2 | G38: kg | H38: =ROUND('Cimentación 1 piso'!H33+'Cimentación 2 pisos '!H33+'Cimentación 3 pisos'!H33+'Cimentación 4 pisos'!H33+Escalera!D13,2) -> 4444.6 | I38: =ROUND('APU ESTRUCTURAS'!J407,2) -> 5.54 | J38: =ROUND(H38*I38,2) -> 24623.08
A39: 02.03.05 | B39: COLUMNAS | J39: =SUM(J40:J42) -> 80734.44
A40: 02.03.05.01 | B40: COLUMNAS-CONCRETO fc=210kg/cm2 | G40: m3 | H40: =ROUND('Estructura 1'!G6,2) -> 48.04 | I40: =ROUND('APU ESTRUCTURAS'!J423,2) -> 399.77 | J40: =ROUND(H40*I40,2) -> 19204.95
A41: 02.03.05.02 | B41: COLUMNAS.- ENCOFRADO Y DESENCOFRADO | G41: m2 | H41: =ROUND('Estructura 1'!G7,2) -> 349.57 | I41: =ROUND('APU ESTRUCTURAS'!J444,2) -> 46.59 | J41: =ROUND(H41*I41,2) -> 16286.47
A42: 02.03.05.03 | B42: COLUMNAS.- ACERO DE REFUERZO fy=4,200 Kg/cm2 | G42: kg | H42: =ROUND('Estructura 1'!G8,2) -> 8166.61 | I42: =ROUND('APU ESTRUCTURAS'!J461,2) -> 5.54 | J42: =ROUND(H42*I42,2) -> 45243.02
A43: 02.03.06 | B43: COLUMNETAS DE CONFINAMIENTO | J43: =SUM(J44:J46) -> 11461.92
A44: 02.03.06.01 | B44: COLUMNETAS DE CONFINAMIENTO-CONCRETO fc=210kg/cm2 | G44: m3 | H44: =ROUND('Estructura 2'!G6,2) -> 7.21 | I44: =ROUND('APU ESTRUCTURAS'!J477,2) -> 356.17 | J44: =ROUND(H44*I44,2) -> 2567.99
A45: 02.03.06.02 | B45: COLUMNETAS DE CONFINAMIENTO.- ENCOFRADO Y DESENCOFRADO | G45: m2 | H45: =ROUND('Estructura 2'!G7,2) -> 122.35 | I45: =ROUND('APU ESTRUCTURAS'!J498,2) -> 46.59 | J45: =ROUND(H45*I45,2) -> 5700.29
A46: 02.03.06.03 | B46: COLUMNETAS DE CONFINAMIENTO.- ACERO DE REFUERZO fy=4,200 Kg/cm2 | G46: kg | H46: =ROUND('Estructura 2'!G8,2) -> 576.47 | I46: =ROUND('APU ESTRUCTURAS'!J515,2) -> 5.54 | J46: =ROUND(H46*I46,2) -> 3193.64
A47: 02.03.07 | B47: VIGAS | J47: =SUM(J48:J50) -> 71363.33
A48: 02.03.07.01 | B48: VIGAS.- CONCRETO fc=210kg/cm2 | G48: m3 | H48: =ROUND('Estructura 1'!G10,2) -> 50.55 | I48: =ROUND('APU ESTRUCTURAS'!J531,2) -> 390.28 | J48: =ROUND(H48*I48,2) -> 19728.65
A49: 02.03.07.02 | B49: VIGAS.- ENCOFRADO Y DESENCOFRADO | G49: m2 | H49: =ROUND('Estructura 1'!G11,2) -> 246.68 | I49: =ROUND('APU ESTRUCTURAS'!J553,2) -> 50.39 | J49: =ROUND(H49*I49,2) -> 12430.21
A50: 02.03.07.03 | B50: VIGAS.- ACERO fy=4200 kg/cm² | G50: kg | H50: =ROUND('Estructura 1'!G12,2) -> 7076.62 | I50: =ROUND('APU ESTRUCTURAS'!J569,2) -> 5.54 | J50: =ROUND(H50*I50,2) -> 39204.47
A51: 02.03.08 | B51: VIGUETAS DE CONFINAMIENTO | J51: =SUM(J52:J54) -> 3865.48
A52: 02.03.08.01 | B52: VIGUETAS DE CONFINAMIENTO.- CONCRETO fc=210kg/cm2 | G52: m3 | H52: =ROUND('Estructura 2'!G10,2) -> 2.53 | I52: =ROUND('APU ESTRUCTURAS'!J585,2) -> 348.19 | J52: =ROUND(H52*I52,2) -> 880.92
A53: 02.03.08.02 | B53: VIGUETAS DE CONFINAMIENTO.- ENCOFRADO Y DESENCOFRADO | G53: m2 | H53: =ROUND('Estructura 2'!G11,2) -> 37 | I53: =ROUND('APU ESTRUCTURAS'!J607,2) -> 50.39 | J53: =ROUND(H53*I53,2) -> 1864.43
A54: 02.03.08.03 | B54: VIGUETAS DE CONFINAMIENTO.- ACERO fy=4200 kg/cm² | G54: kg | H54: =ROUND('Estructura 2'!G12,2) -> 202.19 | I54: =ROUND('APU ESTRUCTURAS'!J623,2) -> 5.54 | J54: =ROUND(H54*I54,2) -> 1120.13
A55: 02.03.09 | B55: LOSA ALIGERADA | J55: =SUM(J56:J59) -> 46872.36
A56: 02.03.09.01 | B56: LOSA ALIGERADA - CONCRETO f'c=210 kg/cm² | G56: m3 | H56: =ROUND('Estructura 1'!G14,2) -> 35.06 | I56: =ROUND('APU ESTRUCTURAS'!J639,2) -> 394.55 | J56: =ROUND(H56*I56,2) -> 13832.92
A57: 02.03.09.02 | B57: LOSA ALIGERADA.- ENCOFRADO Y DESENCOFRADO | G57: m2 | H57: =ROUND('Estructura 1'!G15,2) -> 384.41 | I57: =ROUND('APU ESTRUCTURAS'!J664,2) -> 43.05 | J57: =ROUND(H57*I57,2) -> 16548.85
A58: 02.03.09.03 | B58: LOSA ALIGERADA.- ACERO DE REFUERZO fy=4,200 kg/cm² | G58: kg | H58: =ROUND('Estructura 1'!G16,2) -> 1577.81 | I58: =ROUND('APU ESTRUCTURAS'!J681,2) -> 5.49 | J58: =ROUND(H58*I58,2) -> 8662.18
A59: 02.03.09.04 | B59: LOSA ALIGERADA.- LADRILLO HUECO 30×30×15 cm | G59: und | H59: =ROUND('Estructura 1'!G17,2) -> 2910.19 | I59: =ROUND('APU ESTRUCTURAS'!J697,2) -> 2.69 | J59: =ROUND(H59*I59,2) -> 7828.41
A60: 02.03.10 | B60: LOSA MACIZA | J60: =SUM(J61:J63) -> 1390.03
A61: 02.03.10.01 | B61: LOSA MACIZA CONCRETO f'c= 210 kg/cm² | G61: m3 | H61: =ROUND(Escalera!D15,2) -> 0.88 | I61: =ROUND('APU ESTRUCTURAS'!J713,2) -> 491.8 | J61: =ROUND(H61*I61,2) -> 432.78
A62: 02.03.10.02 | B62: LOSA MACIZA ENCOFRADO Y DESENCOFRADO | G62: m2 | H62: =ROUND(Escalera!D16,2) -> 3.51 | I62: =ROUND('APU ESTRUCTURAS'!J738,2) -> 67.01 | J62: =ROUND(H62*I62,2) -> 235.21
A63: 02.03.10.03 | B63: LOSA MACIZA ACERO fy=4200 kg/cm² | G63: kg | H63: =ROUND(Escalera!D17,2) -> 131.52 | I63: =ROUND('APU ESTRUCTURAS'!J755,2) -> 5.49 | J63: =ROUND(H63*I63,2) -> 722.04
A64: 02.03.11 | B64: PLACAS | J64: =SUM(J65:J67) -> 41807.99
A65: 02.03.11.01 | B65: PLACAS-CONCRETO fc=210kg/cm2 | G65: m3 | H65: =ROUND('Estructura 1'!G19,2) -> 24 | I65: =ROUND('APU ESTRUCTURAS'!J771,2) -> 399.77 | J65: =ROUND(H65*I65,2) -> 9594.48
A66: 02.03.11.02 | B66: PLACAS.- ENCOFRADO Y DESENCOFRADO | G66: m2 | H66: =ROUND('Estructura 1'!G20,2) -> 288.3 | I66: =ROUND('APU ESTRUCTURAS'!J792,2) -> 47.17 | J66: =ROUND(H66*I66,2) -> 13599.11
A67: 02.03.11.03 | B67: PLACAS.- ACERO DE REFUERZO fy=4,200 Kg/cm2 | G67: kg | H67: =ROUND('Estructura 1'!G21,2) -> 3360 | I67: =ROUND('APU ESTRUCTURAS'!J809,2) -> 5.54 | J67: =ROUND(H67*I67,2) -> 18614.4
A68: 02.03.12 | B68: ESCALERA | J68: =SUM(J69:J71) -> 7216.03
A69: 02.03.12.01 | B69: CONCRETO F'C=210 KG/CM² EN ESCALERA | G69: m3 | H69: =ROUND(Escalera!D19,2) -> 3.77 | I69: =ROUND('APU ESTRUCTURAS'!J825,2) -> 547.5 | J69: =ROUND(H69*I69,2) -> 2064.08
A70: 02.03.12.02 | B70: ENCOFRADO Y DESENCOFRADO ESCALERA | G70: m2 | H70: =ROUND(Escalera!D20,2) -> 28.07 | I70: =ROUND('APU ESTRUCTURAS'!J849,2) -> 110.12 | J70: =ROUND(H70*I70,2) -> 3091.07
A71: 02.03.12.03 | B71: ACERO FY=4200 KG/CM² EN ESCALERA | G71: kg | H71: =ROUND(Escalera!D21,2) -> 376.76 | I71: =ROUND('APU ESTRUCTURAS'!J866,2) -> 5.47 | J71: =ROUND(H71*I71,2) -> 2060.88
A72: 2.04 | B72: OBRAS EXTERIORES | J72: =J73+J82+J91+J98+J104+J106+J111 -> 131795.05
A73: 02.04.01 | B73: LOSA DEPORTIVA | J73: =SUM(J74:J81) -> 2563.88
A74: 02.04.01.01 | B74: CONCRETO EN LOSA DEPORTIVA F'C= 210 KG/CM2 | G74: m2 | H74: =ROUND('Obras exteriores '!D13,2) -> 4.4 | I74: =ROUND('APU ESTRUCTURAS'!J883,2) -> 445.67 | J74: =ROUND(H74*I74,2) -> 1960.95
A75: 02.04.01.02 | B75: CONCRETO DE UÑAS = 210KG/CM2 | G75: m3 | H75: =ROUND('Obras exteriores '!D14,2) -> 0.29 | I75: =ROUND('APU ESTRUCTURAS'!J902,2) -> 445.67 | J75: =ROUND(H75*I75,2) -> 129.24
A76: 02.04.01.03 | B76: ENCOFRADO Y DESENCOFRADO NORMAL EN LOSA | G76: m2 | H76: =ROUND('Obras exteriores '!D15,2) -> 1.53 | I76: =ROUND('APU ESTRUCTURAS'!J921,2) -> 118 | J76: =ROUND(H76*I76,2) -> 180.54
A77: 02.04.01.04 | B77: DADOS DE CONCRETO PARA SOPORTE, f'c=210 kg/cm2 | G77: m3 | H77: =ROUND('Obras exteriores '!D16,2) -> 0.02 | I77: =ROUND('APU ESTRUCTURAS'!J940,2) -> 358 | J77: =ROUND(H77*I77,2) -> 7.16
A78: 02.04.01.05 | B78: CURADO DE LOSA | G78: m2 | H78: =ROUND('Obras exteriores '!D17,2) -> 20 | I78: =ROUND('APU ESTRUCTURAS'!J947,2) -> 2.95 | J78: =ROUND(H78*I78,2) -> 59
A79: 02.04.01.06 | B79: JUNTAS DE DILATACION E= 1" , H=0.10 | G79: m | H79: =ROUND('Obras exteriores '!D18,2) -> 3.21 | I79: =ROUND('APU ESTRUCTURAS'!J960,2) -> 19.24 | J79: =ROUND(H79*I79,2) -> 61.76
A80: 02.04.01.07 | B80: JUNTAS DILATACION E= 1", H= 0.05 | G80: m | H80: =ROUND('Obras exteriores '!D19,2) -> 3.78 | I80: =ROUND('APU ESTRUCTURAS'!J975,2) -> 19.24 | J80: =ROUND(H80*I80,2) -> 72.73
A81: 02.04.01.08 | B81: ESTRUCTURA METALICA P/PARANTES DE REFLECTORES | G81: m | H81: =ROUND('Obras exteriores '!D20,2) -> 0.15 | I81: =ROUND('APU ESTRUCTURAS'!J990,2) -> 616.64 | J81: =ROUND(H81*I81,2) -> 92.5
A82: 02.04.02 | B82: PATIO DE INICIAL | J82: =SUM(J83:J90) -> 2563.88
A83: 02.04.02.01 | B83: CONCRETO EN PATIO DE INICIAL F'C= 210 KG/CM2 | G83: m2 | H83: =ROUND('Obras exteriores '!D29,2) -> 4.4 | I83: =ROUND('APU ESTRUCTURAS'!J997,2) -> 445.67 | J83: =ROUND(H83*I83,2) -> 1960.95
A84: 02.04.02.02 | B84: CONCRETO DE UÑAS = 210KG/CM2 | G84: m3 | H84: =ROUND('Obras exteriores '!D30,2) -> 0.29 | I84: =ROUND('APU ESTRUCTURAS'!J1016,2) -> 445.67 | J84: =ROUND(H84*I84,2) -> 129.24
A85: 02.04.02.03 | B85: ENCOFRADO Y DESENCOFRADO NORMAL EN LOSA | G85: m2 | H85: =ROUND('Obras exteriores '!D31,2) -> 1.53 | I85: =ROUND('APU ESTRUCTURAS'!J1035,2) -> 118 | J85: =ROUND(H85*I85,2) -> 180.54
A86: 02.04.02.04 | B86: DADOS DE CONCRETO PARA SOPORTE, f'c=210 kg/cm2 | G86: m3 | H86: =ROUND('Obras exteriores '!D32,2) -> 0.02 | I86: =ROUND('APU ESTRUCTURAS'!J1054,2) -> 358 | J86: =ROUND(H86*I86,2) -> 7.16
A87: 02.04.02.05 | B87: CURADO DE LOSA | G87: m2 | H87: =ROUND('Obras exteriores '!D33,2) -> 20 | I87: =ROUND('APU ESTRUCTURAS'!J1061,2) -> 2.95 | J87: =ROUND(H87*I87,2) -> 59
A88: 02.04.02.06 | B88: JUNTAS DE DILATACION E= 1" , H=0.10 | G88: m | H88: =ROUND('Obras exteriores '!D34,2) -> 3.21 | I88: =ROUND('APU ESTRUCTURAS'!J1074,2) -> 19.24 | J88: =ROUND(H88*I88,2) -> 61.76
A89: 02.04.02.07 | B89: JUNTAS DILATACION E= 1", H= 0.05 | G89: m | H89: =ROUND('Obras exteriores '!D35,2) -> 3.78 | I89: =ROUND('APU ESTRUCTURAS'!J1089,2) -> 19.24 | J89: =ROUND(H89*I89,2) -> 72.73
A90: 02.04.02.08 | B90: ESTRUCTURA METALICA P/PARANTES DE REFLECTORES | G90: m | H90: =ROUND('Obras exteriores '!D36,2) -> 0.15 | I90: =ROUND('APU ESTRUCTURAS'!J1104,2) -> 616.64 | J90: =ROUND(H90*I90,2) -> 92.5
A91: 02.04.03 | B91: VEREDAS Y RAMPAS DE CONCRETO | J91: =SUM(J92:J97) -> 1865.84
A92: 02.04.03.01 | B92: CONCRETO EN VEREDAS F'C= 175 KG/CM2 | G92: m2 | H92: =ROUND('Obras exteriores '!D47,2) -> 2.4 | I92: =ROUND('APU ESTRUCTURAS'!J1111,2) -> 447.89 | J92: =ROUND(H92*I92,2) -> 1074.94
A93: 02.04.03.02 | B93: CONCRETO DE UÑAS = 175KG/CM2 | G93: m3 | H93: =ROUND('Obras exteriores '!D48,2) -> 0.28 | I93: =ROUND('APU ESTRUCTURAS'!J1130,2) -> 447.89 | J93: =ROUND(H93*I93,2) -> 125.41
A94: 02.04.03.03 | B94: ENCOFRADO Y DESENCOFRADO NORMAL EN LOSA | G94: m2 | H94: =ROUND('Obras exteriores '!D49,2) -> 4 | I94: =ROUND('APU ESTRUCTURAS'!J1149,2) -> 118 | J94: =ROUND(H94*I94,2) -> 472
A95: 02.04.03.04 | B95: CURADO DE LOSA | G95: m2 | H95: =ROUND('Obras exteriores '!D50,2) -> 20 | I95: =ROUND('APU ESTRUCTURAS'!J1168,2) -> 2.95 | J95: =ROUND(H95*I95,2) -> 59
A96: 02.04.03.05 | B96: JUNTAS DE DILATACION E= 1" , H=0.10 | G96: m | H96: =ROUND('Obras exteriores '!D52,2) -> 3.21 | I96: =ROUND('APU ESTRUCTURAS'!J1181,2) -> 19.24 | J96: =ROUND(H96*I96,2) -> 61.76
A97: 02.04.03.06 | B97: JUNTAS DILATACION E= 1", H= 0.05 | G97: m | H97: =ROUND('Obras exteriores '!D53,2) -> 3.78 | I97: =ROUND('APU ESTRUCTURAS'!J1196,2) -> 19.24 | J97: =ROUND(H97*I97,2) -> 72.73
A98: 02.04.04 | B98: PAVIMENTO RIGIDO VEHICULAR | J98: =SUM(J99:J103) -> 2325.55
A99: 02.04.04.01 | B99: PAVIMENTO VEHICULAR - ENCOFRADO Y DESENCOFRADO | G99: m2 | H99: =ROUND('Obras exteriores '!D61,2) -> 4.5 | I99: =ROUND('APU ESTRUCTURAS'!J1211,2) -> 84.68 | J99: =ROUND(H99*I99,2) -> 381.06
A100: 02.04.04.02 | B100: DOWELLS | G100: kg | H100: =ROUND('Obras exteriores '!D62,2) -> 4 | I100: =ROUND('APU ESTRUCTURAS'!J1230,2) -> 7.52 | J100: =ROUND(H100*I100,2) -> 30.08
A101: 02.04.04.03 | B101: CURADO DE LOSA | G101: m2 | H101: =ROUND('Obras exteriores '!D63,2) -> 20 | I101: =ROUND('APU ESTRUCTURAS'!J1246,2) -> 2.95 | J101: =ROUND(H101*I101,2) -> 59
...

Sheet APU ESTRUCTURAS
A1: Partida | B1: =ESTRUCTURA!A5 -> 02.01.01 | C1: EXCAVACIÓN LOCALIZADA CON MAQUINARIA
A2: Rendimiento m2/día | B2: m3/dia | C2: M.O | D2: 250 | E2: EQ | F2: =D2 -> 250 | G2: Costo unitario directo | I2: m3 | J2: =J8+J12 -> 8.46
A3: Código | B3: Descripción Recurso | F3: Unidad | G3: Cuadrilla | H3: Cantidad | I3: Precio (S/.) | J3: Parcial (S/.)
B4: Mano de Obra
B5: CAPATAZ | F5: hh | G5: 0.1 | H5: =ROUND(G5*8/$D$2,4) -> 0.0032 | I5: 34.73 | J5: =ROUND(H5*I5,2) -> 0.11 | K5: 47
B6: OPERARIO | F6: hh | G6: 2 | H6: =ROUND(G6*8/$D$2,4) -> 0.064 | I6: 28.94 | J6: =ROUND(H6*I6,2) -> 1.85 | K6: 47
B7: PEON | F7: hh | G7: 1 | H7: =ROUND(G7*8/$D$2,4) -> 0.032 | I7: 20.51 | J7: =ROUND(H7*I7,2) -> 0.66 | K7: 47
J8: =ROUND(SUM(J5:J7),2) -> 2.62
B9: Equipos
B10: HERRAMIENTAS MANUALES | F10: %mo | H10: 3 | I10: =ROUND(J8,2) -> 2.62 | J10: =ROUND(H10%*I10,2) -> 0.08 | K10: 37
B11: RETROEXCAVADORA SOBRE LLANTAS 58 HP 1YD3 | F11: hm | G11: 1 | H11: =ROUND(G11*8/$D$2,4) -> 0.032 | I11: 180 | J11: =ROUND(H11*I11,2) -> 5.76 | K11: 49
J12: =ROUND(SUM(J10:J11),2) -> 5.84
A17: Partida | B17: =ESTRUCTURA!A6 -> 02.01.02 | C17: EXCAVACIÓN MANUAL
A18: Rendimiento m2/día | B18: m3/dia | C18: M.O | D18: 4 | E18: EQ | F18: =D18 -> 4 | G18: Costo unitario directo | I18: m3 | J18: =J23+J26 -> 49.41
A19: Código | B19: Descripción Recurso | F19: Unidad | G19: Cuadrilla | H19: Cantidad | I19: Precio (S/.) | J19: Parcial (S/.)
B20: Mano de Obra
B21: CAPATAZ | F21: hh | G21: 0.1 | H21: =ROUND(G21*8/$D$18,4) -> 0.2 | I21: 34.73 | J21: =ROUND(H21*I21,2) -> 6.95 | K21: 47
B22: PEON | F22: hh | G22: 1 | H22: =ROUND(G22*8/$D$18,4) -> 2 | I22: 20.51 | J22: =ROUND(H22*I22,2) -> 41.02 | K22: 47
J23: =ROUND(SUM(J21:J22),2) -> 47.97
B24: Equipos
B25: HERRAMIENTAS MANUALES | F25: %mo | H25: 3 | I25: =J23 -> 47.97 | J25: =ROUND(H25%*I25,2) -> 1.44 | K25: 37
J26: =ROUND(SUM(J25),2) -> 1.44
A28: Partida | B28: =ESTRUCTURA!A7 -> 02.01.03 | C28: RELLENO COMPACTADO C/PLANCHA COMPACTADORA C/MATERIAL DE PRÉSTAMO
A29: Rendimiento m2/día | B29: m3/dia | C29: M.O | D29: 30 | E29: EQ | F29: =D29 -> 30 | G29: Costo unitario directo | I29: m3 | J29: =J35+J39+J43 -> 66.23
A30: Código | B30: Descripción Recurso | F30: Unidad | G30: Cuadrilla | H30: Cantidad | I30: Precio (S/.) | J30: Parcial (S/.)
B31: Mano de Obra
B32: CAPATAZ | F32: hh | G32: 0.1 | H32: =ROUND(G32*8/$D$29,4) -> 0.0267 | I32: 34.73 | J32: =ROUND(H32*I32,2) -> 0.93 | K32: 47
B33: PEON | F33: hh | G33: 1 | H33: =ROUND(G33*8/$D$29,4) -> 0.2667 | I33: 20.51 | J33: =ROUND(H33*I33,2) -> 5.47 | K33: 47
B34: OPERADOR EQUIPO LIVIANO | F34: hh | G34: 1 | H34: =ROUND(G34*8/$D$29,4) -> 0.2667 | I34: 29.94 | J34: =ROUND(H34*I34,2) -> 7.98 | K34: 47
J35: =ROUND(SUM(J32:J34),2) -> 14.38
B36: Materiales
B37: MATERIAL GRANULAR | F37: m3 | H37: 1.05 | I37: 44.07 | J37: =ROUND(H37*I37,2) -> 46.27 | K37: 5
B38: AGUA | F38: m3 | H38: 0.08 | I38: 6.14 | J38: =ROUND(H38*I38,2) -> 0.49 | K38: 30
J39: =ROUND(SUM(J37:J38),2) -> 46.76
B40: Equipos
B41: HERRAMIENTAS MANUALES | F41: %mo | H41: 3 | I41: =J35 -> 14.38 | J41: =ROUND(H41%*I41,2) -> 0.43 | K41: 37
B42: APISONADOR TIPO CANGURO | F42: hm | G42: 1 | H42: =ROUND(G42*8/$D$29,4) -> 0.2667 | I42: 17.47 | J42: =ROUND(H42*I42,2) -> 4.66 | K42: 49
J43: =ROUND(SUM(J41:J42),2) -> 5.09
A45: Partida | B45: =ESTRUCTURA!A8 -> 02.01.04 | C45: RELLENO COMPACTADO C/PLANCHA COMPACTADORA C/MATERIAL PROPIO
A46: Rendimiento m2/día | B46: m3/dia | C46: M.O | D46: 40 | E46: EQ | F46: =D46 -> 40 | G46: Costo unitario directo | I46: m3 | J46: =J52+J55+J60 -> 19.77
A47: Código | B47: Descripción Recurso | F47: Unidad | G47: Cuadrilla | H47: Cantidad | I47: Precio (S/.) | J47: Parcial (S/.)
B48: Mano de Obra
B49: CAPATAZ | F49: hh | G49: 0.1 | H49: =ROUND(G49*8/$D$46,4) -> 0.02 | I49: 34.73 | J49: =ROUND(H49*I49,2) -> 0.69 | K49: 47
B50: PEON | F50: hh | G50: 2 | H50: =ROUND(G50*8/$D$46,4) -> 0.4 | I50: 20.51 | J50: =ROUND(H50*I50,2) -> 8.2 | K50: 47
B51: OPERADOR EQUIPO LIVIANO | F51: hh | G51: 1 | H51: =ROUND(G51*8/$D$46,4) -> 0.2 | I51: 29.94 | J51: =ROUND(H51*I51,2) -> 5.99 | K51: 47
J52: =ROUND(SUM(J49:J51),2) -> 14.88
B53: Materiales
B54: AGUA | F54: m3 | H54: 0.08 | I54: 6.14 | J54: =ROUND(H54*I54,2) -> 0.49 | K54: 30
J55: =ROUND(SUM(J54:J54),2) -> 0.49
B56: Equipos
B57: HERRAMIENTAS MANUALES | F57: %mo | H57: 5 | I57: =J52 -> 14.88 | J57: =ROUND(H57%*I57,2) -> 0.74 | K57: 37
B58: APISONADOR TIPO CANGURO | F58: hm | G58: 1 | H58: =ROUND(G58*8/$D$46,4) -> 0.2 | I58: 17.47 | J58: =ROUND(H58*I58,2) -> 3.49 | K58: 49
B59: CAMION CISTERNA (1,500 GLNS.) | F59: hm | G59: 0.05 | H59: =ROUND(G59*8/$D$46,4) -> 0.01 | I59: 17.47 | J59: =ROUND(H59*I59,2) -> 0.17 | K59: 48
J60: =ROUND(SUM(J57:J59),2) -> 4.4
A62: Partida | B62: =ESTRUCTURA!A9 -> 02.01.05 | C62: FORMACION Y COMPACTACION DE SUBRASANTE
A63: Rendimiento m2/día | B63: m2/dia | C63: M.O | D63: 500 | E63: EQ | F63: =D63 -> 500 | G63: Costo unitario directo | I63: m2 | J63: =J69+J75 -> 7.99
A64: Código | B64: Descripción Recurso | F64: Unidad | G64: Cuadrilla | H64: Cantidad | I64: Precio (S/.) | J64: Parcial (S/.)
B65: Mano de Obra
B66: CAPATAZ | F66: hh | G66: 1 | H66: =ROUND(G66*8/$D$63,4) -> 0.016 | I66: 34.73 | J66: =ROUND(H66*I66,2) -> 0.56 | K66: 47
B67: OFICIAL | F67: hh | G67: 1 | H67: =ROUND(G67*8/$D$63,4) -> 0.016 | I67: 22.66 | J67: =ROUND(H67*I67,2) -> 0.36 | K67: 47
B68: PEON | F68: hh | G68: 3 | H68: =ROUND(G68*8/$D$63,4) -> 0.048 | I68: 20.51 | J68: =ROUND(H68*I68,2) -> 0.98 | K68: 47
J69: =ROUND(SUM(J66:J68),2) -> 1.9
B70: Equipos
B71: HERRAMIENTAS MANUALES | F71: %mo | H71: 5 | I71: =J69 -> 1.9 | J71: =ROUND(H71%*I71,2) -> 0.1 | K71: 37
B72: APISONADOR TIPO CANGURO | F72: hm | G72: 1 | H72: =ROUND(G72*8/$D$63,4) -> 0.016 | I72: 17.47 | J72: =ROUND(H72*I72,2) -> 0.28 | K72: 49
B73: RODILLO LISO VIBRATORIO AUTOPROPULSADO 7- 9 ton | F73: hm | G73: 1 | H73: =ROUND(G73*8/$D$63,4) -> 0.016 | I73: 136.06 | J73: =ROUND(H73*I73,2) -> 2.18 | K73: 49
B74: MOTONIVELADORA 125 HP | F74: hm | G74: 1 | H74: =ROUND(G74*8/$D$63,4) -> 0.016 | I74: 220.52 | J74: =ROUND(H74*I74,2) -> 3.53 | K74: 48
J75: =ROUND(SUM(J71:J74),2) -> 6.09
A77: Partida | B77: =ESTRUCTURA!A10 -> 02.01.06 | C77: ACARREO DE MATERIAL EXCEDENTE
A78: Rendimiento m2/día | B78: m/dia | C78: M.O | D78: 80 | E78: EQ | F78: =D78 -> 80 | G78: Costo unitario directo | I78: m | J78: =J82+J86 -> 12.11
A79: Código | B79: Descripción Recurso | F79: Unidad | G79: Cuadrilla | H79: Cantidad | I79: Precio (S/.) | J79: Parcial (S/.)
B80: Mano de Obra
B81: PEON | F81: hh | G81: 1 | H81: =ROUND(G81*8/$D$78,4) -> 0.1 | I81: 20.51 | J81: =ROUND(H81*I81,2) -> 2.05 | K81: 47
J82: =ROUND(SUM(J81:J81),2) -> 2.05
B83: Equipos
B84: HERRAMIENTAS MANUALES | F84: %mo | H84: 3 | I84: =J82 -> 2.05 | J84: =ROUND(H84%*I84,2) -> 0.06 | K84: 37
B85: MINICARGADOR DE 73 HP | F85: hm | G85: 1 | H85: =ROUND(G85*8/$D$78,4) -> 0.1 | I85: 100 | J85: =ROUND(H85*I85,2) -> 10 | K85: 48
J86: =ROUND(SUM(J84:J85),2) -> 10.06
A88: Partida | B88: =ESTRUCTURA!A11 -> 02.01.07 | C88: ELIMINACIÓN DE MATERIAL EXCEDENTE HASTA D=10 KM
A89: Rendimiento m2/día | B89: m3/dia | C89: M.O | D89: 187.5 | E89: EQ | F89: =D89 -> 187.5 | G89: Costo unitario directo | I89: m3 | J89: =J94+J99 -> 22.88
A90: Código | B90: Descripción Recurso | F90: Unidad | G90: Cuadrilla | H90: Cantidad | I90: Precio (S/.) | J90: Parcial (S/.)
B91: Mano de Obra
B92: OFICIAL | F92: hh | G92: 1 | H92: =ROUND(G92*8/$D$89,4) -> 0.0427 | I92: 22.66 | J92: =ROUND(H92*I92,2) -> 0.97 | K92: 47
B93: PEON | F93: hh | G93: 1 | H93: =ROUND(G93*8/$D$89,4) -> 0.0427 | I93: 20.51 | J93: =ROUND(H93*I93,2) -> 0.88 | K93: 47
J94: =ROUND(SUM(J92:J93),2) -> 1.85
B95: Equipos
B96: HERRAMIENTAS MANUALES | F96: %mo | H96: 3 | I96: =J94 -> 1.85 | J96: =ROUND(H96%*I96,2) -> 0.06 | K96: 37
B97: CAMION VOLQUETE 4X4 414 HP 15 m3 | F97: hm | G97: 1 | H97: =ROUND(G97*8/$D$89,4) -> 0.0427 | I97: 118.64 | J97: =ROUND(H97*I97,2) -> 5.07 | K97: 48
B98: CARGADOR SOBRE LLANTAS 100-115 HP 2-2.25 yd3 | F98: hm | G98: 2 | H98: =ROUND(G98*8/$D$89,4) -> 0.0853 | I98: 186.44 | J98: =ROUND(H98*I98,2) -> 15.9 | K98: 48
J99: =ROUND(SUM(J96:J98),2) -> 21.03
A101: Partida | B101: =ESTRUCTURA!A12 -> 02.01.08 | C101: COMPACTACION DE SUBRASANTE LOSA DEPORTIVA
A102: Rendimiento m2/día | B102: m2/dia | C102: M.O | D102: 500 | E102: EQ | F102: =D102 -> 500 | G102: Costo unitario directo | I102: m2 | J102: =J108+J114 -> 7.99
A103: Código | B103: Descripción Recurso | F103: Unidad | G103: Cuadrilla | H103: Cantidad | I103: Precio (S/.) | J103: Parcial (S/.)
B104: Mano de Obra
B105: CAPATAZ | F105: hh | G105: 1 | H105: =ROUND(G105*8/$D$102,4) -> 0.016 | I105: 34.73 | J105: =ROUND(H105*I105,2) -> 0.56 | K105: 47
B106: OFICIAL | F106: hh | G106: 1 | H106: =ROUND(G106*8/$D$102,4) -> 0.016 | I106: 22.66 | J106: =ROUND(H106*I106,2) -> 0.36 | K106: 47
B107: PEON | F107: hh | G107: 3 | H107: =ROUND(G107*8/$D$102,4) -> 0.048 | I107: 20.51 | J107: =ROUND(H107*I107,2) -> 0.98 | K107: 47
J108: =ROUND(SUM(J105:J107),2) -> 1.9
B109: Equipos
B110: HERRAMIENTAS MANUALES | F110: %mo | H110: 5 | I110: =J108 -> 1.9 | J110: =ROUND(H110%*I110,2) -> 0.1 | K110: 37
...

Sheet ARQUITECTURA
G2: Unidad | H2: Metrado | I2: C.U | J2: Parcial | K2: Total
A3: 3 | B3: ARQUITECTURA | K3: =J4+J10+J19+J26+J33+J39+J43 -> 1039120.6
A4: 3.01 | B4: MUROS DE MAMPOSTERIA | J4: =SUM(J5:J9) -> 282960.31
A5: 03.01.01 | B5: MURO DE LADRILLO KK TIPO IV SOGA M 1:4 E=1.5 CM | G5: m2 | H5: =ROUND(SUM(BIBLIOTECA:INGRESO!G6),2) -> 1048.34 | I5: =ROUND('APUS ARQUITECTURA'!J5,2) -> 140.28 | J5: =ROUND(H5*I5,2) -> 147061.14
A6: 03.01.02 | B6: MURO DE LADRILLO KK TIPO IV CABEZA M 1:4 E=1.5 CM | G6: m2 | H6: =ROUND(SUM(BIBLIOTECA:INGRESO!G7),2) -> 345.85 | I6: =ROUND('APUS ARQUITECTURA'!J32,2) -> 166.43 | J6: =ROUND(H6*I6,2) -> 57559.82
A7: 03.01.03 | B7: TABIQUE DE DRYWALL E=0.15m | G7: m2 | H7: =ROUND(SUM(BIBLIOTECA:INGRESO!G8),2) -> 287.32 | I7: =ROUND('APUS ARQUITECTURA'!J50,2) -> 141.08 | J7: =ROUND(H7*I7,2) -> 40535.11
A8: 03.01.04 | B8: MELAMINE | G8: m2 | H8: =ROUND(SUM(BIBLIOTECA:INGRESO!G9),2) -> 156.6 | I8: =ROUND('APUS ARQUITECTURA'!J74,2) -> 204.42 | J8: =ROUND(H8*I8,2) -> 32012.17
A9: 03.01.05 | B9: TABLERO C.A. C/CERAMICO | G9: m2 | H9: =ROUND(SUM(BIBLIOTECA:INGRESO!G10),2) -> 12.3 | I9: =ROUND('APUS ARQUITECTURA'!J92,2) -> 470.9 | J9: =ROUND(H9*I9,2) -> 5792.07
A10: 3.02 | B10: REVOQUES, ENLUCIDOS y MOLDURAS | J10: =J11+J14+J16 -> 224988.3
A11: 03.02.01 | B11: TARRAJEO | J11: =SUM(J12:J13) -> 65308.96
A12: 03.02.01.01 | B12: TARRAJEO FROTACHADO EN MUROS INTERIORES | G12: m2 | H12: =ROUND(SUM(BIBLIOTECA:INGRESO!G13),2) -> 1392.44 | I12: =ROUND('APUS ARQUITECTURA'!J127,2) -> 27.34 | J12: =ROUND(H12*I12,2) -> 38069.31
A13: 03.02.01.02 | B13: TARRAJEO FROTACHADO EN MUROS EXTERIORES | G13: m2 | H13: =ROUND(SUM(BIBLIOTECA:INGRESO!G14),2) -> 754.77 | I13: =ROUND('APUS ARQUITECTURA'!J148,2) -> 36.09 | J13: =ROUND(H13*I13,2) -> 27239.65
A14: 03.02.02 | B14: ZOCALO | J14: =SUM(J15) -> 72069.06
A15: 03.02.02.01 | B15: ZOCALO DE CERAMICA 0.30x0.30 | G15: m2 | H15: =ROUND(SUM(BIBLIOTECA:INGRESO!G16),2) -> 793.45 | I15: =ROUND('APUS ARQUITECTURA'!J168,2) -> 90.83 | J15: =ROUND(H15*I15,2) -> 72069.06
A16: 03.02.03 | B16: CIELO RASO | J16: =SUM(J17:J18) -> 87610.28
A17: 03.02.03.01 | B17: FALSO CIELORRADOS DE BALDOSAS DE FIBRA MINERAL DE 0.61x0.61m, e:15mm, BORDE REBAJADO, CON SISTEMA DE SUSPENSION ANTISISMICO | G17: m3 | H17: =ROUND(SUM(BIBLIOTECA:INGRESO!G18),2) -> 160 | I17: =ROUND('APUS ARQUITECTURA'!J188,2) -> 213.18 | J17: =ROUND(H17*I17,2) -> 34108.8
A18: 03.02.03.02 | B18: TARRAJEO DE CIELO RASO MEZCLA C:A 1:5, e=0.15cm | G18: m3 | H18: =ROUND(SUM(BIBLIOTECA:INGRESO!G19),2) -> 866 | I18: =ROUND('APUS ARQUITECTURA'!J212,2) -> 61.78 | J18: =ROUND(H18*I18,2) -> 53501.48
A19: 3.03 | B19: PISOS Y PAVIMENTOS | J19: =SUM(J20:J25) -> 193026.6
A20: 03.03.01 | B20: CONTRAPISOS E=40MM C:A 1:4 | G20: m2 | H20: =ROUND(SUM(BIBLIOTECA:INGRESO!G21),2) -> 1000 | I20: =ROUND('APUS ARQUITECTURA'!J232,2) -> 49.73 | J20: =ROUND(H20*I20,2) -> 49730
A21: 03.03.02 | B21: PISO PORCELANATO ANTIDESLIZANTE 0.60x0.6OM | G21: m2 | H21: =ROUND(SUM(BIBLIOTECA:INGRESO!G22),2) -> 320 | I21: =ROUND('APUS ARQUITECTURA'!J252,2) -> 206.78 | J21: =ROUND(H21*I21,2) -> 66169.6
A22: 03.03.03 | B22: PISO DE BALDOSA CERAMICA 30x30 | G22: m2 | H22: =ROUND(SUM(BIBLIOTECA:INGRESO!G23),2) -> 380 | I22: =ROUND('APUS ARQUITECTURA'!J272,2) -> 102.66 | J22: =ROUND(H22*I22,2) -> 39010.8
A23: 03.03.04 | B23: PISO DE CONCRETO E=4" - FC=175 KG7CM2 / ACABADO FROTACHADO | G23: m2 | H23: =ROUND(SUM(BIBLIOTECA:INGRESO!G24),2) -> 100 | I23: =ROUND('APUS ARQUITECTURA'!J292,2) -> 47.45 | J23: =ROUND(H23*I23,2) -> 4745
A24: 03.03.05 | B24: PISO DE CEMENTO PULIDO Y BRUÑADO E=2" S/ COLOREAR | G24: m2 | H24: =ROUND(SUM(BIBLIOTECA:INGRESO!G25),2) -> 100 | I24: =ROUND('APUS ARQUITECTURA'!J318,2) -> 51.99 | J24: =ROUND(H24*I24,2) -> 5199
A25: 03.03.06 | B25: PISO LAMINADO DE ALTO TRANSITO EN AULAS | G25: m2 | H25: =ROUND(SUM(BIBLIOTECA:INGRESO!G26),2) -> 140 | I25: =ROUND('APUS ARQUITECTURA'!J340,2) -> 201.23 | J25: =ROUND(H25*I25,2) -> 28172.2
A26: 3.04 | B26: CONTRAZOCALOS | J26: =SUM(J27:J32) -> 33501.05
A27: 03.04.01 | B27: CONTR. S/COLOREAR H=30cm MZ 1:2 e=1.5cm | G27: m | H27: =ROUND(SUM(BIBLIOTECA:INGRESO!G28),2) -> 82.3 | I27: =ROUND('APUS ARQUITECTURA'!J347,2) -> 20.58 | J27: =ROUND(H27*I27,2) -> 1693.73
A28: 03.04.02 | B28: CONTRAZOCALO DE CEMENTO SEMIPULIDO CON IMPERMEABILIZANTE Y ENDURECEDOR | G28: m | H28: =ROUND(SUM(BIBLIOTECA:INGRESO!G29),2) -> 393.14 | I28: =ROUND('APUS ARQUITECTURA'!J364,2) -> 26.7 | J28: =ROUND(H28*I28,2) -> 10496.84
A29: 03.04.03 | B29: CONTRAZOCALO PORCELANATO ANTIDESLIZANTE H=0.10M | G29: m | H29: =ROUND(SUM(BIBLIOTECA:INGRESO!G30),2) -> 177.6 | I29: =ROUND('APUS ARQUITECTURA'!J383,2) -> 36.55 | J29: =ROUND(H29*I29,2) -> 6491.28
A30: 03.04.04 | B30: CONTRAZOCALO LAMINADO EN AULAS | G30: m | H30: =ROUND(SUM(BIBLIOTECA:INGRESO!G31),2) -> 63.91 | I30: =ROUND('APUS ARQUITECTURA'!J403,2) -> 25 | J30: =ROUND(H30*I30,2) -> 1597.75
A31: 03.04.05 | B31: CONTRAZOCALO DE BALDOSA CERAMICA H=30cm | G31: m | H31: =ROUND(SUM(BIBLIOTECA:INGRESO!G32),2) -> 117.83 | I31: =ROUND('APUS ARQUITECTURA'!J410,2) -> 44.2 | J31: =ROUND(H31*I31,2) -> 5208.09
A32: 03.04.06 | B32: CONTRAZOCALO SANITARIO TERRAZO PULIDO, H=0,10M | G32: m | H32: =ROUND(SUM(BIBLIOTECA:INGRESO!G33),2) -> 94.9 | I32: =ROUND('APUS ARQUITECTURA'!J430,2) -> 84.44 | J32: =ROUND(H32*I32,2) -> 8013.36
A33: 3.05 | B33: CARPINTERIA | J33: =SUM(J34:J38) -> 233643.5
A34: 03.05.01 | B34: PUERTA DE MADERA ROBLE NACIONAL APANELADA TIPO MACHIMBRADA +SOBRELUZ+VIDRIO TEMPLADO DE 8MM DE 02 HOJAS+INST+ACABADO, SEGUN PLANO Y ET | G34: m2 | H34: =ROUND(SUM(BIBLIOTECA:INGRESO!G35),2) -> 135.16 | I34: =ROUND('APUS ARQUITECTURA'!J449,2) -> 560.62 | J34: =ROUND(H34*I34,2) -> 75773.4
A35: 03.05.02 | B35: VENTANA C/MARCO DE ALUMINIO SISTEMA CORREDIZO TIPO SERIE 3160 + VIDRIOS INCOLORO TEMPLADO DE 8MM+ACCESORIO + ACCESORIO+ INSTALACION, SEGUN PLANO Y ESPECIFICACIONES TECNICAS | G35: m2 | H35: =ROUND(SUM(BIBLIOTECA:INGRESO!G36),2) -> 124.47 | I35: =ROUND('APUS ARQUITECTURA'!J456,2) -> 367.87 | J35: =ROUND(H35*I35,2) -> 45788.78
A36: 03.05.03 | B36: MAMPARA DE ALUMINIO+VIDRIO INCOLORO TEMPLADO 8MM+ACCESORIOS+INSTALACION,SEGUN PLANO Y ESPECIFICACIONES TECNICAS | G36: m2 | H36: =ROUND(SUM(BIBLIOTECA:INGRESO!G37),2) -> 66.35 | I36: =ROUND('APUS ARQUITECTURA'!J463,2) -> 514.54 | J36: =ROUND(H36*I36,2) -> 34139.73
A37: 03.05.04 | B37: PARASOLES | G37: m | H37: =ROUND(SUM(BIBLIOTECA:INGRESO!G38),2) -> 122.2 | I37: =ROUND('APUS ARQUITECTURA'!J470,2) -> 622.13 | J37: =ROUND(H37*I37,2) -> 76024.29
A38: 03.05.05 | B38: PERSIANA METALICA | G38: m2 | H38: =ROUND(SUM(BIBLIOTECA:INGRESO!G39),2) -> 35 | I38: =ROUND('APUS ARQUITECTURA'!J477,2) -> 54.78 | J38: =ROUND(H38*I38,2) -> 1917.3
A39: 3.06 | B39: PINTURA | J39: =SUM(J40:J41) -> 48739.24
A40: 03.06.01 | B40: PINTURA LATEX PARA INTERIOR - 2 MANOS (MUROS, TECHOS, VIGAS Y COLUMNAS) | G40: m2 | H40: =ROUND(SUM(BIBLIOTECA:INGRESO!G41),2) -> 2395.93 | I40: =ROUND('APUS ARQUITECTURA'!J484,2) -> 15.63 | J40: =ROUND(H40*I40,2) -> 37448.39
A41: 03.06.02 | B41: PINTURA OLEO PARA EXTERIORES - 2 MANOS | G41: m2 | H41: =ROUND(SUM(BIBLIOTECA:INGRESO!G42),2) -> 707.89 | I41: =ROUND('APUS ARQUITECTURA'!J504,2) -> 15.95 | J41: =ROUND(H41*I41,2) -> 11290.85
A43: 3.07 | B43: OBRAS EXTERIORES | J43: =J44+J48+J50+J52+J54+J56+J58+J63+J65 -> 22261.56
A44: 03.07.01 | B44: AREAS VERDES | J44: =SUM(J45:J47) -> 1498.72
A45: 03.07.01.01 | B45: SUMINISTRO Y PREPARACIÓN DE TIERRA DE CHACRA | G45: m2 | H45: =ROUND('Obras exteriores '!D5,2) -> 30 | I45: =ROUND('APUS ARQUITECTURA'!J525,2) -> 13.47 | J45: =ROUND(H45*I45,2) -> 404.1
A46: 03.07.01.02 | B46: SUMINISTRO Y SEMBRIO DE ARBUSTOS | G46: und | H46: =ROUND('Obras exteriores '!D6,2) -> 10 | I46: =ROUND('APUS ARQUITECTURA'!J541,2) -> 73.84 | J46: =ROUND(H46*I46,2) -> 738.4
A47: 03.07.01.03 | B47: SUMINISTRO Y SEMBRIO DE ARBOLES | G47: und | H47: =ROUND('Obras exteriores '!D7,2) -> 3 | I47: =ROUND('APUS ARQUITECTURA'!J558,2) -> 118.74 | J47: =ROUND(H47*I47,2) -> 356.22
A48: 03.07.02 | B48: LOSA DEPORTIVA | J48: =SUM(J49) -> 25.53
A49: 03.07.02.01 | B49: PINTURA DE LINEAS EN LOSA DEPORTIVA | G49: m | H49: =ROUND('Obras exteriores '!D21,2) -> 0.5 | I49: =ROUND('APUS ARQUITECTURA'!J575,2) -> 51.05 | J49: =ROUND(H49*I49,2) -> 25.53
A50: 03.07.03 | B50: PATIO DE FORMACIÓN | J50: =SUM(J51) -> 25.53
A51: 03.07.03.01 | B51: PINTURA DE LINEAS EN PATIO DE INICIAL | G51: m | H51: =ROUND('Obras exteriores '!D37,2) -> 0.5 | I51: =ROUND('APUS ARQUITECTURA'!J591,2) -> 51.05 | J51: =ROUND(H51*I51,2) -> 25.53
A52: 03.07.04 | B52: VEREDAS Y RAMPAS DE CONCRETO | J52: =SUM(J53) -> 197.6
A53: 03.07.04.01 | B53: ACABADO FROTACHADO Y BRUÑADO EN VEREDAS | G53: m2 | H53: =ROUND('Obras exteriores '!D51,2) -> 20 | I53: =ROUND('APUS ARQUITECTURA'!J607,2) -> 9.88 | J53: =ROUND(H53*I53,2) -> 197.6
A54: 03.07.05 | B54: PAVIMENTO RIGIDO VEHICULAR | J54: =SUM(J55) -> 440
A55: 03.07.05.01 | B55: ACABADO CEPILLADO | G55: glb | H55: =ROUND('Obras exteriores '!D60,2) -> 20 | I55: =ROUND('APUS ARQUITECTURA'!J618,2) -> 22 | J55: =ROUND(H55*I55,2) -> 440
A56: 03.07.06 | B56: LAMAS EN PASADIZOS | J56: =SUM(J57) -> 1509.2
A57: 03.07.06.01 | B57: LAMAS EN PASADIZOS | G57: m2 | H57: =ROUND('Obras exteriores '!D66,2) -> 20 | I57: =ROUND('APUS ARQUITECTURA'!J625,2) -> 75.46 | J57: =ROUND(H57*I57,2) -> 1509.2
A58: 03.07.07 | B58: CERCO PERIMETRICO | J58: =SUM(J59:J62) -> 7559.68
A59: 03.07.07.01 | B59: MURO DE LADRILLO | G59: m | H59: =ROUND('Obras exteriores '!D86,2) -> 43.21 | I59: =ROUND('APUS ARQUITECTURA'!J632,2) -> 110.42 | J59: =ROUND(H59*I59,2) -> 4771.25
A60: 03.07.07.02 | B60: TARRAJEO COLUMNAS Y PLACAS | G60: m2 | H60: =ROUND('Obras exteriores '!D88,2) -> 7.73 | I60: =ROUND('APUS ARQUITECTURA'!J639,2) -> 68.02 | J60: =ROUND(H60*I60,2) -> 525.79
A61: 03.07.07.03 | B61: TARRAJEO DE VIGAS | G61: m2 | H61: =ROUND('Obras exteriores '!D89,2) -> 8 | I61: =ROUND('APUS ARQUITECTURA'!J659,2) -> 39.51 | J61: =ROUND(H61*I61,2) -> 316.08
A62: 03.07.07.04 | B62: PINTURA DE MUROS | G62: m2 | H62: =ROUND('Obras exteriores '!D90,2) -> 112 | I62: =ROUND('APUS ARQUITECTURA'!J666,2) -> 17.38 | J62: =ROUND(H62*I62,2) -> 1946.56
A63: 03.07.08 | B63: ASTA DE BANDERA | J63: =SUM(J64) -> 4225.7
A64: 03.07.08.01 | B64: ASTA DE BANDERA | G64: und | H64: =ROUND('Obras exteriores '!D40,2) -> 2 | I64: =ROUND('APUS ARQUITECTURA'!J673,2) -> 2112.85 | J64: =ROUND(H64*I64,2) -> 4225.7
A65: 03.07.09 | B65: COBERTURAS | J65: =SUM(J66:J67) -> 6779.6
A66: 03.07.09.01 | B66: COBERTURA LIVIANA DE LOSA DEPORTIVA | G66: m2 | H66: =ROUND('Obras exteriores '!D22,2) -> 20 | I66: =ROUND('APUS ARQUITECTURA'!J705,2) -> 169.49 | J66: =ROUND(H66*I66,2) -> 3389.8
A67: 03.07.09.02 | B67: COBERTURA LIVIANA DE PATIO DE INICIAL | G67: m2 | H67: =ROUND('Obras exteriores '!D38,2) -> 20 | I67: =ROUND('APUS ARQUITECTURA'!J712,2) -> 169.49 | J67: =ROUND(H67*I67,2) -> 3389.8

Sheet APUS ARQUITECTURA
A4: Partida | B4: =ARQUITECTURA!A5 -> 03.01.01 | C4: MURO DE LADRILLO KK TIPO IV SOGA M 1:4 E=1.5 CM | R4: Partida | S4: =A22 -> 100000000010 | T4: COLUMNETAS - CONCRETO f'c=210 kg/cm²
A5: Rendimiento m2/día | B5: m2/dia | C5: M.O | D5: 16 | E5: EQ | F5: =D5 -> 16 | G5: Costo unitario directo | I5: m2 | J5: =J10+J16+J20+J29 -> 140.28 | R5: Rendimiento m2/día | S5: m3/dia | T5: M.O | U5: 10 | V5: EQ | W5: =U5 -> 10 | X5: Costo unitario directo | Z5: m3 | AA5: =AA11+AA18+AA23 -> 493.41
A6: Código | B6: Descripción Recurso | F6: Unidad | G6: Cuadrilla | H6: Cantidad | I6: Precio (S/.) | J6: Parcial (S/.) | R6: Código | S6: Descripción Recurso | W6: Unidad | X6: Cuadrilla | Y6: Cantidad | Z6: Precio (S/.) | AA6: Parcial (S/.)
B7: Mano de Obra | S7: Mano de Obra
B8: OPERARIO | F8: hh | G8: 2 | H8: =ROUND(G8*8/$D$5,4) -> 1 | I8: 28.94 | J8: =ROUND(H8*I8,2) -> 28.94 | K8: 47 | S8: OPERARIO | W8: hh | X8: 2 | Y8: =ROUND(X8*8/$U$5,4) -> 1.6 | Z8: 28.94 | AA8: =ROUND(Y8*Z8,2) -> 46.3 | AB8: 47
B9: PEON | F9: hh | G9: 1 | H9: =ROUND(G9*8/$D$5,4) -> 0.5 | I9: 20.51 | J9: =ROUND(H9*I9,2) -> 10.26 | K9: 47 | S9: OFICIAL | W9: hh | X9: 1 | Y9: =ROUND(X9*8/$U$5,4) -> 0.8 | Z9: 22.66 | AA9: =ROUND(Y9*Z9,2) -> 18.13 | AB9: 47
J10: =ROUND(SUM(J8:J9),2) -> 39.2 | S10: PEON | W10: hh | X10: 8 | Y10: =ROUND(X10*8/$U$5,4) -> 6.4 | Z10: 20.51 | AA10: =ROUND(Y10*Z10,2) -> 131.26 | AB10: 47
B11: Materiales | AA11: =ROUND(SUM(AA8:AA10),2) -> 195.69
B12: AGUA | F12: m3 | H12: 0.0068 | I12: 6.14 | J12: =ROUND(H12*I12,2) -> 0.04 | K12: 30 | S12: Materiales
B13: ARENA GRUESA | F13: m3 | H13: 0.0269 | I13: 47 | J13: =ROUND(H13*I13,2) -> 1.26 | K13: 4 | S13: PIEDRA CHANCADA DE 1/2" Y 3/4" | W13: m3 | Y13: 0.55 | Z13: 55.08 | AA13: =ROUND(Y13*Z13,2) -> 30.29 | AB13: 5
B14: CEMENTO PORTLAND TIPO I (42.5 kg) | F14: bls | H14: 0.2211 | I14: 24.52 | J14: =ROUND(H14*I14,2) -> 5.42 | K14: 21 | S14: ARENA GRUESA | W14: m3 | Y14: 0.54 | Z14: 47 | AA14: =ROUND(Y14*Z14,2) -> 25.38 | AB14: 4
B15: LADRILLO KK TIPO IV 24X13X9 CM | F15: und | H15: 39 | I15: 1.02 | J15: =ROUND(H15*I15,2) -> 39.78 | K15: 17 | S15: CEMENTO PORTLAND TIPO I (42.5 kg) | W15: bls | Y15: 8.43 | Z15: 24.52 | AA15: =ROUND(Y15*Z15,2) -> 206.7 | AB15: 21
J16: =ROUND(SUM(J12:J15),2) -> 46.5 | S16: AGUA | W16: m3 | Y16: 0.185 | Z16: 6.14 | AA16: =ROUND(Y16*Z16,2) -> 1.14 | AB16: 30
B17: Equipos | S17: GASOLINA DE 84 OCTANOS | W17: gal | Y17: 0.36 | Z17: 13.93 | AA17: =ROUND(Y17*Z17,2) -> 5.01 | AB17: 34
B18: HERRAMIENTAS MANUALES | F18: %mo | H18: 3 | I18: =J10 -> 39.2 | J18: =ROUND(H18%*I18,2) -> 1.18 | K18: 37 | AA18: =ROUND(SUM(AA13:AA17),2) -> 268.52
B19: ANDAMIO METALICO HOMOLOGADO | F19: d | G19: 2 | H19: =ROUND(G19*8/$D$5,4) -> 1 | I19: 10.34 | J19: =ROUND(H19*I19,2) -> 10.34 | K19: 39 | S19: Equipos
J20: =ROUND(SUM(J18:J19),2) -> 11.52 | S20: HERRAMIENTAS MANUALES | W20: %mo | Y20: 3 | Z20: =AA11 -> 195.69 | AA20: =ROUND(Y20%*Z20,2) -> 5.87 | AB20: 37
B21: Subpartidas | S21: MEZCLADORA DE CONCRETO TAMBOR 11 p3 18 HP | W21: hm | X21: 1 | Y21: =ROUND(X21*8/$U$5,4) -> 0.8 | Z21: 25.63 | AA21: =ROUND(Y21*Z21,2) -> 20.5 | AB21: 48
A22: 100000000010 | B22: COLUMNETAS - CONCRETO F'C= 210 kg/cm2 | F22: m3 | H22: 0.011 | I22: =AA5 -> 493.41 | J22: =ROUND(H22*I22,2) -> 5.43 | S22: VIBRADOR A GASOLINA Y 1 3/4" , 4 HP | W22: hm | X22: 0.5 | Y22: =ROUND(X22*8/$U$5,4) -> 0.4 | Z22: 7.07 | AA22: =ROUND(Y22*Z22,2) -> 2.83 | AB22: 49
A23: 100000000011 | B23: COLUMNETAS - ENCOFRADO Y DESENCOFRADO | F23: m2 | H23: 0.1069 | I23: =AA26 -> 56.16 | J23: =ROUND(H23*I23,2) -> 6 | AA23: =ROUND(SUM(AA20:AA22),2) -> 29.2
A24: 100000000012 | B24: COLUMNETAS - ACERO DE REFUERZO Fy= 4200 kg/cm2 | F24: kg | H24: 0.9331 | I24: =AA42 -> 5.54 | J24: =ROUND(H24*I24,2) -> 5.17
A25: 100000000013 | B25: VIGUETAS - CONCRETO F'C= 210 kg/cm2 | F25: m3 | H25: 0.0058 | I25: =AA58 -> 377.33 | J25: =ROUND(H25*I25,2) -> 2.19 | R25: Partida | S25: =A23 -> 100000000011 | T25: COLUMNETAS - ENCOFRADO Y DESENCOFRADO NORMAL
A26: 100000000014 | B26: VIGUETAS - ENCOFRADO Y DESENCOFRADO | F26: m2 | H26: 0.0774 | I26: =AA79 -> 71.15 | J26: =ROUND(H26*I26,2) -> 5.51 | R26: Rendimiento m2/día | S26: m2/dia | T26: M.O | U26: 12 | V26: EQ | W26: =U26 -> 12 | X26: Costo unitario directo | Z26: m2 | AA26: =AA31+AA36+AA39 -> 56.16
A27: 100000000015 | B27: VIGUETAS - ACERO DE REFUERZO Fy= 4200 kg/cm2 | F27: kg | H27: 0.9009 | I27: =AA96 -> 5.54 | J27: =ROUND(H27*I27,2) -> 4.99 | R27: Código | S27: Descripción Recurso | W27: Unidad | X27: Cuadrilla | Y27: Cantidad | Z27: Precio (S/.) | AA27: Parcial (S/.)
A28: 100000000016 | B28: JUNTAS CON ESPUMA PLASTICO + SELLO ELASTOMERICO DE POLIURETANO E=0.15M | F28: m | H28: 0.2487 | I28: =AA112 -> 55.35 | J28: =ROUND(H28*I28,2) -> 13.77 | S28: Mano de Obra
J29: =ROUND(SUM(J22:J28),2) -> 43.06 | S29: OPERARIO | W29: hh | X29: 1 | Y29: =ROUND(X29*8/$U$26,4) -> 0.6667 | Z29: 28.94 | AA29: =ROUND(Y29*Z29,2) -> 19.29 | AB29: 47
S30: PEON | W30: hh | X30: 1 | Y30: =ROUND(X30*8/$U$26,4) -> 0.6667 | Z30: 20.51 | AA30: =ROUND(Y30*Z30,2) -> 13.67 | AB30: 47
A31: Partida | B31: =ARQUITECTURA!A6 -> 03.01.02 | C31: MURO DE LADRILLO KK TIPO IV CABEZA M 1:4 E=1.5 CM | AA31: =ROUND(SUM(AA29:AA30),2) -> 32.96
A32: Rendimiento m2/día | B32: m2/dia | C32: M.O | D32: 10 | E32: EQ | F32: =D32 -> 10 | G32: Costo unitario directo | I32: m2 | J32: =J37+J43+J47 -> 166.43 | S32: Materiales
A33: Código | B33: Descripción Recurso | F33: Unidad | G33: Cuadrilla | H33: Cantidad | I33: Precio (S/.) | J33: Parcial (S/.) | S33: ALAMBRE NEGRO RECOCIDO BWG N 8 | W33: kg | Y33: 0.2 | Z33: 2.64 | AA33: =ROUND(Y33*Z33,2) -> 0.53 | AB33: 2
B34: Mano de Obra | S34: CLAVO C/CABEZA P/CONSTRUCCION D.PROMEDIO | W34: kg | Y34: 0.25 | Z34: 5.51 | AA34: =ROUND(Y34*Z34,2) -> 1.38 | AB34: 2
B35: OPERARIO | F35: hh | G35: 2 | H35: =ROUND(G35*8/$D$32,4) -> 1.6 | I35: 28.94 | J35: =ROUND(H35*I35,2) -> 46.3 | K35: 47 | S35: MADERA TORNILLO | W35: p2 | Y35: 3.5 | Z35: 5.8 | AA35: =ROUND(Y35*Z35,2) -> 20.3 | AB35: 43
B36: PEON | F36: hh | G36: 1 | H36: =ROUND(G36*8/$D$32,4) -> 0.8 | I36: 20.51 | J36: =ROUND(H36*I36,2) -> 16.41 | K36: 47 | AA36: =ROUND(SUM(AA33:AA35),2) -> 22.21
J37: =ROUND(SUM(J35:J36),2) -> 62.71 | S37: Equipos
B38: Materiales | S38: HERRAMIENTAS MANUALES | W38: %mo | Y38: 3 | Z38: =AA31 -> 32.96 | AA38: =ROUND(Y38%*Z38,2) -> 0.99 | AB38: 37
B39: AGUA | F39: m3 | H39: 0.015 | I39: 6.14 | J39: =ROUND(H39*I39,2) -> 0.09 | K39: 30 | AA39: =ROUND(SUM(AA38),2) -> 0.99
B40: ARENA GRUESA | F40: m3 | H40: 0.06 | I40: 47 | J40: =ROUND(H40*I40,2) -> 2.82 | K40: 4
B41: CEMENTO PORTLAND TIPO I (42.5 kg) | F41: bls | H41: 0.49 | I41: 24.52 | J41: =ROUND(H41*I41,2) -> 12.01 | K41: 21 | R41: Partida | S41: =A24 -> 100000000012 | T41: COLUMNETAS - ACERO fy=4200 kg/cm²
B42: LADRILLO KK TIPO IV 24X13X9 CM | F42: und | H42: 69 | I42: 1.02 | J42: =ROUND(H42*I42,2) -> 70.38 | K42: 17 | R42: Rendimiento m2/día | S42: m2/dia | T42: M.O | U42: 250 | V42: EQ | W42: =U42 -> 250 | X42: Costo unitario directo | Z42: m2 | AA42: =AA47+AA51+AA55 -> 5.54
J43: =ROUND(SUM(J39:J42),2) -> 85.3 | R43: Código | S43: Descripción Recurso | W43: Unidad | X43: Cuadrilla | Y43: Cantidad | Z43: Precio (S/.) | AA43: Parcial (S/.)
B44: Equipos | S44: Mano de Obra
B45: HERRAMIENTAS MANUALES | F45: %mo | H45: 3 | I45: =J37 -> 62.71 | J45: =ROUND(H45%*I45,2) -> 1.88 | K45: 37 | S45: OPERARIO | W45: hh | X45: 1 | Y45: =ROUND(X45*8/$U$42,4) -> 0.032 | Z45: 28.94 | AA45: =ROUND(Y45*Z45,2) -> 0.93 | AB45: 47
B46: ANDAMIO METALICO HOMOLOGADO | F46: d | G46: 2 | H46: =ROUND(G46*8/$D$32,4) -> 1.6 | I46: 10.34 | J46: =ROUND(H46*I46,2) -> 16.54 | K46: 39 | S46: OFICIAL | W46: hh | X46: 1 | Y46: =ROUND(X46*8/$U$42,4) -> 0.032 | Z46: 22.66 | AA46: =ROUND(Y46*Z46,2) -> 0.73 | AB46: 47
J47: =ROUND(SUM(J45:J46),2) -> 18.42 | AA47: =ROUND(SUM(AA45:AA46),2) -> 1.66
S48: Materiales
A49: Partida | B49: =ARQUITECTURA!A7 -> 03.01.03 | C49: TABIQUE DE DRYWALL E=0.15m | S49: ALAMBRE NEGRO RECOCIDO BWG N 16 | W49: kg | Y49: 0.03 | Z49: 2.64 | AA49: =ROUND(Y49*Z49,2) -> 0.08 | AB49: 2
A50: Rendimiento m2/día | B50: m2/dia | C50: M.O | D50: 14 | E50: EQ | F50: =D50 -> 14 | G50: Costo unitario directo | I50: m2 | J50: =J57+J68+J71 -> 141.08 | S50: ACERO CORRUGADO F'Y 4200 (G-60) PRECIO PROMEDIO | W50: kg | Y50: 1.05 | Z50: 3.42 | AA50: =ROUND(Y50*Z50,2) -> 3.59 | AB50: 3
A51: Código | B51: Descripción Recurso | F51: Unidad | G51: Cuadrilla | H51: Cantidad | I51: Precio (S/.) | J51: Parcial (S/.) | AA51: =ROUND(SUM(AA49:AA50),2) -> 3.67
B52: Mano de Obra | S52: Equipos
B53: CAPATAZ | F53: hh | G53: 0.1 | H53: =ROUND(G53*8/$D$50,4) -> 0.0571 | I53: 34.73 | J53: =ROUND(H53*I53,2) -> 1.98 | S53: HERRAMIENTAS MANUALES | W53: %mo | Y53: 3 | Z53: =AA47 -> 1.66 | AA53: =ROUND(Y53%*Z53,2) -> 0.05 | AB53: 37
B54: OPERARIO | F54: hh | G54: 1 | H54: =ROUND(G54*8/$D$50,4) -> 0.5714 | I54: 28.94 | J54: =ROUND(H54*I54,2) -> 16.54 | K54: 47 | S54: CIZALLA PARA CORTE DE FIERRO | W54: hh | X54: 1 | Y54: =ROUND(X54*8/$U$42,4) -> 0.032 | Z54: 5 | AA54: =ROUND(Y54*Z54,2) -> 0.16 | AB54: 37
B55: OFICIAL | F55: hh | G55: 1 | H55: =ROUND(G55*8/$D$50,4) -> 0.5714 | I55: 22.66 | J55: =ROUND(H55*I55,2) -> 12.95 | K55: 47 | AA55: =ROUND(SUM(AA53:AA54),2) -> 0.21
B56: PEON | F56: hh | G56: 1 | H56: =ROUND(G56*8/$D$50,4) -> 0.5714 | I56: 20.51 | J56: =ROUND(H56*I56,2) -> 11.72 | K56: 47
J57: =ROUND(SUM(J53:J56),2) -> 43.19 | R57: Partida | S57: =A25 -> 100000000013 | T57: VIGUETAS - CONCRETO f'c=210 kg/cm²
B58: Materiales | R58: Rendimiento m2/día | S58: m3/dia | T58: M.O | U58: 20 | V58: EQ | W58: =U58 -> 20 | X58: Costo unitario directo | Z58: m3 | AA58: =AA64+AA71+AA76 -> 377.33
B59: ANGULO ESQUINERO DE ACERO 30x30x0.30mm, L=2.40m | F59: und | H59: 0.4 | I59: 5.3 | J59: =ROUND(H59*I59,2) -> 2.12 | K59: 39 | R59: Código | S59: Descripción Recurso | W59: Unidad | X59: Cuadrilla | Y59: Cantidad | Z59: Precio (S/.) | AA59: Parcial (S/.)
B60: CLAVOS DISPARO 3.7x3.8mm | F60: und | H60: 8 | I60: 0.12 | J60: =ROUND(H60*I60,2) -> 0.96 | K60: 2 | S60: Mano de Obra
B61: PARANTE DE FoGo 89x38x0.45mm, L=3.00m | F61: und | H61: 2.2 | I61: 16.2 | J61: =ROUND(H61*I61,2) -> 35.64 | K61: 39 | S61: OPERARIO | W61: hh | X61: 2 | Y61: =ROUND(X61*8/$U$58,4) -> 0.8 | Z61: 28.94 | AA61: =ROUND(Y61*Z61,2) -> 23.15 | AB61: 47
B62: CINTA DE PAPEL PARA JUNTAS 2"x75m | F62: und | H62: 0.12 | I62: 9.24 | J62: =ROUND(H62*I62,2) -> 1.11 | K62: 39 | S62: OFICIAL | W62: hh | X62: 1 | Y62: =ROUND(X62*8/$U$58,4) -> 0.4 | Z62: 22.66 | AA62: =ROUND(Y62*Z62,2) -> 9.06 | AB62: 47
B63: MASILLA PARA DRYWALL (25Kg) | F63: bol | H63: 0.35 | I63: 39.9 | J63: =ROUND(H63*I63,2) -> 13.97 | K63: 30 | S63: PEON | W63: hh | X63: 8 | Y63: =ROUND(X63*8/$U$58,4) -> 3.2 | Z63: 20.51 | AA63: =ROUND(Y63*Z63,2) -> 65.63 | AB63: 47
B64: TORNILLO AUTORROSCANTE 1/2"x4mm | F64: und | H64: 6 | I64: 0.1 | J64: =ROUND(H64*I64,2) -> 0.6 | K64: 26 | AA64: =ROUND(SUM(AA61:AA63),2) -> 97.84
B65: TORNILLOS VOLCANITA 6x1" | F65: und | H65: 8 | I65: 0.02 | J65: =ROUND(H65*I65,2) -> 0.16 | K65: 26 | S65: Materiales
B66: PLACA DE YESO ESTANDAR GYPLAC e=5/8", 1.22 m x 2.44m | F66: und | H66: 0.7 | I66: 53 | J66: =ROUND(H66*I66,2) -> 37.1 | K66: 30 | S66: PIEDRA CHANCADA DE 1/2" Y 3/4" | W66: m3 | Y66: 0.55 | Z66: 55.08 | AA66: =ROUND(Y66*Z66,2) -> 30.29 | AB66: 5
B67: RIEL DE FoGo 90x25x0.45mm, L=3.00m | F67: und | H67: 0.65 | I67: 7.58 | J67: =ROUND(H67*I67,2) -> 4.93 | K67: 30 | S67: ARENA GRUESA | W67: m3 | Y67: 0.51 | Z67: 47 | AA67: =ROUND(Y67*Z67,2) -> 23.97 | AB67: 4
J68: =ROUND(SUM(J59:J67),2) -> 96.59 | S68: CEMENTO PORTLAND TIPO I (42.5 kg) | W68: bls | Y68: 8.43 | Z68: 24.52 | AA68: =ROUND(Y68*Z68,2) -> 206.7 | AB68: 21
B69: Equipos | S69: AGUA | W69: m3 | Y69: 0.185 | Z69: 6.14 | AA69: =ROUND(Y69*Z69,2) -> 1.14 | AB69: 30
B70: HERRAMIENTAS MANUALES | F70: %mo | H70: 3 | I70: =J57 -> 43.19 | J70: =ROUND(H70%*I70,2) -> 1.3 | K70: 37 | S70: GASOLINA DE 84 OCTANOS | W70: gal | Y70: 0.2 | Z70: 13.93 | AA70: =ROUND(Y70*Z70,2) -> 2.79 | AB70: 34
J71: =ROUND(SUM(J70:J70),2) -> 1.3 | AA71: =ROUND(SUM(AA66:AA70),2) -> 264.89
R72: Equipos
A73: Partida | B73: =ARQUITECTURA!A8 -> 03.01.04 | C73: MELAMINE | S73: HERRAMIENTAS MANUALES | W73: %mo | Y73: 3 | Z73: =AA64 -> 97.84 | AA73: =ROUND(Y73%*Z73,2) -> 2.94 | AB73: 37
A74: Rendimiento m2/día | B74: m2/dia | C74: M.O | D74: 8 | E74: EQ | F74: =D74 -> 8 | G74: Costo unitario directo | I74: m2 | J74: =J80+J86+J89 -> 204.42 | S74: MEZCLADORA DE CONCRETO TAMBOR 11 p3 18 HP | W74: hm | X74: 1 | Y74: =ROUND(X74*8/$U$58,4) -> 0.4 | Z74: 25.63 | AA74: =ROUND(Y74*Z74,2) -> 10.25 | AB74: 48
A75: Código | B75: Descripción Recurso | F75: Unidad | G75: Cuadrilla | H75: Cantidad | I75: Precio (S/.) | J75: Parcial (S/.) | S75: VIBRADOR A GASOLINA Y 1 3/4" , 4 HP | W75: hm | X75: 0.5 | Y75: =ROUND(X75*8/$U$58,4) -> 0.2 | Z75: 7.07 | AA75: =ROUND(Y75*Z75,2) -> 1.41 | AB75: 49
B76: Mano de Obra | AA76: =ROUND(SUM(AA73:AA75),2) -> 14.6
B77: CAPATAZ | F77: hh | G77: 0.1 | H77: =ROUND(G77*8/$D$74,4) -> 0.1 | I77: 34.73 | J77: =ROUND(H77*I77,2) -> 3.47
B78: OPERARIO | F78: hh | G78: 2 | H78: =ROUND(G78*8/$D$74,4) -> 2 | I78: 28.94 | J78: =ROUND(H78*I78,2) -> 57.88 | K78: 47 | R78: Partida | S78: =A26 -> 100000000014 | T78: VIGUETAS - ENCOFRADO y DESENCOFRADO
B79: OFICIAL | F79: hh | G79: 1 | H79: =ROUND(G79*8/$D$74,4) -> 1 | I79: 22.66 | J79: =ROUND(H79*I79,2) -> 22.66 | K79: 47 | R79: Rendimiento m2/día | S79: m2/dia | T79: M.O | U79: 10 | V79: EQ | W79: =U79 -> 10 | X79: Costo unitario directo | Z79: m2 | AA79: =AA85+AA90+AA93 -> 71.15
J80: =ROUND(SUM(J77:J79),2) -> 84.01 | R80: Código | S80: Descripción Recurso | W80: Unidad | X80: Cuadrilla | Y80: Cantidad | Z80: Precio (S/.) | AA80: Parcial (S/.)
B81: Materiales | S81: Mano de Obra
B82: TORNILLO AUTOROSCANTE CABEZA AVELLANADA 1/2" | F82: und | H82: 7 | I82: 1.01 | J82: =ROUND(H82*I82,2) -> 7.07 | K82: 26 | S82: OPERARIO | W82: hh | X82: 1 | Y82: =ROUND(X82*8/$U$79,4) -> 0.8 | Z82: 28.94 | AA82: =ROUND(Y82*Z82,2) -> 23.15 | AB82: 47
B83: MELAMINE 18MM (1.80X2.50) | F83: m2 | H83: 1.5 | I83: 39.9 | J83: =ROUND(H83*I83,2) -> 59.85 | K83: 39 | S83: OFICIAL | W83: hh | X83: 1 | Y83: =ROUND(X83*8/$U$79,4) -> 0.8 | Z83: 22.66 | AA83: =ROUND(Y83*Z83,2) -> 18.13 | AB83: 47
B84: PARANTE DE ALUMINIO DE 38.10X25.40X2.00MM | F84: m | H84: 4.5 | I84: 5.66 | J84: =ROUND(H84*I84,2) -> 25.47 | K84: 39 | S84: PEON | W84: hh | X84: 0.5 | Y84: =ROUND(X84*8/$U$79,4) -> 0.4 | Z84: 20.51 | AA84: =ROUND(Y84*Z84,2) -> 8.2 | AB84: 47
B85: BASTIDOR DE ALUMINIO DE 39.70X25.40X2.00MM | F85: m | H85: 4.8102 | I85: 5.79 | J85: =ROUND(H85*I85,2) -> 27.85 | K85: 39 | AA85: =ROUND(SUM(AA82:AA84),2) -> 49.48
J86: =ROUND(SUM(J82:J85),2) -> 120.24 | S86: Materiales
B87: Equipos | S87: ALAMBRE NEGRO RECOCIDO BWG N 8 | W87: kg | Y87: 0.3 | Z87: 2.64 | AA87: =ROUND(Y87*Z87,2) -> 0.79 | AB87: 2
B88: HERRAMIENTAS MANUALES | F88: %mo | H88: 0.2 | I88: =J80 -> 84.01 | J88: =ROUND(H88%*I88,2) -> 0.17 | K88: 37 | S88: CLAVO C/CABEZA P/CONSTRUCCION D.PROMEDIO | W88: kg | Y88: 0.31 | Z88: 5.51 | AA88: =ROUND(Y88*Z88,2) -> 1.71 | AB88: 2
J89: =ROUND(SUM(J88:J88),2) -> 0.17 | S89: MADERA TORNILLO | W89: p2 | Y89: 3.05 | Z89: 5.8 | AA89: =ROUND(Y89*Z89,2) -> 17.69 | AB89: 43
AA90: =ROUND(SUM(AA87:AA89),2) -> 20.19
A91: Partida | B91: =ARQUITECTURA!A9 -> 03.01.05 | C91: TABLERO C.A.C/CERAMICO | S91: Equipos
A92: Rendimiento m2/día | B92: m2/dia | C92: M.O | D92: 2 | E92: EQ | F92: =D92 -> 2 | G92: Costo unitario directo | I92: m2 | J92: =J99+J119+J122 -> 470.9 | S92: HERRAMIENTAS MANUALES | W92: %mo | Y92: 3 | Z92: =AA85 -> 49.48 | AA92: =ROUND(Y92%*Z92,2) -> 1.48 | AB92: 37
A93: Código | B93: Descripción Recurso | F93: Unidad | G93: Cuadrilla | H93: Cantidad | I93: Precio (S/.) | J93: Parcial (S/.) | AA93: =ROUND(SUM(AA92),2) -> 1.48
B94: Mano de Obra
B95: CAPATAZ | F95: hh | G95: 0.1 | H95: =ROUND(G95*8/$D$92,4) -> 0.4 | I95: 34.73 | J95: =ROUND(H95*I95,2) -> 13.89 | R95: Partida | S95: =A27 -> 100000000015 | T95: VIGUETAS - ACERO fy=4200 kg/cm²
B96: OPERARIO | F96: hh | G96: 1 | H96: =ROUND(G96*8/$D$92,4) -> 4 | I96: 28.94 | J96: =ROUND(H96*I96,2) -> 115.76 | K96: 47 | R96: Rendimiento m2/día | S96: m2/dia | T96: M.O | U96: 250 | V96: EQ | W96: =U96 -> 250 | X96: Costo unitario directo | Z96: m2 | AA96: =AA101+AA105+AA109 -> 5.54
B97: OFICIAL | F97: hh | G97: 0.5 | H97: =ROUND(G97*8/$D$92,4) -> 2 | I97: 22.66 | J97: =ROUND(H97*I97,2) -> 45.32 | K97: 47 | R97: Código | S97: Descripción Recurso | W97: Unidad | X97: Cuadrilla | Y97: Cantidad | Z97: Precio (S/.) | AA97: Parcial (S/.)
B98: PEON | F98: hh | G98: 1 | H98: =ROUND(G98*8/$D$92,4) -> 4 | I98: 20.51 | J98: =ROUND(H98*I98,2) -> 82.04 | K98: 47 | S98: Mano de Obra
J99: =ROUND(SUM(J95:J98),2) -> 257.01 | S99: OPERARIO | W99: hh | X99: 1 | Y99: =ROUND(X99*8/$U$96,4) -> 0.032 | Z99: 28.94 | AA99: =ROUND(Y99*Z99,2) -> 0.93 | AB99: 47
B100: Materiales | S100: OFICIAL | W100: hh | X100: 1 | Y100: =ROUND(X100*8/$U$96,4) -> 0.032 | Z100: 22.66 | AA100: =ROUND(Y100*Z100,2) -> 0.73 | AB100: 47
B101: ALAMBRE NEGRO RECOCIDO BWG N 16 | F101: kg | H101: 0.185 | I101: 2.64 | J101: =ROUND(H101*I101,2) -> 0.49 | K101: 2 | AA101: =ROUND(SUM(AA99:AA100),2) -> 1.66
B102: ALAMBRE NEGRO RECOCIDO BWG N 8 | F102: kg | H102: 0.151 | I102: 2.64 | J102: =ROUND(H102*I102,2) -> 0.4 | K102: 2 | S102: Materiales
B103: CLAVO C/CABEZA P/CONSTRUCCION D.PROMEDIO | F103: kg | H103: 0.267 | I103: 5.51 | J103: =ROUND(H103*I103,2) -> 1.47 | K103: 2 | S103: ALAMBRE NEGRO RECOCIDO BWG N 16 | W103: kg | Y103: 0.03 | Z103: 2.64 | AA103: =ROUND(Y103*Z103,2) -> 0.08 | AB103: 2
...

Sheet SANITARIAS
G2: Unidad | H2: Metrado | I2: C.U | J2: Parcial | K2: Total
A3: 4 | B3: INSTALACIONES SANITARIAS | K3: =J4+J9+J12+J14+J16+J18+J21+J23+J26 -> 647777.59
A4: 4.01 | B4: APARATOS SANITARIOS | J4: =SUM(J5:J8) -> 77385.49
A5: 04.01.01 | B5: INODORO | G5: und | H5: =ROUNDUP(SUM(BIBLIOTECA:INGRESO!G44),0) -> 159 | I5: =ROUND('APUS SANITARIAS'!J5,2) -> 193.31 | J5: =ROUND(H5*I5,2) -> 30736.29
A6: 04.01.02 | B6: URINARIO | G6: und | H6: =ROUNDUP(SUM(BIBLIOTECA:INGRESO!G45),0) -> 91 | I6: =ROUND('APUS SANITARIAS'!J12,2) -> 192.4 | J6: =ROUND(H6*I6,2) -> 17508.4
A7: 04.01.03 | B7: LAVATORIO | G7: und | H7: =ROUNDUP(SUM(BIBLIOTECA:INGRESO!G46),0) -> 165 | I7: =ROUND('APUS SANITARIAS'!J19,2) -> 67.52 | J7: =ROUND(H7*I7,2) -> 11140.8
A8: 04.01.04 | B8: LAVADEROS DE LIMPIEZA DE MAMPOSTERIA DE LADRILLO REVESTIDO CON CERAMICA + GRIFERIA | G8: und | H8: =ROUNDUP(SUM(BIBLIOTECA:INGRESO!G47),0) -> 24 | I8: =ROUND('APUS SANITARIAS'!J26,2) -> 750 | J8: =ROUND(H8*I8,2) -> 18000
A9: 4.02 | B9: SALIDAS DE AGUA | J9: =SUM(J10:J11) -> 37638.69
A10: 04.02.01 | B10: SALIDA DE AGUA FRIA PVC INC. TUBERIA Y ACCESORIOS 1/2" | G10: pto | H10: =ROUNDUP(SUM(BIBLIOTECA:INGRESO!G48),0) -> 193 | I10: =ROUND('APUS SANITARIAS'!J32,2) -> 131.73 | J10: =ROUND(H10*I10,2) -> 25423.89
A11: 04.02.02 | B11: SALIDA DE AGUA CALIENTE, CON TUBERIA CPVC (PROMEDIO) | G11: pto | H11: =ROUNDUP(SUM(BIBLIOTECA:INGRESO!G49),0) -> 58 | I11: =ROUND('APUS SANITARIAS'!J50,2) -> 210.6 | J11: =ROUND(H11*I11,2) -> 12214.8
A12: 4.03 | B12: VALVULAS | J12: =SUM(J13) -> 38400
A13: 04.03.01 | B13: VALVULAS COMPUERTAS, ESFERICAS Y CAJAS PARA VALVULAS | G13: und | H13: =ROUNDUP(SUM(BIBLIOTECA:INGRESO!G50),0) -> 192 | I13: =ROUND('APUS SANITARIAS'!J69,2) -> 200 | J13: =ROUND(H13*I13,2) -> 38400
A14: 4.04 | B14: EXTINTORES Y GABINETES | J14: =SUM(J15) -> 8595.52
A15: 04.04.01 | B15: EXTINTORES Y GABINETES | G15: und | H15: =ROUNDUP(SUM(BIBLIOTECA:INGRESO!G51),0) -> 16 | I15: =ROUND('APUS SANITARIAS'!J76,2) -> 537.22 | J15: =ROUND(H15*I15,2) -> 8595.52
A16: 4.05 | B16: SALIDAS DRENAJE PLUVIAL | J16: =SUM(J17) -> 790.75
A17: 04.05.01 | B17: DRENAJE PLUVIAL | G17: pto | H17: =ROUND(1.3*'Datos iniciales '!B3/75,0) -> 5 | I17: =ROUND('APUS SANITARIAS'!J91,2) -> 158.15 | J17: =ROUND(H17*I17,2) -> 790.75
A18: 4.06 | B18: DESAGÜE | J18: =SUM(J19:J20) -> 57487.18
A19: 04.06.01 | B19: SALIDA DE DESAGUE PVC-SAL 2" | G19: pto | H19: =ROUNDUP(SUM(BIBLIOTECA:INGRESO!G53),0) -> 202 | I19: =ROUND('APUS SANITARIAS'!J108,2) -> 138.65 | J19: =ROUND(H19*I19,2) -> 28007.3
A20: 04.06.02 | B20: SALIDA DE DESAGUE PVC-SAL 4" | G20: pto | H20: =ROUNDUP(SUM(BIBLIOTECA:INGRESO!G54),0) -> 202 | I20: =ROUND('APUS SANITARIAS'!J127,2) -> 145.94 | J20: =ROUND(H20*I20,2) -> 29479.88
A21: 4.07 | B21: VENTILACIÓN | J21: =SUM(J22) -> 28498.16
A22: 04.07.01 | B22: SALIDA DE VENTILACION (PROMEDIO) | G22: pto | H22: =ROUNDUP(SUM(BIBLIOTECA:INGRESO!G55),0) -> 202 | I22: =ROUND('APUS SANITARIAS'!J145,2) -> 141.08 | J22: =ROUND(H22*I22,2) -> 28498.16
A23: 4.08 | B23: ACCESORIOS | J23: =SUM(J24:J25) -> 17491.65
A24: 04.08.01 | B24: MEZCLADORA DE DUCHA | G24: und | H24: =ROUNDUP(SUM(BIBLIOTECA:INGRESO!G56),0) -> 55 | I24: =ROUND('APUS SANITARIAS'!J163,2) -> 214.34 | J24: =ROUND(H24*I24,2) -> 11788.7
A25: 04.08.02 | B25: JABONERA DE LOSA PARA EMPOTRAR | G25: und | H25: =ROUNDUP(SUM(BIBLIOTECA:INGRESO!G57),0) -> 55 | I25: =ROUND('APUS SANITARIAS'!J178,2) -> 103.69 | J25: =ROUND(H25*I25,2) -> 5702.95
A26: 4.09 | B26: INSTALACIONES EXTERIORES | J26: =SUM(J27:J29) -> 381490.15
A27: 04.09.01 | B27: SISTEMA DE BOMBEO DE PRESIÓN CONSTANTE | G27: Glb | H27: 1 | I27: =ROUND('APUS SANITARIAS'!J195,2) -> 79716.91 | J27: =ROUND(H27*I27,2) -> 79716.91
A28: 04.09.02 | B28: INSTALACIONES SANITARIAS EXTERIORES INC. CANALETAS DE EVACUACIÓN PLUVIAL | G28: Glb | H28: 1 | I28: =ROUND('APUS SANITARIAS'!J202,2) -> 131735.24 | J28: =ROUND(H28*I28,2) -> 131735.24
A29: 04.09.03 | B29: SISTEMA DE AGUA CONTRA INCENDIOS (RED CONTRA INCENDIOS, GABINETES) | G29: Glb | H29: 1 | I29: =ROUND('APUS SANITARIAS'!J209,2) -> 170038 | J29: =ROUND(H29*I29,2) -> 170038

Sheet APUS SANITARIAS
A4: Partida | B4: =SANITARIAS!A5 -> 04.01.01 | C4: INODORO
A5: Rendimiento m2/día | B5: und/dia | C5: M.O | D5: 35 | E5: EQ | F5: =D5 -> 35 | G5: Costo unitario directo | I5: und | J5: =J9 -> 193.31
A6: Código | B6: Descripción Recurso | F6: Unidad | G6: Cuadrilla | H6: Cantidad | I6: Precio (S/.) | J6: Parcial (S/.)
B7: Materiales
B8: INODORO | F8: und | H8: 0.3333 | I8: 580 | J8: =ROUND(H8*I8,2) -> 193.31 | K8: 10
J9: =ROUND(SUM(J8),2) -> 193.31
A11: Partida | B11: =SANITARIAS!A6 -> 04.01.02 | C11: URINARIO
A12: Rendimiento m2/día | B12: und/dia | C12: M.O | D12: 35 | E12: EQ | F12: =D12 -> 35 | G12: Costo unitario directo | I12: und | J12: =J16 -> 192.4
A13: Código | B13: Descripción Recurso | F13: Unidad | G13: Cuadrilla | H13: Cantidad | I13: Precio (S/.) | J13: Parcial (S/.)
B14: Materiales
B15: URINARIO | F15: und | H15: 0.3333 | I15: 577.26 | J15: =ROUND(H15*I15,2) -> 192.4 | K15: 10
J16: =ROUND(SUM(J15),2) -> 192.4
A18: Partida | B18: =SANITARIAS!A7 -> 04.01.03 | C18: LAVATORIO
A19: Rendimiento m2/día | B19: und/dia | C19: M.O | D19: 35 | E19: EQ | F19: =D19 -> 35 | G19: Costo unitario directo | I19: und | J19: =J23 -> 67.52
A20: Código | B20: Descripción Recurso | F20: Unidad | G20: Cuadrilla | H20: Cantidad | I20: Precio (S/.) | J20: Parcial (S/.)
B21: Materiales
B22: LAVATORIO | F22: und | H22: 0.3333 | I22: 202.57 | J22: =ROUND(H22*I22,2) -> 67.52 | K22: 10
J23: =ROUND(SUM(J22:J22),2) -> 67.52
A25: Partida | B25: =SANITARIAS!A8 -> 04.01.04 | C25: LAVADEROS DE LIMPIEZA DE MAMPOSTERIA DE LADRILLO REVESTIDO CON CERAMICA + GRIFERIA
A26: Rendimiento m2/día | B26: und/dia | C26: M.O | D26: 1 | E26: EQ | F26: =D26 -> 1 | G26: Costo unitario directo | I26: und | J26: =J30 -> 750
A27: Código | B27: Descripción Recurso | F27: Unidad | G27: Cuadrilla | H27: Cantidad | I27: Precio (S/.) | J27: Parcial (S/.)
B28: Materiales
B29: LAVADEROS DE LIMPIEZA DE MAMPOSTERIA DE LADRILLO REVESTIDO CON CERAMICA + GRIFERIA | F29: und | H29: 1 | I29: 750 | J29: =ROUND(H29*I29,2) -> 750 | K29: 10
J30: =ROUND(SUM(J29),2) -> 750
A31: Partida | B31: =SANITARIAS!A10 -> 04.02.01 | C31: SALIDA DE AGUA FRIA PVC INC. TUBERIA Y ACCESORIOS 1/2"
A32: Rendimiento m2/día | B32: pto/dia | C32: M.O | D32: 3 | E32: EQ | F32: =D32 -> 3 | G32: Costo unitario directo | I32: pto | J32: =J38+J44+J47 -> 131.73
A33: Código | B33: Descripción Recurso | F33: Unidad | G33: Cuadrilla | H33: Cantidad | I33: Precio (S/.) | J33: Parcial (S/.)
B34: Mano de Obra
B35: CAPATAZ | F35: hh | G35: 0.1 | H35: =ROUND(G35*8/$D$32,4) -> 0.2667 | I35: 34.73 | J35: =ROUND(H35*I35,2) -> 9.26 | K35: 47
B36: OPERARIO | F36: hh | G36: 1 | H36: =ROUND(G36*8/$D$32,4) -> 2.6667 | I36: 28.94 | J36: =ROUND(H36*I36,2) -> 77.17 | K36: 47
B37: PEON | F37: hh | G37: 0.5 | H37: =ROUND(G37*8/$D$32,4) -> 1.3333 | I37: 20.51 | J37: =ROUND(H37*I37,2) -> 27.35 | K37: 47
J38: =ROUND(SUM(J35:J37),2) -> 113.78
B39: Materiales
B40: PEGAMENTO PVC AZUL 128 ONZAS - OATEY | F40: gal | H40: 0.03 | I40: 189.66 | J40: =ROUND(H40*I40,2) -> 5.69 | K40: 30
B41: TUBO PVC AGUA S.P. CLASE 10 1/2" X 5m | F41: pza | H41: 0.412 | I41: 11.27 | J41: =ROUND(H41*I41,2) -> 4.64 | K41: 72
B42: CODO PVC AGUA DOBLE CAMPANA S.P. 1/2" X 90° | F42: pza | H42: 2 | I42: 1.19 | J42: =ROUND(H42*I42,2) -> 2.38 | K42: 72
B43: TEE PVC AGUA S.P. 1/2" | F43: pza | H43: 1 | I43: 1.83 | J43: =ROUND(H43*I43,2) -> 1.83 | K43: 72
J44: =ROUND(SUM(J40:J43),2) -> 14.54
B45: Equipos
B46: HERRAMIENTAS MANUALES | F46: %mo | H46: 3 | I46: =J38 -> 113.78 | J46: =ROUND(H46%*I46,2) -> 3.41 | K46: 37
J47: =ROUND(SUM(J46),2) -> 3.41
A49: Partida | B49: =SANITARIAS!A11 -> 04.02.02 | C49: SALIDA DE AGUA CALIENTE, CON TUBERIA CPVC (PROMEDIO)
A50: Rendimiento m2/día | B50: pto/dia | C50: M.O | D50: 2 | E50: EQ | F50: =D50 -> 2 | G50: Costo unitario directo | I50: pto | J50: =J56+J63+J66 -> 210.6
A51: Código | B51: Descripción Recurso | F51: Unidad | G51: Cuadrilla | H51: Cantidad | I51: Precio (S/.) | J51: Parcial (S/.)
B52: Mano de Obra
B53: CAPATAZ | F53: hh | G53: 0.1 | H53: =ROUND(G53*8/$D$50,4) -> 0.4 | I53: 34.73 | J53: =ROUND(H53*I53,2) -> 13.89 | K53: 47
B54: OPERARIO | F54: hh | G54: 1 | H54: =ROUND(G54*8/$D$50,4) -> 4 | I54: 28.94 | J54: =ROUND(H54*I54,2) -> 115.76 | K54: 47
B55: PEON | F55: hh | G55: 0.5 | H55: =ROUND(G55*8/$D$50,4) -> 2 | I55: 20.51 | J55: =ROUND(H55*I55,2) -> 41.02 | K55: 47
J56: =ROUND(SUM(J53:J55),2) -> 170.67
B57: Materiales
B58: PEGAMENTO P/TUBO CPVC ML | F58: gal | H58: 0.04 | I58: 400.54 | J58: =ROUND(H58*I58,2) -> 16.02 | K58: 30
B59: TUBO CPVC AGUA CALIENTE S.P. 1/2" X 5m | F59: pza | H59: 0.5 | I59: 26.1 | J59: =ROUND(H59*I59,2) -> 13.05 | K59: 72
B60: CODO ACERO GALV. TIPO ISO I 1/2" X 90° | F60: pza | H60: 1 | I60: 1 | J60: =ROUND(H60*I60,2) -> 1 | K60: 72
B61: CODO CPVC AGUA CALIENTE S.P/ 1/2" X 90° | F61: pza | H61: 2 | I61: 1.27 | J61: =ROUND(H61*I61,2) -> 2.54 | K61: 72
B62: TEE CPVC AGUA CALIENTE S.P/ 1/2" | F62: pza | H62: 1 | I62: 2.2 | J62: =ROUND(H62*I62,2) -> 2.2 | K62: 72
J63: =ROUND(SUM(J58:J62),2) -> 34.81
B64: Equipos
B65: HERRAMIENTAS MANUALES | F65: %mo | H65: 3 | I65: =J56 -> 170.67 | J65: =ROUND(H65%*I65,2) -> 5.12 | K65: 37
J66: =ROUND(SUM(J65),2) -> 5.12
A68: Partida | B68: =SANITARIAS!A13 -> 04.03.01 | C68: VALVULAS COMPUERTAS, ESFERICAS Y CAJAS PARA VALVULAS
A69: Rendimiento m2/día | B69: glb/dia | C69: M.O | D69: 1 | E69: EQ | F69: =D69 -> 1 | G69: Costo unitario directo | I69: glb | J69: =J73 -> 200
A70: Código | B70: Descripción Recurso | F70: Unidad | G70: Cuadrilla | H70: Cantidad | I70: Precio (S/.) | J70: Parcial (S/.)
B71: Materiales
B72: VALVULAS COMPUERTAS, ESFERICAS Y CAJAS PARA VALVULAS | F72: glb | H72: 1 | I72: 200 | J72: =ROUND(H72*I72,2) -> 200 | K72: 10
J73: =ROUND(SUM(J72),2) -> 200
A75: Partida | B75: =SANITARIAS!A15 -> 04.04.01 | C75: EXTINTORES Y GABINETES
A76: Rendimiento m2/día | B76: glb/dia | C76: M.O | D76: 5 | E76: EQ | F76: =D76 -> 5 | G76: Costo unitario directo | I76: glb | J76: =J82+J85+J88 -> 537.22
A77: Código | B77: Descripción Recurso | F77: Unidad | G77: Cuadrilla | H77: Cantidad | I77: Precio (S/.) | J77: Parcial (S/.)
B78: Mano de Obra
B79: CAPATAZ | F79: hh | G79: 0.1 | H79: =ROUND(G79*8/$D$76,4) -> 0.16 | I79: 34.73 | J79: =ROUND(H79*I79,2) -> 5.56 | K79: 47
B80: OPERARIO | F80: hh | G80: 1 | H80: =ROUND(G80*8/$D$76,4) -> 1.6 | I80: 28.94 | J80: =ROUND(H80*I80,2) -> 46.3 | K80: 47
B81: PEON | F81: hh | G81: 1 | H81: =ROUND(G81*8/$D$76,4) -> 1.6 | I81: 20.51 | J81: =ROUND(H81*I81,2) -> 32.82 | K81: 47
J82: =ROUND(SUM(J79:J81),2) -> 84.68
B83: Materiales
B84: CO2, DIOXIDO DE CARBONO - 10 LBS. Incluye gabinete | F84: und | H84: 1 | I84: 450 | J84: =ROUND(H84*I84,2) -> 450 | K84: 39
J85: =ROUND(SUM(J84),2) -> 450
B86: Equipos
B87: HERRAMIENTAS MANUALES | F87: %mo | H87: 3 | I87: =J82 -> 84.68 | J87: =ROUND(H87%*I87,2) -> 2.54 | K87: 37
J88: =ROUND(SUM(J87:J87),2) -> 2.54
A90: Partida | B90: =SANITARIAS!A17 -> 04.05.01 | C90: DRENAJE PLUVIAL
A91: Rendimiento m2/día | B91: pto/dia | C91: M.O | D91: 4 | E91: EQ | F91: =D91 -> 4 | G91: Costo unitario directo | I91: pto | J91: =J97+J102+J105 -> 158.15
A92: Código | B92: Descripción Recurso | F92: Unidad | G92: Cuadrilla | H92: Cantidad | I92: Precio (S/.) | J92: Parcial (S/.)
B93: Mano de Obra
B94: CAPATAZ | F94: hh | G94: 0.1 | H94: =ROUND(G94*8/$D$91,4) -> 0.2 | I94: 34.73 | J94: =ROUND(H94*I94,2) -> 6.95 | K94: 47
B95: OPERARIO | F95: hh | G95: 1 | H95: =ROUND(G95*8/$D$91,4) -> 2 | I95: 28.94 | J95: =ROUND(H95*I95,2) -> 57.88 | K95: 47
B96: PEON | F96: hh | G96: 1 | H96: =ROUND(G96*8/$D$91,4) -> 2 | I96: 20.51 | J96: =ROUND(H96*I96,2) -> 41.02 | K96: 47
J97: =ROUND(SUM(J94:J96),2) -> 105.85
B98: Materiales
B99: GRAVA DE 1/2" | F99: m3 | H99: 0.0324 | I99: 88.04 | J99: =ROUND(H99*I99,2) -> 2.85 | K99: 5
B100: TUBERIA PVC-SAP 3" | F100: m3 | H100: 0.3 | I100: 19.24 | J100: =ROUND(H100*I100,2) -> 5.77 | K100: 72
B101: REJILLA BRONCE Ø 3" ROSCADA | F101: und | H101: 2 | I101: 20.25 | J101: =ROUND(H101*I101,2) -> 40.5 | K101: 72
J102: =ROUND(SUM(J99:J101),2) -> 49.12
B103: Equipos
B104: HERRAMIENTAS MANUALES | F104: %mo | H104: 3 | I104: =J97 -> 105.85 | J104: =ROUND(H104%*I104,2) -> 3.18 | K104: 37
J105: =ROUND(SUM(J104:J104),2) -> 3.18
A107: Partida | B107: =SANITARIAS!A19 -> 04.06.01 | C107: SALIDA DE DESAGÜE PVC-SAL 2"
A108: Rendimiento m2/día | B108: pto/dia | C108: M.O | D108: 4 | E108: EQ | F108: =D108 -> 4 | G108: Costo unitario directo | I108: pto | J108: =J114+J121+J124 -> 138.65
A109: Código | B109: Descripción Recurso | F109: Unidad | G109: Cuadrilla | H109: Cantidad | I109: Precio (S/.) | J109: Parcial (S/.)
B110: Mano de Obra
B111: CAPATAZ | F111: hh | G111: 0.1 | H111: =ROUND(G111*8/$D$108,4) -> 0.2 | I111: 34.73 | J111: =ROUND(H111*I111,2) -> 6.95 | K111: 47
...

Sheet ELECTRICAS
G2: Unidad | H2: Metrado | I2: C.U | J2: Parcial | K2: Total
A3: 5 | B3: INSTALACIONES ELECTRICAS | K3: =J4+J9 -> 266619.99
A4: 5.01 | B4: SALIDAS | J4: =SUM(J5:J8) -> 181212.1
A5: 05.01.01 | B5: SALIDAS PARA ALUMBRADO, TOMACORRIENTES, FUERZA Y SEÑALES DÉBILES | G5: pto | H5: =ROUNDUP(SUM(BIBLIOTECA:INGRESO!G59),0) -> 449 | I5: =ROUND('APUS ELECTRICAS'!J5,2) -> 121.05 | J5: =ROUND(H5*I5,2) -> 54351.45
A6: 05.01.02 | B6: SALIDAS PARA TOMACORRIENTES | G6: pto | H6: =ROUNDUP(SUM(BIBLIOTECA:INGRESO!G60),0) -> 449 | I6: =ROUND('APUS ELECTRICAS'!J26,2) -> 163.75 | J6: =ROUND(H6*I6,2) -> 73523.75
A7: 05.01.03 | B7: SALIDAS PARA FUERZA Y SEÑALES DÉBILES | G7: pto | H7: =ROUNDUP(SUM(BIBLIOTECA:INGRESO!G61),0) -> 449 | I7: =ROUND('APUS ELECTRICAS'!J48,2) -> 118.3 | J7: =ROUND(H7*I7,2) -> 53116.7
A8: 05.01.04 | B8: SALIDAS TRIFÁSICAS | G8: pto | H8: =ROUNDUP(SUM(BIBLIOTECA:INGRESO!G62),0) -> 30 | I8: =ROUND('APUS ELECTRICAS'!J66,2) -> 7.34 | J8: =ROUND(H8*I8,2) -> 220.2
A9: 5.02 | B9: LÁMPARAS | J9: =SUM(J10:J15) -> 85407.89
A10: 05.02.01 | B10: ARTEFACTO DE ILUMINACIÓN P = 63 W L = 8000 LM | G10: und | H10: =ROUNDUP(SUM(BIBLIOTECA:INGRESO!G64),0) -> 141 | I10: =ROUND('APUS ELECTRICAS'!J74,2) -> 396.15 | J10: =ROUND(H10*I10,2) -> 55857.15
A11: 05.02.02 | B11: INSTALACIÓN DE ARTEFACTO DE ILUMINACIÓN, P=63 W L=8000 LM | G11: und | H11: =ROUNDUP(SUM(BIBLIOTECA:INGRESO!G65),0) -> 141 | I11: =ROUND('APUS ELECTRICAS'!J88,2) -> 125.39 | J11: =ROUND(H11*I11,2) -> 17679.99
A12: 05.02.03 | B12: PROYECTOR Y PANTALLA | G12: und | H12: =ROUNDUP(SUM(BIBLIOTECA:INGRESO!G66),0) -> 11 | I12: =ROUND('APUS ELECTRICAS'!J106,2) -> 143.11 | J12: =ROUND(H12*I12,2) -> 1574.21
A13: 05.02.04 | B13: EXTRACTORES DE AIRE | G13: und | H13: =ROUNDUP(SUM(BIBLIOTECA:INGRESO!G67),0) -> 3 | I13: =ROUND('APUS ELECTRICAS'!J114,2) -> 86.82 | J13: =ROUND(H13*I13,2) -> 260.46
A14: 05.02.05 | B14: SISTEMA DE BAJA TENSIÓN | G14: und | H14: =ROUND('Datos iniciales '!B69,2) -> 106 | I14: =ROUND('APUS ELECTRICAS'!J133,2) -> 87.34 | J14: =ROUND(H14*I14,2) -> 9258.04
A15: 05.02.06 | B15: SISTEMA DE MEDIA TENSIÓN | G15: und | H15: =ROUND('Datos iniciales '!B69,2) -> 106 | I15: =ROUND('APUS ELECTRICAS'!J140,2) -> 7.34 | J15: =ROUND(H15*I15,2) -> 778.04

Sheet APUS ELECTRICAS
A4: Partida | B4: =ELECTRICAS!A5 -> 05.01.01 | C4: SALIDAS PARA ALUMBRADO
A5: Rendimiento m2/día | B5: pto/dia | C5: M.O | D5: 5 | E5: EQ | F5: =D5 -> 5 | G5: Costo unitario directo | I5: pto | J5: =J11+J20+J23 -> 121.05
A6: Código | B6: Descripción Recurso | F6: Unidad | G6: Cuadrilla | H6: Cantidad | I6: Precio (S/.) | J6: Parcial (S/.)
B7: Mano de Obra
B8: CAPATAZ | F8: hh | G8: 0.1 | H8: =ROUND(G8*8/$D$5,4) -> 0.16 | I8: 34.73 | J8: =ROUND(H8*I8,2) -> 5.56 | K8: 47
B9: OPERARIO | F9: hh | G9: 1 | H9: =ROUND(G9*8/$D$5,4) -> 1.6 | I9: 28.94 | J9: =ROUND(H9*I9,2) -> 46.3 | K9: 47
B10: PEON | F10: hh | G10: 1 | H10: =ROUND(G10*8/$D$5,4) -> 1.6 | I10: 20.51 | J10: =ROUND(H10*I10,2) -> 32.82 | K10: 47
J11: =ROUND(SUM(J8:J10),2) -> 84.68
B12: Materiales
B13: TUBERÍA ELÉCTRICA SAP GRIS 3/4" X3 METROS NICOLL | F13: und | H13: 1.5 | I13: 10.68 | J13: =ROUND(H13*I13,2) -> 16.02 | K13: 72
B14: CURVA SAP 3/4" NICOLL | F14: und | H14: 3 | I14: 2.12 | J14: =ROUND(H14*I14,2) -> 6.36 | K14: 72
B15: UNIÓN SAP 3/4" NICOLL | F15: und | H15: 1 | I15: 0.68 | J15: =ROUND(H15*I15,2) -> 0.68 | K15: 72
B16: CONEXIÓN A CAJA PVC ELÉCTRICA SAP 3/4" | F16: und | H16: 1 | I16: 0.51 | J16: =ROUND(H16*I16,2) -> 0.51 | K16: 39
B17: CINTA AISLANTE ELÉCTRICA | F17: und | H17: 0.1 | I17: 4.66 | J17: =ROUND(H17*I17,2) -> 0.47 | K17: 30
B18: CAJA DE PASE OCTOGONAL F.G. PESADA 4" | F18: und | H18: 1 | I18: 1.69 | J18: =ROUND(H18*I18,2) -> 1.69 | K18: 39
B19: ALAMBRE TW 14 AWG | F19: m | H19: 9 | I19: 0.9 | J19: =ROUND(H19*I19,2) -> 8.1 | K19: 2
J20: =ROUND(SUM(J13:J19),2) -> 33.83
B21: Equipos
B22: HERRAMIENTAS MANUALES | F22: %mo | H22: 3 | I22: =J11 -> 84.68 | J22: =ROUND(H22%*I22,2) -> 2.54 | K22: 37
J23: =ROUND(SUM(J22),2) -> 2.54
A25: Partida | B25: =ELECTRICAS!A6 -> 05.01.02 | C25: SALIDAS PARA TOMACORRIENTE
A26: Rendimiento m2/día | B26: pto/dia | C26: M.O | D26: 4 | E26: EQ | F26: =D26 -> 4 | G26: Costo unitario directo | I26: pto | J26: =J32+J42+J45 -> 163.75
A27: Código | B27: Descripción Recurso | F27: Unidad | G27: Cuadrilla | H27: Cantidad | I27: Precio (S/.) | J27: Parcial (S/.)
B28: Mano de Obra
B29: CAPATAZ | F29: hh | G29: 0.1 | H29: =ROUND(G29*8/$D$26,4) -> 0.2 | I29: 34.73 | J29: =ROUND(H29*I29,2) -> 6.95 | K29: 47
B30: OPERARIO | F30: hh | G30: 1 | H30: =ROUND(G30*8/$D$26,4) -> 2 | I30: 28.94 | J30: =ROUND(H30*I30,2) -> 57.88 | K30: 47
B31: PEON | F31: hh | G31: 1 | H31: =ROUND(G31*8/$D$26,4) -> 2 | I31: 20.51 | J31: =ROUND(H31*I31,2) -> 41.02 | K31: 47
J32: =ROUND(SUM(J29:J31),2) -> 105.85
B33: Materiales
B34: TUBERÍA ELÉCTRICA SAP GRIS 3/4" X3 METROS NICOLL | F34: und | H34: 1.5 | I34: 10.68 | J34: =ROUND(H34*I34,2) -> 16.02 | K34: 72
B35: CURVA SAP 3/4" NICOLL | F35: und | H35: 3 | I35: 2.12 | J35: =ROUND(H35*I35,2) -> 6.36 | K35: 72
B36: UNIÓN SAP 3/4" NICOLL | F36: und | H36: 1 | I36: 0.68 | J36: =ROUND(H36*I36,2) -> 0.68 | K36: 72
B37: CONEXIÓN A CAJA PVC ELÉCTRICA SAP 3/4" | F37: und | H37: 2 | I37: 0.51 | J37: =ROUND(H37*I37,2) -> 1.02 | K37: 39
B38: CINTA AISLANTE ELÉCTRICA | F38: und | H38: 0.1 | I38: 4.66 | J38: =ROUND(H38*I38,2) -> 0.47 | K38: 30
B39: TOMACORRIENTE DOBLE UNIVERSAL 2 POLOS 10A 250VAC | F39: und | H39: 1.05 | I39: 16.02 | J39: =ROUND(H39*I39,2) -> 16.82 | K39: 11
B40: CAJA DE PASE RECTANGULAR F.G. PESADA 50 x100 mm | F40: und | H40: 1.05 | I40: 5 | J40: =ROUND(H40*I40,2) -> 5.25 | K40: 39
B41: ALAMBRE TW 14 AWG | F41: m | H41: 9 | I41: 0.9 | J41: =ROUND(H41*I41,2) -> 8.1 | K41: 2
J42: =ROUND(SUM(J34:J41),2) -> 54.72
B43: Equipos
B44: HERRAMIENTAS MANUALES | F44: %mo | H44: 3 | I44: =J32 -> 105.85 | J44: =ROUND(H44%*I44,2) -> 3.18 | K44: 37
J45: =ROUND(SUM(J44),2) -> 3.18
A47: Partida | B47: =ELECTRICAS!A7 -> 05.01.03 | C47: SALIDAS PARA FUERZAS Y SEÑALES DEBILES
A48: Rendimiento m2/día | B48: pto/dia | C48: M.O | D48: 3 | E48: EQ | F48: =D48 -> 3 | G48: Costo unitario directo | I48: pto | J48: =J53+J60+J63 -> 118.3
A49: Código | B49: Descripción Recurso | F49: Unidad | G49: Cuadrilla | H49: Cantidad | I49: Precio (S/.) | J49: Parcial (S/.)
B50: Mano de Obra
B51: CAPATAZ | F51: hh | G51: 0.1 | H51: =ROUND(G51*8/$D$48,4) -> 0.2667 | I51: 34.73 | J51: =ROUND(H51*I51,2) -> 9.26 | K51: 47
B52: OPERARIO | F52: hh | G52: 1 | H52: =ROUND(G52*8/$D$48,4) -> 2.6667 | I52: 28.94 | J52: =ROUND(H52*I52,2) -> 77.17 | K52: 47
J53: =ROUND(SUM(J51:J52),2) -> 86.43
B54: Materiales
B55: TUBERÍA ELÉCTRICA SAP GRIS 3/4" X3 METROS NICOLL | F55: und | H55: 2 | I55: 10.68 | J55: =ROUND(H55*I55,2) -> 21.36 | K55: 72
B56: CURVA SAP 3/4" NICOLL | F56: und | H56: 1 | I56: 2.12 | J56: =ROUND(H56*I56,2) -> 2.12 | K56: 72
B57: UNIÓN SAP 3/4" NICOLL | F57: und | H57: 2 | I57: 0.68 | J57: =ROUND(H57*I57,2) -> 1.36 | K57: 72
B58: CONEXIÓN A CAJA PVC ELÉCTRICA SAP 3/4" | F58: und | H58: 2 | I58: 0.51 | J58: =ROUND(H58*I58,2) -> 1.02 | K58: 39
B59: CAJA DE PASE RECTANGULAR F.G. LIVIANA 50 x100 mm | F59: und | H59: 1.05 | I59: 1.61 | J59: =ROUND(H59*I59,2) -> 1.69 | K59: 39
J60: =ROUND(SUM(J55:J59),2) -> 27.55
B61: Equipos
B62: HERRAMIENTAS MANUALES | F62: %mo | H62: 5 | I62: =J53 -> 86.43 | J62: =ROUND(H62%*I62,2) -> 4.32 | K62: 37
J63: =ROUND(SUM(J62),2) -> 4.32
A65: Partida | B65: =ELECTRICAS!A8 -> 05.01.04 | C65: SALIDA TRIFASICA
A66: Rendimiento m2/día | B66: ptp/dia | C66: M.O | D66: 1 | E66: EQ | F66: =D66 -> 1 | G66: Costo unitario directo | I66: pto | J66: =+J70 -> 7.34
A67: Código | B67: Descripción Recurso | F67: Unidad | G67: Cuadrilla | H67: Cantidad | I67: Precio (S/.) | J67: Parcial (S/.)
B68: Materiales
B69: SALIDA TRIFASICA | F69: pto | H69: 1 | I69: 7.34 | J69: =ROUND(H69*I69,2) -> 7.34 | K69: 39
J70: =ROUND(SUM(J69:J69),2) -> 7.34
A73: Partida | B73: =ELECTRICAS!A10 -> 05.02.01 | C73: ARTEFACTO DE ILUMINACIÓN P = 63 W L = 8000 LM
A74: Rendimiento m2/día | B74: un/dia | C74: M.O | D74: 10 | E74: EQ | F74: =D74 -> 10 | G74: Costo unitario directo | I74: und | J74: =+J79+J82+J85 -> 396.15
A75: Código | B75: Descripción Recurso | F75: Unidad | G75: Cuadrilla | H75: Cantidad | I75: Precio (S/.) | J75: Parcial (S/.)
B76: Mano de Obra
B77: CAPATAZ | F77: hh | G77: 0.1 | H77: =ROUND(G77*8/$D$74,4) -> 0.08 | I77: 34.73 | J77: =ROUND(H77*I77,2) -> 2.78 | K77: 47
B78: OPERARIO | F78: hh | G78: 0.5 | H78: =ROUND(G78*8/$D$74,4) -> 0.4 | I78: 28.94 | J78: =ROUND(H78*I78,2) -> 11.58 | K78: 47
J79: =ROUND(SUM(J77:J78),2) -> 14.36
B80: Materiales
B81: ARTEFACTO DE ILUMINACIÓN P=63W | F81: und | H81: 1 | I81: 381.36 | J81: =ROUND(H81*I81,2) -> 381.36 | K81: 12
J82: =ROUND(SUM(J81:J81),2) -> 381.36
B83: Equipos
B84: HERRAMIENTAS MANUALES | F84: %mo | H84: 3 | I84: =J79 -> 14.36 | J84: =ROUND(H84%*I84,2) -> 0.43 | K84: 37
J85: =ROUND(SUM(J84),2) -> 0.43
A87: Partida | B87: =ELECTRICAS!A11 -> 05.02.02 | C87: INSTALACIÓN DE ARTEFACTO DE ILUMINACIÓN, P=63 W L=8000 LM
A88: Rendimiento m2/día | B88: un/dia | C88: M.O | D88: 6 | E88: EQ | F88: =D88 -> 6 | G88: Costo unitario directo | I88: und | J88: =+J94+J99+J103 -> 125.39
A89: Código | B89: Descripción Recurso | F89: Unidad | G89: Cuadrilla | H89: Cantidad | I89: Precio (S/.) | J89: Parcial (S/.)
B90: Mano de Obra
B91: OPERARIO | F91: hh | G91: 1.1 | H91: =ROUND(G91*8/$D$88,4) -> 1.4667 | I91: 28.94 | J91: =ROUND(H91*I91,2) -> 42.45 | K91: 47
B92: OFICIAL | F92: hh | G92: 1 | H92: =ROUND(G92*8/$D$88,4) -> 1.3333 | I92: 22.66 | J92: =ROUND(H92*I92,2) -> 30.21 | K92: 47
B93: PEON | F93: hh | G93: 1 | H93: =ROUND(G93*8/$D$88,4) -> 1.3333 | I93: 20.51 | J93: =ROUND(H93*I93,2) -> 27.35 | K93: 47
J94: =ROUND(SUM(J91:J93),2) -> 100.01
B95: Materiales
B96: ALAMBRE NEGRO RECOCIDO BWG N 8 | F96: rll | H96: 0.05 | I96: 2.64 | J96: =ROUND(H96*I96,2) -> 0.13 | K96: 2
B97: CINTA AISLANTE 20 MM X 1700 | F97: rll | H97: 0.1 | I97: 5.08 | J97: =ROUND(H97*I97,2) -> 0.51 | K97: 30
B98: CINTILLOS AMARRACABLE 4.8 MM X 250 MM | F98: bls | H98: 0.01 | I98: 45 | J98: =ROUND(H98*I98,2) -> 0.45 | K98: 39
J99: =ROUND(SUM(J96:J98),2) -> 1.09
B100: Equipos
B101: HERRAMIENTAS MANUALES | F101: %mo | H101: 5 | I101: =J94 -> 100.01 | J101: =ROUND(H101%*I101,2) -> 5 | K101: 37
B102: ESCALERA DE FIBRA DE ALUMINIO | F102: hm | G102: 0.5 | H102: =ROUND(G102*8/$D$88,4) -> 0.6667 | I102: 28.94 | J102: =ROUND(H102*I102,2) -> 19.29 | K102: 39
J103: =ROUND(SUM(J101:J102),2) -> 24.29
A105: Partida | B105: =ELECTRICAS!A12 -> 05.02.03 | C105: PROYECTOR Y PANTALLA
A106: Rendimiento m2/día | B106: pto/dia | C106: M.O | D106: 1 | E106: EQ | F106: =D106 -> 1 | G106: Costo unitario directo | I106: pto | J106: =+J110 -> 143.11
A107: Código | B107: Descripción Recurso | F107: Unidad | G107: Cuadrilla | H107: Cantidad | I107: Precio (S/.) | J107: Parcial (S/.)
B108: Materiales
B109: SALIDA PROYECTOR | F109: pto | H109: 1 | I109: 143.11 | J109: =ROUND(H109*I109,2) -> 143.11 | K109: 39
J110: =ROUND(SUM(J109:J109),2) -> 143.11
...

Sheet COMUNICACIONES
G2: Unidad | H2: Metrado | I2: C.U | J2: Parcial | K2: Total
A3: 6 | B3: INSTALACIONES COMUNICACIONES | K3: =J4+J16+J32+J36+J39 -> 141077.34
A4: 6.01 | B4: CANALIZACIÓN, CONDUCTOS Y/O TUBERÍAS | J4: =SUM(J5:J15) -> 21248.12
A5: 06.01.01 | B5: INSTALACION DE PUNTOS DE RED EN PISO | G5: und | H5: =ROUNDUP(SUM(BIBLIOTECA:INGRESO!G72),0) -> 26 | I5: =ROUND('APUS COMUNICACIONES'!J5,2) -> 279.85 | J5: =ROUND(H5*I5,2) -> 7276.1
A6: 06.01.02 | B6: INSTALACION DE PUNTOS DE RED EN PARED | G6: und | H6: =ROUNDUP(SUM(BIBLIOTECA:INGRESO!G73),0) -> 26 | I6: =ROUND('APUS COMUNICACIONES'!J23,2) -> 95.84 | J6: =ROUND(H6*I6,2) -> 2491.84
A7: 06.01.03 | B7: INSTALACION DE PUNTOS DE RED EN CIELO RASO | G7: und | H7: =ROUNDUP(SUM(BIBLIOTECA:INGRESO!G74),0) -> 26 | I7: =ROUND('APUS COMUNICACIONES'!J41,2) -> 95.84 | J7: =ROUND(H7*I7,2) -> 2491.84
A8: 06.01.04 | B8: TUBERIA PVC-P ELÉCTRICA Ø50mm, NTP 339.006 | G8: m | H8: =ROUND(SUM(BIBLIOTECA:INGRESO!G75),2) -> 1.56 | I8: =ROUND('APUS COMUNICACIONES'!J59,2) -> 26.42 | J8: =ROUND(H8*I8,2) -> 41.22
A9: 06.01.05 | B9: TUBERIA PVC-P ELÉCTRICA Ø40mm, NTP 339.006 | G9: m | H9: =ROUND(SUM(BIBLIOTECA:INGRESO!G76),2) -> 35.36 | I9: =ROUND('APUS COMUNICACIONES'!J77,2) -> 25.01 | J9: =ROUND(H9*I9,2) -> 884.35
A10: 06.01.06 | B10: TUBERIA PVC-P ELÉCTRICA Ø25mm, NTP 339.006 | G10: m | H10: =ROUND(SUM(BIBLIOTECA:INGRESO!G77),2) -> 142.48 | I10: =ROUND('APUS COMUNICACIONES'!J95,2) -> 19.23 | J10: =ROUND(H10*I10,2) -> 2739.89
A11: 06.01.07 | B11: TUBERIA PVC-P ELÉCTRICA Ø15mm, NTP 339.006 | G11: m | H11: =ROUND(SUM(BIBLIOTECA:INGRESO!G78),2) -> 0.78 | I11: =ROUND('APUS COMUNICACIONES'!J113,2) -> 16.37 | J11: =ROUND(H11*I11,2) -> 12.77
A12: 06.01.08 | B12: CAJA DE PASE FºGº 300x300x100mm | G12: und | H12: =ROUNDUP(SUM(BIBLIOTECA:INGRESO!G79),0) -> 26 | I12: =ROUND('APUS COMUNICACIONES'!J131,2) -> 62.67 | J12: =ROUND(H12*I12,2) -> 1629.42
A13: 06.01.09 | B13: CAJA DE PASE FºGº 200x200x100mm | G13: und | H13: =ROUNDUP(SUM(BIBLIOTECA:INGRESO!G80),0) -> 26 | I13: =ROUND('APUS COMUNICACIONES'!J146,2) -> 58.85 | J13: =ROUND(H13*I13,2) -> 1530.1
A14: 06.01.10 | B14: CAJA DE PASE FºGº 100x100x100mm | G14: und | H14: =ROUNDUP(SUM(BIBLIOTECA:INGRESO!G81),0) -> 26 | I14: =ROUND('APUS COMUNICACIONES'!J161,2) -> 57.88 | J14: =ROUND(H14*I14,2) -> 1504.88
A15: 06.01.11 | B15: BANDEJA PORTACABLE 200x54 P/COMUNICACIÓN | G15: m | H15: =ROUND(SUM(BIBLIOTECA:INGRESO!G82),2) -> 6.5 | I15: =ROUND('APUS COMUNICACIONES'!J176,2) -> 99.34 | J15: =ROUND(H15*I15,2) -> 645.71
A16: 6.02 | B16: SISTEMA ESTRUCTURADO Y NETWORKING | J16: =SUM(J17:J31) -> 63099.67
A17: 06.02.01 | B17: SUMINISTRO E INSTALACIÓN DE RECEPTOR MO ISP | G17: und | H17: 1 | I17: =ROUND('APUS COMUNICACIONES'!J191,2) -> 2842.98 | J17: =ROUND(H17*I17,2) -> 2842.98
A18: 06.02.02 | B18: SUMINISTRO E INSTALACIÓN DE ROUTER | G18: und | H18: 1 | I18: =ROUND('APUS COMUNICACIONES'!J205,2) -> 813.09 | J18: =ROUND(H18*I18,2) -> 813.09
A19: 06.02.03 | B19: SUMINISTRO E INSTALACION SWITCH GIGABIT 48 PORT | G19: und | H19: 1 | I19: =ROUND('APUS COMUNICACIONES'!J219,2) -> 2276.01 | J19: =ROUND(H19*I19,2) -> 2276.01
A20: 06.02.04 | B20: SUMINISTRO E INSTALACION DE PATCH PANEL 48 PORT | G20: und | H20: 1 | I20: =ROUND('APUS COMUNICACIONES'!J233,2) -> 460.54 | J20: =ROUND(H20*I20,2) -> 460.54
A21: 06.02.05 | B21: SUMINISTRO E INSTALACION DE SERVIDOR | G21: und | H21: 1 | I21: =ROUND('APUS COMUNICACIONES'!J247,2) -> 15436.01 | J21: =ROUND(H21*I21,2) -> 15436.01
A22: 06.02.06 | B22: SUMINISTRO E INSTALACION DE SERVIDOR NVR | G22: und | H22: 1 | I22: =ROUND('APUS COMUNICACIONES'!J261,2) -> 14367.01 | J22: =ROUND(H22*I22,2) -> 14367.01
A23: 06.02.07 | B23: SUMINISTRO E INSTALACION DE SWITH POE 16 PORT | G23: und | H23: 1 | I23: =ROUND('APUS COMUNICACIONES'!J275,2) -> 1343.81 | J23: =ROUND(H23*I23,2) -> 1343.81
A24: 06.02.08 | B24: SUMINISTRO E INSTALACION DE PATCH PANEL 24 PORT | G24: und | H24: 1 | I24: =ROUND('APUS COMUNICACIONES'!J289,2) -> 456.64 | J24: =ROUND(H24*I24,2) -> 456.64
A25: 06.02.09 | B25: SUMINISTRO E INSTALACION DE BANDEJA 19" | G25: und | H25: 1 | I25: =ROUND('APUS COMUNICACIONES'!J303,2) -> 168.56 | J25: =ROUND(H25*I25,2) -> 168.56
A26: 06.02.10 | B26: SUMINISTRO E INSTALACION DE BANDEJA EQUIPO ALARMAS | G26: und | H26: 1 | I26: =ROUND('APUS COMUNICACIONES'!J318,2) -> 138.47 | J26: =ROUND(H26*I26,2) -> 138.47
A27: 06.02.11 | B27: SUMINISTRO E INSTALACION DE BANDEJA TELEFONIA IP PBX | G27: und | H27: 1 | I27: =ROUND('APUS COMUNICACIONES'!J333,2) -> 146.57 | J27: =ROUND(H27*I27,2) -> 146.57
A28: 06.02.12 | B28: SUMINISTRO E INSTALACION DE BANDEJA 19" | G28: und | H28: 1 | I28: =ROUND('APUS COMUNICACIONES'!J348,2) -> 165.77 | J28: =ROUND(H28*I28,2) -> 165.77
A29: 06.02.13 | B29: SUMINISTRO E INSTALACION DE UPS 3 KVA, MONOFASICO / 2 RU | G29: und | H29: 1 | I29: =ROUND('APUS COMUNICACIONES'!J363,2) -> 6296.12 | J29: =ROUND(H29*I29,2) -> 6296.12
A30: 06.02.14 | B30: CONEXIÓN DE GABINETE DE PISO 42 RU | G30: und | H30: 1 | I30: =ROUND('APUS COMUNICACIONES'!J377,2) -> 8654.52 | J30: =ROUND(H30*I30,2) -> 8654.52
A31: 06.02.15 | B31: CONEXIÓN DE GABINETE 42RU Y COMPONENTES DE REDES | G31: und | H31: 1 | I31: =ROUND('APUS COMUNICACIONES'!J391,2) -> 9533.57 | J31: =ROUND(H31*I31,2) -> 9533.57
A32: 6.03 | B32: SISTEMA CCTV | J32: =SUM(J33:J35) -> 40291.79
A33: 06.03.01 | B33: SERVIDOR NVR 1RU | G33: und | H33: 1 | I33: =ROUND('APUS COMUNICACIONES'!J408,2) -> 8346.11 | J33: =ROUND(H33*I33,2) -> 8346.11
A34: 06.03.02 | B34: VIDEOCAMARA TUBULAR IP | G34: und | H34: =ROUNDUP(SUM(BIBLIOTECA:INGRESO!G85),0) -> 26 | I34: =ROUND('APUS COMUNICACIONES'!J422,2) -> 670.77 | J34: =ROUND(H34*I34,2) -> 17440.02
A35: 06.03.03 | B35: VIDEOCAMARA DOMO IP | G35: und | H35: =ROUNDUP(SUM(BIBLIOTECA:INGRESO!G86),0) -> 26 | I35: =ROUND('APUS COMUNICACIONES'!J440,2) -> 557.91 | J35: =ROUND(H35*I35,2) -> 14505.66
A36: 6.04 | B36: SISTEMA MEGAFONÍA (PERIFONEO) | J36: =SUM(J37:J38) -> 11049.87
A37: 06.04.01 | B37: AMPLIFICADOR DE AUDIO DE 100W | G37: und | H37: 1 | I37: =ROUND('APUS COMUNICACIONES'!J455,2) -> 526.63 | J37: =ROUND(H37*I37,2) -> 526.63
A38: 06.04.02 | B38: PARLANTE IP DE TECHO | G38: und | H38: =ROUNDUP(SUM(BIBLIOTECA:INGRESO!G88),0) -> 26 | I38: =ROUND('APUS COMUNICACIONES'!J469,2) -> 404.74 | J38: =ROUND(H38*I38,2) -> 10523.24
A39: 6.05 | B39: SISTEMA DACI (DETECCIÓN Y ALARMA CONTRA INCENDIO) | J39: =SUM(J40:J42) -> 5387.89
A40: 06.05.01 | B40: EQUIPAMIENTO DE UNIDAD CENTRAL DEL SISTEMA DE ALARMA CONTRA INCENDIO | G40: und | H40: 1 | I40: =ROUND('APUS COMUNICACIONES'!J484,2) -> 949.43 | J40: =ROUND(H40*I40,2) -> 949.43
A41: 06.05.02 | B41: SUMINISTRO E INSTALACION DE DETECTOR DE HUMO | G41: und | H41: =ROUNDUP(SUM(BIBLIOTECA:INGRESO!G90),0) -> 26 | I41: =ROUND('APUS COMUNICACIONES'!J497,2) -> 106.38 | J41: =ROUND(H41*I41,2) -> 2765.88
A42: 06.05.03 | B42: SALIDA PARA ALARMA CONTRA INCENDIO | G42: und | H42: =ROUNDUP(SUM(BIBLIOTECA:INGRESO!G91),0) -> 26 | I42: =ROUND('APUS COMUNICACIONES'!J513,2) -> 64.33 | J42: =ROUND(H42*I42,2) -> 1672.58

Sheet APUS COMUNICACIONES
A4: Partida | B4: =COMUNICACIONES!A5 -> 06.01.01 | C4: INSTALACION DE PUNTOS DE RED EN PISO
A5: Rendimiento m2/día | B5: und/dia | C5: M.O | D5: 8 | E5: EQ | F5: =D5 -> 8 | G5: Costo unitario directo | I5: und | J5: =J10+J17+J20 -> 279.85
A6: Código | B6: Descripción Recurso | F6: Unidad | G6: Cuadrilla | H6: Cantidad | I6: Precio (S/.) | J6: Parcial (S/.)
B7: Mano de Obra
B8: OFICIAL | F8: hh | G8: 1 | H8: =ROUND(G8*8/$D$5,4) -> 1 | I8: 22.66 | J8: =ROUND(H8*I8,2) -> 22.66 | K8: 47
B9: TECNICO ESPECIALISTA EN TELECOMUNICACIONES | F9: hh | G9: 1 | H9: =ROUND(G9*8/$D$5,4) -> 1 | I9: 26.11 | J9: =ROUND(H9*I9,2) -> 26.11 | K9: 47
J10: =ROUND(SUM(J8:J9),2) -> 48.77
B11: Materiales
B12: JACK DE DATOS CAT CAT6A (BLANCO) P/CAJA POP UP | F12: und | H12: 2 | I12: 40 | J12: =ROUND(H12*I12,2) -> 80 | K12: 39
B13: CAJA GALV. TIPO GANG INC. TAPA GANG | F13: und | H13: 1 | I13: 7 | J13: =ROUND(H13*I13,2) -> 7 | K13: 39
B14: CAJA POP-UP PARA 4 MOD.MOSAIC.ALUMINIO MATE | F14: und | H14: 1 | I14: 140 | J14: =ROUND(H14*I14,2) -> 140 | K14: 39
B15: CONECTOR PVC-P (ELEC.) 25mm | F15: und | H15: 1 | I15: 0.93 | J15: =ROUND(H15*I15,2) -> 0.93 | K15: 72
B16: ETIQUETA PARA JACK DE DATOS | F16: und | H16: 1 | I16: 1.69 | J16: =ROUND(H16*I16,2) -> 1.69 | K16: 39
J17: =ROUND(SUM(J12:J16),2) -> 229.62
B18: Equipos
B19: HERRAMIENTAS MANUALES | F19: %mo | H19: 3 | I19: =J10 -> 48.77 | J19: =ROUND(H19%*I19,2) -> 1.46 | K19: 37
J20: =ROUND(SUM(J19),2) -> 1.46
A22: Partida | B22: =COMUNICACIONES!A6 -> 06.01.02 | C22: INSTALACION DE PUNTOS DE RED EN PARED
A23: Rendimiento m2/día | B23: und/dia | C23: M.O | D23: 8 | E23: EQ | F23: =D23 -> 8 | G23: Costo unitario directo | I23: und | J23: =J28+J35+J38 -> 95.84
A24: Código | B24: Descripción Recurso | F24: Unidad | G24: Cuadrilla | H24: Cantidad | I24: Precio (S/.) | J24: Parcial (S/.)
B25: Mano de Obra
B26: OFICIAL | F26: hh | G26: 1 | H26: =ROUND(G26*8/$D$23,4) -> 1 | I26: 22.66 | J26: =ROUND(H26*I26,2) -> 22.66 | K26: 47
B27: TECNICO ESPECIALISTA EN TELECOMUNICACIONES | F27: hh | G27: 1 | H27: =ROUND(G27*8/$D$23,4) -> 1 | I27: 26.11 | J27: =ROUND(H27*I27,2) -> 26.11 | K27: 47
J28: =ROUND(SUM(J26:J27),2) -> 48.77
B29: Materiales
B30: JACK DE DATOS CAT CAT6A (BLANCO) | F30: und | H30: 2 | I30: 12.63 | J30: =ROUND(H30*I30,2) -> 25.26 | K30: 39
B31: CAJA GALV. RECTANGULAR PESADA DE 4"x2"x21/4" | F31: und | H31: 1 | I31: 3.73 | J31: =ROUND(H31*I31,2) -> 3.73 | K31: 39
B32: CONECTOR PVC-P (ELEC.) 25mm | F32: und | H32: 1 | I32: 0.93 | J32: =ROUND(H32*I32,2) -> 0.93 | K32: 72
B33: ETIQUETA PARA JACK DE DATOS | F33: und | H33: 1 | I33: 1.69 | J33: =ROUND(H33*I33,2) -> 1.69 | K33: 39
B34: FACE PLATE DOBLE PARA DATOS RJ45 BLANCO | F34: und | H34: 1 | I34: 14 | J34: =ROUND(H34*I34,2) -> 14 | K34: 39
J35: =ROUND(SUM(J30:J34),2) -> 45.61
B36: Equipos
B37: HERRAMIENTAS MANUALES | F37: %mo | H37: 3 | I37: =J28 -> 48.77 | J37: =ROUND(H37%*I37,2) -> 1.46 | K37: 37
J38: =ROUND(SUM(J37),2) -> 1.46
A40: Partida | B40: =COMUNICACIONES!A7 -> 06.01.03 | C40: INSTALACION DE PUNTOS DE RED EN CIELO RASO
A41: Rendimiento m2/día | B41: und/dia | C41: M.O | D41: 8 | E41: EQ | F41: =D41 -> 8 | G41: Costo unitario directo | I41: und | J41: =J46+J53+J56 -> 95.84
A42: Código | B42: Descripción Recurso | F42: Unidad | G42: Cuadrilla | H42: Cantidad | I42: Precio (S/.) | J42: Parcial (S/.)
B43: Mano de Obra
B44: OFICIAL | F44: hh | G44: 1 | H44: =ROUND(G44*8/$D$41,4) -> 1 | I44: 22.66 | J44: =ROUND(H44*I44,2) -> 22.66 | K44: 47
B45: TECNICO ESPECIALISTA EN TELECOMUNICACIONES | F45: hh | G45: 1 | H45: =ROUND(G45*8/$D$41,4) -> 1 | I45: 26.11 | J45: =ROUND(H45*I45,2) -> 26.11 | K45: 47
J46: =ROUND(SUM(J44:J45),2) -> 48.77
B47: Materiales
B48: JACK DE DATOS CAT CAT6A (BLANCO) | F48: und | H48: 2 | I48: 12.63 | J48: =ROUND(H48*I48,2) -> 25.26 | K48: 39
B49: CAJA GALV. RECTANGULAR PESADA DE 4"x2"x21/4" | F49: und | H49: 1 | I49: 3.73 | J49: =ROUND(H49*I49,2) -> 3.73 | K49: 39
B50: CONECTOR PVC-P (ELEC.) 25mm | F50: und | H50: 1 | I50: 0.93 | J50: =ROUND(H50*I50,2) -> 0.93 | K50: 72
B51: ETIQUETA PARA JACK DE DATOS | F51: und | H51: 1 | I51: 1.69 | J51: =ROUND(H51*I51,2) -> 1.69 | K51: 39
B52: FACE PLATE DOBLE PARA DATOS RJ45 BLANCO | F52: und | H52: 1 | I52: 14 | J52: =ROUND(H52*I52,2) -> 14 | K52: 39
J53: =ROUND(SUM(J48:J52),2) -> 45.61
B54: Equipos
B55: HERRAMIENTAS MANUALES | F55: %mo | H55: 3 | I55: =J46 -> 48.77 | J55: =ROUND(H55%*I55,2) -> 1.46 | K55: 37
J56: =ROUND(SUM(J55),2) -> 1.46
A58: Partida | B58: =COMUNICACIONES!A8 -> 06.01.04 | C58: TUBERIA PVC-P ELÉCTRICA Ø50mm, NTP 339.006
A59: Rendimiento m2/día | B59: m/dia | C59: M.O | D59: 30 | E59: EQ | F59: =D59 -> 30 | G59: Costo unitario directo | I59: m | J59: =J65+J71+J74 -> 26.42
A60: Código | B60: Descripción Recurso | F60: Unidad | G60: Cuadrilla | H60: Cantidad | I60: Precio (S/.) | J60: Parcial (S/.)
B61: Mano de Obra
B62: CAPATAZ | F62: hh | G62: 0.1 | H62: =ROUND(G62*8/$D$59,4) -> 0.0267 | I62: 34.73 | J62: =ROUND(H62*I62,2) -> 0.93 | K62: 47
B63: OPERARIO | F63: hh | G63: 1 | H63: =ROUND(G63*8/$D$59,4) -> 0.2667 | I63: 28.94 | J63: =ROUND(H63*I63,2) -> 7.72 | K63: 47
B64: PEON | F64: hh | G64: 1 | H64: =ROUND(G64*8/$D$59,4) -> 0.2667 | I64: 20.51 | J64: =ROUND(H64*I64,2) -> 5.47 | K64: 47
J65: =ROUND(SUM(J62:J64),2) -> 14.12
B66: Materiales
B67: TUBERÍA PVC-P ELECTRICO Ø50mm 3.0m | F67: m | H67: 1.05 | I67: 7.1 | J67: =ROUND(H67*I67,2) -> 7.46 | K67: 72
B68: CURVA PVC-P ELECTRICO Ø50mm | F68: und | H68: 0.25 | I68: 11.58 | J68: =ROUND(H68*I68,2) -> 2.9 | K68: 72
B69: PEGAMENTO PARA TUBERÍA PVC | F69: gal | H69: 0.005 | I69: 133.93 | J69: =ROUND(H69*I69,2) -> 0.67 | K69: 30
B70: CONECTOR PVC-P (ELEC.) 50mm | F70: und | H70: 0.25 | I70: 3.39 | J70: =ROUND(H70*I70,2) -> 0.85 | K70: 72
J71: =ROUND(SUM(J67:J70),2) -> 11.88
B72: Equipos
B73: HERRAMIENTAS MANUALES | F73: %mo | H73: 3 | I73: =J65 -> 14.12 | J73: =ROUND(H73%*I73,2) -> 0.42 | K73: 37
J74: =ROUND(SUM(J73),2) -> 0.42
A76: Partida | B76: =COMUNICACIONES!A9 -> 06.01.05 | C76: TUBERIA PVC-P ELÉCTRICA Ø40mm, NTP 339.006
A77: Rendimiento m2/día | B77: m/dia | C77: M.O | D77: 30 | E77: EQ | F77: =D77 -> 30 | G77: Costo unitario directo | I77: m | J77: =J83+J89+J92 -> 25.01
A78: Código | B78: Descripción Recurso | F78: Unidad | G78: Cuadrilla | H78: Cantidad | I78: Precio (S/.) | J78: Parcial (S/.)
B79: Mano de Obra
B80: CAPATAZ | F80: hh | G80: 0.1 | H80: =ROUND(G80*8/$D$77,4) -> 0.0267 | I80: 34.73 | J80: =ROUND(H80*I80,2) -> 0.93 | K80: 47
B81: OPERARIO | F81: hh | G81: 1 | H81: =ROUND(G81*8/$D$77,4) -> 0.2667 | I81: 28.94 | J81: =ROUND(H81*I81,2) -> 7.72 | K81: 47
B82: PEON | F82: hh | G82: 1 | H82: =ROUND(G82*8/$D$77,4) -> 0.2667 | I82: 20.51 | J82: =ROUND(H82*I82,2) -> 5.47 | K82: 47
J83: =ROUND(SUM(J80:J82),2) -> 14.12
B84: Materiales
B85: CURVA PVC-P ELECTRICO Ø40mm | F85: und | H85: 0.25 | I85: 8.39 | J85: =ROUND(H85*I85,2) -> 2.1 | K85: 72
B86: TUBERÍA PVC-P ELECTRICO Ø40mm 3.0m | F86: m | H86: 1.05 | I86: 6.77 | J86: =ROUND(H86*I86,2) -> 7.11 | K86: 72
B87: PEGAMENTO PARA TUBERÍA PVC | F87: gal | H87: 0.005 | I87: 133.93 | J87: =ROUND(H87*I87,2) -> 0.67 | K87: 30
B88: CONECTOR PVC Ø 40mm | F88: und | H88: 0.25 | I88: 2.37 | J88: =ROUND(H88*I88,2) -> 0.59 | K88: 72
J89: =ROUND(SUM(J85:J88),2) -> 10.47
B90: Equipos
B91: HERRAMIENTAS MANUALES | F91: %mo | H91: 3 | I91: =J83 -> 14.12 | J91: =ROUND(H91%*I91,2) -> 0.42 | K91: 37
J92: =ROUND(SUM(J91),2) -> 0.42
A94: Partida | B94: =COMUNICACIONES!A10 -> 06.01.06 | C94: TUBERIA PVC-P ELÉCTRICA Ø25mm, NTP 339.006
A95: Rendimiento m2/día | B95: m/dia | C95: M.O | D95: 40 | E95: EQ | F95: =D95 -> 40 | G95: Costo unitario directo | I95: m | J95: =J101+J107+J110 -> 19.23
A96: Código | B96: Descripción Recurso | F96: Unidad | G96: Cuadrilla | H96: Cantidad | I96: Precio (S/.) | J96: Parcial (S/.)
B97: Mano de Obra
B98: CAPATAZ | F98: hh | G98: 0.1 | H98: =ROUND(G98*8/$D$95,4) -> 0.02 | I98: 34.73 | J98: =ROUND(H98*I98,2) -> 0.69 | K98: 47
B99: OPERARIO | F99: hh | G99: 1 | H99: =ROUND(G99*8/$D$95,4) -> 0.2 | I99: 28.94 | J99: =ROUND(H99*I99,2) -> 5.79 | K99: 47
B100: PEON | F100: hh | G100: 1 | H100: =ROUND(G100*8/$D$95,4) -> 0.2 | I100: 20.51 | J100: =ROUND(H100*I100,2) -> 4.1 | K100: 47
J101: =ROUND(SUM(J98:J100),2) -> 10.58
B102: Materiales
B103: TUBERÍA PVC-P ELECTRICO Ø25mm 3.0m | F103: m | H103: 1.05 | I103: 6.47 | J103: =ROUND(H103*I103,2) -> 6.79 | K103: 72
B104: CURVA PVC-P ELECTRICO Ø25mm | F104: und | H104: 0.25 | I104: 2.54 | J104: =ROUND(H104*I104,2) -> 0.64 | K104: 72
B105: PEGAMENTO PARA TUBERÍA PVC | F105: gal | H105: 0.005 | I105: 133.93 | J105: =ROUND(H105*I105,2) -> 0.67 | K105: 30
B106: CONECTOR PVC-P (ELEC.) 25mm | F106: und | H106: 0.25 | I106: 0.93 | J106: =ROUND(H106*I106,2) -> 0.23 | K106: 72
J107: =ROUND(SUM(J103:J106),2) -> 8.33
B108: Equipos
...

Sheet Metrado Provisionales
G2: Unidad | H2: Largo | I2: Ancho | J2: Alto | K2: Área | L2: Volumen | M2: Cantidad | N2: N°Elem | O2: Factor | P2: Parcial | Q2: Metrado
A3: 1 | B3: OBRAS PROVISIONALES, PRELIMINARES, SEGURIDAD Y SALUD EN EL TRABAJO Y PLAN DE CONTINGENCIA
A4: 1.1 | B4: OBRAS PROVISIONALES
A5: 1.1.1 | B5: CONSTRUCCIONES PROVISIONALES
A6: 1.1.1.1 | B6: OFICINAS DE RESIDENCIA Y SUPERVISIÓN | G6: m2 | M6: =PROVISIONALES!H6 -> 50 | Q6: =ROUND('Obras provisionales'!H9,2) -> 50
A7: 1.1.1.2 | B7: ALMACENES DE OBRA | G7: m2 | M7: =PROVISIONALES!H7 -> 3 | Q7: =ROUND('Obras provisionales'!H10,2) -> 3
A8: 1.1.1.3 | B8: CASETAS DE GUARDIANÍA | G8: m2 | M8: =PROVISIONALES!H8 -> 8 | Q8: =ROUND('Obras provisionales'!H11,2) -> 8
A9: 1.1.1.4 | B9: COMEDOR PARA PERSONAL DE OBRA | G9: m2 | M9: =PROVISIONALES!H9 -> 50 | Q9: =ROUND('Obras provisionales'!H12,2) -> 50
A10: 1.1.1.5 | B10: VESTUARIO PARA PERSONAL DE OBRA | G10: m2 | M10: =PROVISIONALES!H10 -> 25 | Q10: =ROUND('Obras provisionales'!H13,2) -> 25
A11: 1.1.1.6 | B11: CERCO PERIMÉTRICO DE MALLA ARPILLERA | G11: m | M11: =PROVISIONALES!H11 -> 126.49 | Q11: =ROUND('Obras provisionales'!H14,2) -> 126.49
A12: 1.1.1.7 | B12: SERVICIOS HIGIÉNICOS | G12: m2 | M12: =PROVISIONALES!H12 -> 16 | Q12: =ROUND('Obras provisionales'!H15,2) -> 16
A13: 1.1.1.8 | B13: CARTEL DE IDENTIFICACIÓN DE LA OBRA | G13: und | M13: =PROVISIONALES!H13 -> 2 | Q13: =ROUND('Obras provisionales'!H16,2) -> 2
A14: 1.1.2 | B14: INSTALACIONES PROVISIONALES
A15: 1.1.2.1 | B15: CONEXIÓN E INSTALACIÓN DE AGUA | G15: glb | M15: =PROVISIONALES!H15 -> 1 | Q15: =ROUND('Obras provisionales'!H18,2) -> 1
A16: 1.1.2.2 | B16: CONSUMO Y MANTENIMIENTO DE AGUA PARA LA CONSTRUCCIÓN | G16: mes | M16: =PROVISIONALES!H16 -> 12 | Q16: =ROUND('Obras provisionales'!H19,2) -> 12
A17: 1.1.2.3 | B17: CONEXIÓN E INSTALACIÓN DE ENERGÍA ELÉCTRICA | G17: glb | M17: =PROVISIONALES!H17 -> 1 | Q17: =ROUND('Obras provisionales'!H20,2) -> 1
A18: 1.1.2.4 | B18: CONSUMO Y MANTENIMIENTO DE ENERGÍA ELÉCTRICA | G18: mes | M18: =PROVISIONALES!H18 -> 12 | Q18: =ROUND('Obras provisionales'!H21,2) -> 12
A19: 1.2 | B19: TRABAJOS PRELIMINARES
A20: 1.2.1 | B20: LIMPIEZA DEL TERRENO
A21: 1.2.1.1 | B21: LIMPIEZA DEL TERRENO MANUAL | G21: m2 | M21: =PROVISIONALES!H21 -> 1000 | Q21: =ROUND('Obras provisionales'!H27,2) -> 1000
A22: 1.2.1.2 | B22: ELIMINACIÓN DE OBSTRUCCIONES | G22: m2 | M22: =PROVISIONALES!H22 -> 1000 | Q22: =ROUND('Obras provisionales'!H28,2) -> 1000
A23: 1.2.2 | B23: MOVILIZACIÓN DE CAMPAMENTO, MAQUINARIA Y HERRAMIENTAS
A24: 1.2.2.1 | B24: MOVILIZACIÓN DE EQUIPOS Y HERRAMIENTAS | G24: glb | M24: =PROVISIONALES!H24 -> 1 | Q24: =ROUND('Obras provisionales'!H30,2) -> 1
A25: 1.2.2.2 | B25: TRANSPORTE DE MATERIALES A LA OBRA | G25: glb | M25: =PROVISIONALES!H25 -> 1 | Q25: =ROUND('Obras provisionales'!H31,2) -> 1
A26: 1.2.3 | B26: TRAZOS, NIVELES Y REPLANTEO
A27: 1.2.3.1 | B27: TRAZO Y REPLANTEO PRELIMINAR | G27: m2 | M27: =PROVISIONALES!H27 -> 1000 | Q27: =ROUND('Obras provisionales'!H33,2) -> 1000
A28: 1.2.3.2 | B28: TRAZO NIVELACIÓN Y REPLANTEO DURANTE EL PROCESO | G28: m2 | M28: =PROVISIONALES!H28 -> 1000 | Q28: =ROUND('Obras provisionales'!H34,2) -> 1000
A29: 1.3 | B29: PLAN DE SEGURIDAD Y SALUD EN EL TRABAJO
A30: 1.3.1 | B30: Equipo de seguridad y salud
A31: 1.3.1.1 | B31: EQUIPOS DE PROTECCIÓN INDIVIDUAL | G31: glb | M31: =PROVISIONALES!H31 -> 1 | Q31: =ROUND('Obras provisionales'!H37,2) -> 1
A32: 1.3.1.2 | B32: EQUIPOS DE PROTECCIÓN COLECTIVA | G32: glb | M32: =PROVISIONALES!H32 -> 1 | Q32: =ROUND('Obras provisionales'!H38,2) -> 1
A33: 1.3.1.3 | B33: SEÑALIZACIÓN TEMPORAL DE SEGURIDAD | G33: glb | M33: =PROVISIONALES!H33 -> 1 | Q33: =ROUND('Obras provisionales'!H39,2) -> 1
A34: 1.3.1.4 | B34: PROGRAMA DE CAPACITACIÓN EN SEGURIDAD Y SALUD | G34: glb | M34: =PROVISIONALES!H34 -> 1 | Q34: =ROUND('Obras provisionales'!H40,2) -> 1
A35: 1.3.1.5 | B35: RECURSOS PARA RESPUESTA ANTE EMERGENCIAS | G35: glb | M35: =PROVISIONALES!H35 -> 1 | Q35: =ROUND('Obras provisionales'!H41,2) -> 1
A36: 1.3.1.6 | B36: PROGRAMA DE PREVENCIÓN Y CONTROL | G36: und | M36: =PROVISIONALES!H36 -> 1 | Q36: =ROUND('Obras provisionales'!H42,2) -> 1
A37: 1.3.1.7 | B37: EXAMEN MÉDICO GENERAL | G37: und | M37: =PROVISIONALES!H37 -> 1 | Q37: =ROUND('Obras provisionales'!H43,2) -> 1
A38: 1.4 | B38: PLAN DE MANEJO AMBIENTAL
A39: 1.4.1 | B39: PROGRAMA DE PREVENCIÓN Y MITIGACIÓN AMBIENTAL
A40: 1.4.1.1 | B40: PREVENCIÓN Y MITIGACIÓN DE IMPACTOS | G40: m3 | M40: =PROVISIONALES!H40 -> 609.6 | Q40: =ROUND('Obras provisionales'!H46,2) -> 609.6
A41: 1.4.1.2 | B41: IMPLEMENTACIÓN DE ÁREA DE SEÑALIZACIÓN | G41: und | M41: =PROVISIONALES!H41 -> 16 | Q41: =ROUND('Obras provisionales'!H47,2) -> 16
A42: 1.4.2 | B42: PROGRAMA DE EDUCACIÓN Y CAPACITACIÓN AMBIENTAL
A43: 1.4.2.1 | B43: CHARLAS DE SENSIBILIZACIÓN AMBIENTAL | G43: glb | M43: =PROVISIONALES!H43 -> 12 | Q43: =ROUND('Obras provisionales'!H49,2) -> 12
A44: 1.4.3 | B44: PROGRAMA DE SEGUIMIENTO, CONTROL Y VIGILANCIA AMBIENTAL
A45: 1.4.3.1 | B45: MONITOREO DE CALIDAD AMBIENTAL | G45: pto | M45: =PROVISIONALES!H45 -> 6 | Q45: =ROUND('Obras provisionales'!H51,2) -> 6
A46: 1.4.4 | B46: PROGRAMA DE MANEJO DE RESIDUOS SÓLIDOS
A47: 1.4.4.1 | B47: Manejo de residuos peligrosos
A48: 1.4.4.1.1 | B48: ADQUISICIÓN DE CONTENEDORES PARA RESIDUOS PELIGROSOS | G48: und | M48: =PROVISIONALES!H48 -> 3 | Q48: =ROUND('Obras provisionales'!H54,2) -> 3
A49: 1.4.4.1.2 | B49: RECOLECCIÓN DE RESIDUOS PELIGROSOS | G49: m3 | M49: =PROVISIONALES!H49 -> 9 | Q49: =ROUND('Obras provisionales'!H55,2) -> 9
A50: 1.4.4.1.3 | B50: ELIMINACIÓN Y TRANSPORTE DE RESIDUOS PELIGROSOS | G50: m3 | M50: =PROVISIONALES!H50 -> 9 | Q50: =ROUND('Obras provisionales'!H56,2) -> 9
A51: 1.4.4.2 | B51: Manejo de residuos no peligrosos
A52: 1.4.4.2.1 | B52: ACONDICIONAMIENTO | G52: m2 | M52: =PROVISIONALES!H52 -> 1 | Q52: =ROUND('Obras provisionales'!H58,2) -> 1
A53: 1.4.4.2.2 | B53: ADQUISICIÓN DE CONTENEDORES PARA RESIDUOS NO PELIGROSOS | G53: und | M53: =PROVISIONALES!H53 -> 15 | Q53: =ROUND('Obras provisionales'!H59,2) -> 15
A54: 1.4.4.2.3 | B54: RECOLECCIÓN DE RESIDUOS NO PELIGROSOS | G54: m3 | M54: =PROVISIONALES!H54 -> 24 | Q54: =ROUND('Obras provisionales'!H60,2) -> 24
A55: 1.4.4.2.4 | B55: DISPOSICIÓN FINAL DE RESIDUOS NO PELIGROSOS | G55: m3 | M55: =PROVISIONALES!H55 -> 36 | Q55: =ROUND('Obras provisionales'!H61,2) -> 36
A56: 1.4.4.3 | B56: Manejo de residuos valorizables
A57: 1.4.4.3.1 | B57: CLASIFICACIÓN DE RESIDUOS VALORIZABLES | G57: mes | M57: =PROVISIONALES!H57 -> 12 | Q57: =ROUND('Obras provisionales'!H63,2) -> 12
A58: 1.4.4.3.2 | B58: DISPOSICIÓN FINAL | G58: m3 | M58: =PROVISIONALES!H58 -> 9.6 | Q58: =ROUND('Obras provisionales'!H64,2) -> 9.6
A59: 1.4.5 | B59: PROGRAMA DE CONTINGENCIA
A60: 1.4.5.1 | B60: CONTINGENCIA ANTE DERRAMES | G60: und | M60: =PROVISIONALES!H60 -> 1 | Q60: =ROUND('Obras provisionales'!H66,2) -> 1
A61: 1.4.6 | B61: PROGRAMA DE CIERRE Y ABANDONO
A62: 1.4.6.1 | B62: MANEJO DE RESIDUOS DE DESINSTALACIÓN | G62: m2 | M62: =PROVISIONALES!H62 -> 20 | Q62: =ROUND('Obras provisionales'!H68,2) -> 20
A63: 1.4.6.2 | B63: TRASLADO Y DISPOSICIÓN FINAL DE RESIDUOS | G63: m3 | M63: =PROVISIONALES!H63 -> 1.5 | Q63: =ROUND('Obras provisionales'!H69,2) -> 1.5
A64: 1.4.6.3 | B64: REHABILITACIÓN DE SUELOS AFECTADOS | G64: m2 | M64: =PROVISIONALES!H64 -> 3 | Q64: =ROUND('Obras provisionales'!H70,2) -> 3
A65: 1.4.6.4 | B65: NIVELACIÓN Y COMPACTACIÓN | G65: m2 | M65: =PROVISIONALES!H65 -> 4 | Q65: =ROUND('Obras provisionales'!H71,2) -> 4
A66: 1.5 | B66: DEMOLICIONES
A67: 1.5.1 | B67: DESMONTAJE
A68: 1.5.1.1 | B68: DESMONTAJE DE TECHO DE TEJA ANDINA + ESTRUCTURA DE MADERA | G68: m2 | M68: =PROVISIONALES!H68 -> 10.2 | Q68: =IF('Datos iniciales '!$E$3="SI",ROUND('Obras provisionales'!H74,2),0) -> 10.2
A69: 1.5.1.2 | B69: DESMONTAJE DE TECHO DE CALAMINA + ESTRUCTURA DE MADERA | G69: m2 | M69: =PROVISIONALES!H69 -> 15.6 | Q69: =IF('Datos iniciales '!$E$3="SI",ROUND('Obras provisionales'!H75,2),0) -> 15.6
A70: 1.5.1.3 | B70: DESMONTAJE DE CIELORRASO EXISTENTE | G70: m2 | M70: =PROVISIONALES!H70 -> 14.1 | Q70: =IF('Datos iniciales '!$E$3="SI",ROUND('Obras provisionales'!H76,2),0) -> 14.1
A71: 1.5.1.4 | B71: DESMONTAJE DE PUERTAS METÁLICAS EXISTENTES | G71: m2 | M71: =PROVISIONALES!H71 -> 0.3 | Q71: =IF('Datos iniciales '!$E$3="SI",ROUND('Obras provisionales'!H77,2),0) -> 0.3
A72: 1.5.1.5 | B72: DESMONTAJE DE PUERTAS DE MADERA EXISTENTES | G72: m2 | M72: =PROVISIONALES!H72 -> 0.69 | Q72: =IF('Datos iniciales '!$E$3="SI",ROUND('Obras provisionales'!H78,2),0) -> 0.69
A73: 1.5.1.6 | B73: DESMONTAJE DE VENTANAS EXISTENTES | G73: m2 | M73: =PROVISIONALES!H73 -> 1.14 | Q73: =IF('Datos iniciales '!$E$3="SI",ROUND('Obras provisionales'!H79,2),0) -> 1.14
A74: 1.5.1.7 | B74: DESMONTAJE DE PISO DE MADERA | G74: m2 | M74: =PROVISIONALES!H74 -> 11.1 | Q74: =IF('Datos iniciales '!$E$3="SI",ROUND('Obras provisionales'!H80,2),0) -> 11.1
A75: 1.5.2 | B75: DEMOLICIONES
A76: 1.5.2.1 | B76: DEMOLICIÓN MANUAL DE PISO DE CONCRETO | G76: m2 | M76: =PROVISIONALES!H76 -> 15.9 | Q76: =IF('Datos iniciales '!$E$3="SI",ROUND('Obras provisionales'!H82,2),0) -> 15.9
A77: 1.5.2.2 | B77: DEMOLICIÓN MANUAL DE MURO DE TAPIAL | G77: m3 | M77: =PROVISIONALES!H77 -> 13.2 | Q77: =IF('Datos iniciales '!$E$3="SI",ROUND('Obras provisionales'!H83,2),0) -> 13.2

Sheet Metrado Estructuras
G2: Unidad | H2: Largo | I2: Ancho | J2: Alto | K2: Área | L2: Volumen | M2: Cantidad | N2: N°Elem | O2: Factor | P2: Parcial | Q2: Metrado
A3: 2 | B3: ESTRUCTURA
A4: 2.01 | B4: MOVIMIENTO DE TIERRAS
A5: 02.01.01 | B5: EXCAVACIÓN LOCALIZADA CON MAQUINARIA | G5: m3 | M5: =ESTRUCTURA!H5 -> 2961.86 | Q5: =ROUND('Cimentación 1 piso'!H9+'Cimentación 2 pisos '!H9+'Cimentación 3 pisos'!H9+'Cimentación 4 pisos'!H9+'Platea de Cimentacion'!H9,2) -> 2961.86
A6: 02.01.02 | B6: EXCAVACIÓN MANUAL | G6: m3 | M6: =ESTRUCTURA!H6 -> 38.29 | Q6: =ROUND('Cimentación 1 piso'!H10+'Cimentación 2 pisos '!H10+'Cimentación 3 pisos'!H10+'Cimentación 4 pisos'!H10+'Platea de Cimentacion'!H10,2) -> 38.29
A7: 02.01.03 | B7: RELLENO COMPACTADO C/PLANCHA COMPACTADORA C/MATERIAL DE PRÉSTAMO | G7: m3 | M7: =ESTRUCTURA!H7 -> 176.72 | Q7: =ROUND('Cimentación 1 piso'!H11+'Cimentación 2 pisos '!H11+'Cimentación 3 pisos'!H11+'Cimentación 4 pisos'!H11+'Platea de Cimentacion'!H11,2) -> 176.72
A8: 02.01.04 | B8: RELLENO COMPACTADO C/PLANCHA COMPACTADORA C/MATERIAL PROPIO | G8: m3 | M8: =ESTRUCTURA!H8 -> 1827.84 | Q8: =ROUND('Cimentación 1 piso'!H12+'Cimentación 2 pisos '!H12+'Cimentación 3 pisos'!H12+'Cimentación 4 pisos'!H12+'Platea de Cimentacion'!H12,2) -> 1827.84
A9: 02.01.05 | B9: FORMACION Y COMPACTACION DE SUBRASANTE | G9: m2 | M9: =ESTRUCTURA!H9 -> 1332.21 | Q9: =ROUND('Cimentación 1 piso'!H13+'Cimentación 2 pisos '!H13+'Cimentación 3 pisos'!H13+'Cimentación 4 pisos'!H13+'Platea de Cimentacion'!H13,2) -> 1332.21
A10: 02.01.06 | B10: ACARREO DE MATERIAL EXCEDENTE | G10: m2 | M10: =ESTRUCTURA!H10 -> 1446.64 | Q10: =ROUND('Cimentación 1 piso'!H14+'Cimentación 2 pisos '!H14+'Cimentación 3 pisos'!H14+'Cimentación 4 pisos'!H14+'Platea de Cimentacion'!H14,2) -> 1446.64
A11: 02.01.07 | B11: ELIMINACIÓN DE MATERIAL EXCEDENTE HASTA D=10 KM | G11: m3 | M11: =ESTRUCTURA!H11 -> 1446.64 | Q11: =ROUND('Cimentación 1 piso'!H15+'Cimentación 2 pisos '!H15+'Cimentación 3 pisos'!H15+'Cimentación 4 pisos'!H15+'Platea de Cimentacion'!H15,2) -> 1446.64
A12: 02.01.08 | B12: COMPACTACION DE SUBRASANTE LOSA DEPORTIVA | G12: m3 | M12: =ESTRUCTURA!H12 -> 60 | Q12: =ROUND('Obras exteriores '!D11+'Obras exteriores '!D27+'Obras exteriores '!D45,2) -> 60
A13: 02.01.09 | B13: AFIRMADO DE e=0.30m PARA LOSA DEPORTIVA | G13: m3 | M13: =ESTRUCTURA!H13 -> 26.4 | Q13: =ROUND('Obras exteriores '!D12+'Obras exteriores '!D28+'Obras exteriores '!D46+'Obras exteriores '!D59,2) -> 26.4
A14: 2.02 | B14: CONCRETO SIMPLE
A15: 02.02.01 | B15: CONCRETO CICLOPEO -PLATEA DE CIMENTACION
A16: 02.02.01.01 | B16: CONCRETO CICLOPEO F’C=100 KG/CM² + PIEDRA GRANDE DE 8" E=0.80 M | G16: m2 | M16: =ESTRUCTURA!H16 -> 100 | Q16: =ROUND('Platea de Cimentacion'!H17,2) -> 100
A17: 02.02.02 | B17: FALSA ZAPATA
A18: 02.02.02.01 | B18: FALSA ZAPATA F’C=100 KG/CM² + PIEDRA GRANDE DE 8" E=0.80 M | G18: m2 | M18: =ESTRUCTURA!H18 -> 556.3 | Q18: =ROUND('Cimentación 1 piso'!H17+'Cimentación 2 pisos '!H17+'Cimentación 3 pisos'!H17+'Cimentación 4 pisos'!H17+Escalera!D7,2) -> 556.3
A19: 02.02.03 | B19: FALSO PISO
A20: 02.02.03.01 | B20: FALSO PISO E = 4" FC = 175 KG/CM2 | G20: m2 | M20: =ESTRUCTURA!H20 -> 524.54 | Q20: =ROUND('Cimentación 1 piso'!H19+'Cimentación 2 pisos '!H19+'Cimentación 3 pisos'!H19+'Cimentación 4 pisos'!H19+Escalera!D8,2) -> 524.54
A21: 02.02.04 | B21: SOLADOS
A22: 02.02.04.01 | B22: SOLADO PARA VIGA DE CIMENTACIÓN FC=100 KG/CM2 E=4" | G22: m2 | M22: =ESTRUCTURA!H22 -> 29.31 | Q22: =ROUND('Cimentación 1 piso'!H21+'Cimentación 2 pisos '!H21+'Cimentación 3 pisos'!H21+'Cimentación 4 pisos'!H21,2) -> 29.31
A23: 2.03 | B23: CONCRETO ARMADO
A24: 02.03.01 | B24: ZAPATAS
A25: 02.03.01.01 | B25: ZAPATAS.- CONCRETO f'c=210 Kg/cm2 | G25: m3 | M25: =ESTRUCTURA!H25 -> 355.99 | Q25: =ROUND('Cimentación 1 piso'!H24+'Cimentación 2 pisos '!H24+'Cimentación 3 pisos'!H24+'Cimentación 4 pisos'!H24,2) -> 355.99
A26: 02.03.01.02 | B26: ZAPATAS.- ACERO DE REFUERZO fy=4,200 Kg/cm2 | G26: kg | M26: =ESTRUCTURA!H26 -> 12402.68 | Q26: =ROUND('Cimentación 1 piso'!H25+'Cimentación 2 pisos '!H25+'Cimentación 3 pisos'!H25+'Cimentación 4 pisos'!H25,2) -> 12402.68
A27: 02.03.02 | B27: PLATEA DE CIMENTACION
A28: 02.03.02.01 | B28: PLATEA DE CIMENTACION. – CONCRETO f'c=210 | G28: m3 | M28: =ESTRUCTURA!H28 -> 60 | Q28: =ROUND('Platea de Cimentacion'!H24,2) -> 60
A29: 02.03.02.02 | B29: PLATEA DE CIMENTACION. – ENCOFRADO Y DESENCOFRADO | G29: m2 | M29: =ESTRUCTURA!H29 -> 50 | Q29: =ROUND('Platea de Cimentacion'!H25,2) -> 50
A30: 02.03.02.03 | B30: PLATEA DE CIMENTACION.- ACERO DE REFUERZO fy=4,200 Kg/cm2 | G30: kg | M30: =ESTRUCTURA!H30 -> 14400 | Q30: =ROUND('Platea de Cimentacion'!H26,2) -> 14400
A31: 02.03.03 | B31: SOBRECIMIENTOS ARMADO
A32: 02.03.03.01 | B32: SOBRECIMIENTO REFORZADO.- CONCRETO 210 KG/CM2 | G32: m3 | M32: =ESTRUCTURA!H32 -> 80.78 | Q32: =ROUND('Cimentación 1 piso'!H27+'Cimentación 2 pisos '!H27+'Cimentación 3 pisos'!H27+'Cimentación 4 pisos'!H27+'Platea de Cimentacion'!H28,2) -> 80.78
A33: 02.03.03.02 | B33: SOBRECIMIENTOS REFORZADOS.- ENCOFRADO Y DESENCOFRADO | G33: m2 | M33: =ESTRUCTURA!H33 -> 443.33 | Q33: =ROUND('Cimentación 1 piso'!H28+'Cimentación 2 pisos '!H28+'Cimentación 3 pisos'!H28+'Cimentación 4 pisos'!H28+'Platea de Cimentacion'!H29,2) -> 443.33
A34: 02.03.03.03 | B34: SOBRECIMIENTO ARMADO.- ACERO DE REFUERZO fy=4,200 Kg/cm2 | G34: kg | M34: =ESTRUCTURA!H34 -> 3932.33 | Q34: =ROUND('Cimentación 1 piso'!H29+'Cimentación 2 pisos '!H29+'Cimentación 3 pisos'!H29+'Cimentación 4 pisos'!H29+'Platea de Cimentacion'!H30,2) -> 3932.33
A35: 02.03.04 | B35: VIGAS DE CIMENTACIÓN
A36: 02.03.04.01 | B36: VIGAS DE CIMENTACIÓN.- CONCRETO 210 KG/CM2 | G36: m3 | M36: =ESTRUCTURA!H36 -> 45.93 | Q36: =ROUND('Cimentación 1 piso'!H31+'Cimentación 2 pisos '!H31+'Cimentación 3 pisos'!H31+'Cimentación 4 pisos'!H31+Escalera!D11,2) -> 45.93
A37: 02.03.04.02 | B37: VIGAS DE CIMENTACIÓN.- ENCOFRADO Y DESENCOFRADO | G37: m2 | M37: =ESTRUCTURA!H37 -> 234.31 | Q37: =ROUND('Cimentación 1 piso'!H32+'Cimentación 2 pisos '!H32+'Cimentación 3 pisos'!H32+'Cimentación 4 pisos'!H32+Escalera!D12,2) -> 234.31
A38: 02.03.04.03 | B38: VIGAS DE CIMENTACIÓN.- ACERO DE REFUERZO fy=4,200 Kg/cm2 | G38: kg | M38: =ESTRUCTURA!H38 -> 4444.6 | Q38: =ROUND('Cimentación 1 piso'!H33+'Cimentación 2 pisos '!H33+'Cimentación 3 pisos'!H33+'Cimentación 4 pisos'!H33+Escalera!D13,2) -> 4444.6
A39: 02.03.05 | B39: COLUMNAS
A40: 02.03.05.01 | B40: COLUMNAS-CONCRETO fc=210kg/cm2 | G40: m3 | M40: =ESTRUCTURA!H40 -> 48.04 | Q40: =ROUND('Estructura 1'!G6,2) -> 48.04
A41: 02.03.05.02 | B41: COLUMNAS.- ENCOFRADO Y DESENCOFRADO | G41: m2 | M41: =ESTRUCTURA!H41 -> 349.57 | Q41: =ROUND('Estructura 1'!G7,2) -> 349.57
A42: 02.03.05.03 | B42: COLUMNAS.- ACERO DE REFUERZO fy=4,200 Kg/cm2 | G42: kg | M42: =ESTRUCTURA!H42 -> 8166.61 | Q42: =ROUND('Estructura 1'!G8,2) -> 8166.61
A43: 02.03.06 | B43: COLUMNETAS DE CONFINAMIENTO
A44: 02.03.06.01 | B44: COLUMNETAS DE CONFINAMIENTO-CONCRETO fc=210kg/cm2 | G44: m3 | M44: =ESTRUCTURA!H44 -> 7.21 | Q44: =ROUND('Estructura 2'!G6,2) -> 7.21
A45: 02.03.06.02 | B45: COLUMNETAS DE CONFINAMIENTO.- ENCOFRADO Y DESENCOFRADO | G45: m2 | M45: =ESTRUCTURA!H45 -> 122.35 | Q45: =ROUND('Estructura 2'!G7,2) -> 122.35
A46: 02.03.06.03 | B46: COLUMNETAS DE CONFINAMIENTO.- ACERO DE REFUERZO fy=4,200 Kg/cm2 | G46: kg | M46: =ESTRUCTURA!H46 -> 576.47 | Q46: =ROUND('Estructura 2'!G8,2) -> 576.47
A47: 02.03.07 | B47: VIGAS
A48: 02.03.07.01 | B48: VIGAS.- CONCRETO fc=210kg/cm2 | G48: m3 | M48: =ESTRUCTURA!H48 -> 50.55 | Q48: =ROUND('Estructura 1'!G10,2) -> 50.55
A49: 02.03.07.02 | B49: VIGAS.- ENCOFRADO Y DESENCOFRADO | G49: m2 | M49: =ESTRUCTURA!H49 -> 246.68 | Q49: =ROUND('Estructura 1'!G11,2) -> 246.68
A50: 02.03.07.03 | B50: VIGAS.- ACERO fy=4200 kg/cm² | G50: kg | M50: =ESTRUCTURA!H50 -> 7076.62 | Q50: =ROUND('Estructura 1'!G12,2) -> 7076.62
A51: 02.03.08 | B51: VIGUETAS DE CONFINAMIENTO
A52: 02.03.08.01 | B52: VIGUETAS DE CONFINAMIENTO.- CONCRETO fc=210kg/cm2 | G52: m3 | M52: =ESTRUCTURA!H52 -> 2.53 | Q52: =ROUND('Estructura 2'!G10,2) -> 2.53
A53: 02.03.08.02 | B53: VIGUETAS DE CONFINAMIENTO.- ENCOFRADO Y DESENCOFRADO | G53: m2 | M53: =ESTRUCTURA!H53 -> 37 | Q53: =ROUND('Estructura 2'!G11,2) -> 37
A54: 02.03.08.03 | B54: VIGUETAS DE CONFINAMIENTO.- ACERO fy=4200 kg/cm² | G54: kg | M54: =ESTRUCTURA!H54 -> 202.19 | Q54: =ROUND('Estructura 2'!G12,2) -> 202.19
A55: 02.03.09 | B55: LOSA ALIGERADA
A56: 02.03.09.01 | B56: LOSA ALIGERADA - CONCRETO f'c=210 kg/cm² | G56: m3 | M56: =ESTRUCTURA!H56 -> 35.06 | Q56: =ROUND('Estructura 1'!G14,2) -> 35.06
A57: 02.03.09.02 | B57: LOSA ALIGERADA.- ENCOFRADO Y DESENCOFRADO | G57: m2 | M57: =ESTRUCTURA!H57 -> 384.41 | Q57: =ROUND('Estructura 1'!G15,2) -> 384.41
A58: 02.03.09.03 | B58: LOSA ALIGERADA.- ACERO DE REFUERZO fy=4,200 kg/cm² | G58: kg | M58: =ESTRUCTURA!H58 -> 1577.81 | Q58: =ROUND('Estructura 1'!G16,2) -> 1577.81
A59: 02.03.09.04 | B59: LOSA ALIGERADA.- LADRILLO HUECO 30×30×15 cm | G59: und | M59: =ESTRUCTURA!H59 -> 2910.19 | Q59: =ROUND('Estructura 1'!G17,2) -> 2910.19
A60: 02.03.10 | B60: LOSA MACIZA
A61: 02.03.10.01 | B61: LOSA MACIZA CONCRETO f'c= 210 kg/cm² | G61: m3 | M61: =ESTRUCTURA!H61 -> 0.88 | Q61: =ROUND(Escalera!D15,2) -> 0.88
A62: 02.03.10.02 | B62: LOSA MACIZA ENCOFRADO Y DESENCOFRADO | G62: m2 | M62: =ESTRUCTURA!H62 -> 3.51 | Q62: =ROUND(Escalera!D16,2) -> 3.51
A63: 02.03.10.03 | B63: LOSA MACIZA ACERO fy=4200 kg/cm² | G63: kg | M63: =ESTRUCTURA!H63 -> 131.52 | Q63: =ROUND(Escalera!D17,2) -> 131.52
A64: 02.03.11 | B64: PLACAS
A65: 02.03.11.01 | B65: PLACAS-CONCRETO fc=210kg/cm2 | G65: m3 | M65: =ESTRUCTURA!H65 -> 24 | Q65: =ROUND('Estructura 1'!G19,2) -> 24
A66: 02.03.11.02 | B66: PLACAS.- ENCOFRADO Y DESENCOFRADO | G66: m2 | M66: =ESTRUCTURA!H66 -> 288.3 | Q66: =ROUND('Estructura 1'!G20,2) -> 288.3
A67: 02.03.11.03 | B67: PLACAS.- ACERO DE REFUERZO fy=4,200 Kg/cm2 | G67: kg | M67: =ESTRUCTURA!H67 -> 3360 | Q67: =ROUND('Estructura 1'!G21,2) -> 3360
A68: 02.03.12 | B68: ESCALERA
A69: 02.03.12.01 | B69: CONCRETO F'C=210 KG/CM² EN ESCALERA | G69: m3 | M69: =ESTRUCTURA!H69 -> 3.77 | Q69: =ROUND(Escalera!D19,2) -> 3.77
A70: 02.03.12.02 | B70: ENCOFRADO Y DESENCOFRADO ESCALERA | G70: m2 | M70: =ESTRUCTURA!H70 -> 28.07 | Q70: =ROUND(Escalera!D20,2) -> 28.07
A71: 02.03.12.03 | B71: ACERO FY=4200 KG/CM² EN ESCALERA | G71: kg | M71: =ESTRUCTURA!H71 -> 376.76 | Q71: =ROUND(Escalera!D21,2) -> 376.76
A72: 2.04 | B72: OBRAS EXTERIORES
A73: 02.04.01 | B73: LOSA DEPORTIVA
A74: 02.04.01.01 | B74: CONCRETO EN LOSA DEPORTIVA F'C= 210 KG/CM2 | G74: m2 | M74: =ESTRUCTURA!H74 -> 4.4 | Q74: =ROUND('Obras exteriores '!D13,2) -> 4.4
A75: 02.04.01.02 | B75: CONCRETO DE UÑAS = 210KG/CM2 | G75: m3 | M75: =ESTRUCTURA!H75 -> 0.29 | Q75: =ROUND('Obras exteriores '!D14,2) -> 0.29
A76: 02.04.01.03 | B76: ENCOFRADO Y DESENCOFRADO NORMAL EN LOSA | G76: m2 | M76: =ESTRUCTURA!H76 -> 1.53 | Q76: =ROUND('Obras exteriores '!D15,2) -> 1.53
A77: 02.04.01.04 | B77: DADOS DE CONCRETO PARA SOPORTE, f'c=210 kg/cm2 | G77: m3 | M77: =ESTRUCTURA!H77 -> 0.02 | Q77: =ROUND('Obras exteriores '!D16,2) -> 0.02
A78: 02.04.01.05 | B78: CURADO DE LOSA | G78: m2 | M78: =ESTRUCTURA!H78 -> 20 | Q78: =ROUND('Obras exteriores '!D17,2) -> 20
A79: 02.04.01.06 | B79: JUNTAS DE DILATACION E= 1" , H=0.10 | G79: m | M79: =ESTRUCTURA!H79 -> 3.21 | Q79: =ROUND('Obras exteriores '!D18,2) -> 3.21
A80: 02.04.01.07 | B80: JUNTAS DILATACION E= 1", H= 0.05 | G80: m | M80: =ESTRUCTURA!H80 -> 3.78 | Q80: =ROUND('Obras exteriores '!D19,2) -> 3.78
A81: 02.04.01.08 | B81: ESTRUCTURA METALICA P/PARANTES DE REFLECTORES | G81: m | M81: =ESTRUCTURA!H81 -> 0.15 | Q81: =ROUND('Obras exteriores '!D20,2) -> 0.15
A82: 02.04.02 | B82: PATIO DE INICIAL
A83: 02.04.02.01 | B83: CONCRETO EN PATIO DE INICIAL F'C= 210 KG/CM2 | G83: m2 | M83: =ESTRUCTURA!H83 -> 4.4 | Q83: =ROUND('Obras exteriores '!D29,2) -> 4.4
A84: 02.04.02.02 | B84: CONCRETO DE UÑAS = 210KG/CM2 | G84: m3 | M84: =ESTRUCTURA!H84 -> 0.29 | Q84: =ROUND('Obras exteriores '!D30,2) -> 0.29
A85: 02.04.02.03 | B85: ENCOFRADO Y DESENCOFRADO NORMAL EN LOSA | G85: m2 | M85: =ESTRUCTURA!H85 -> 1.53 | Q85: =ROUND('Obras exteriores '!D31,2) -> 1.53
A86: 02.04.02.04 | B86: DADOS DE CONCRETO PARA SOPORTE, f'c=210 kg/cm2 | G86: m3 | M86: =ESTRUCTURA!H86 -> 0.02 | Q86: =ROUND('Obras exteriores '!D32,2) -> 0.02
A87: 02.04.02.05 | B87: CURADO DE LOSA | G87: m2 | M87: =ESTRUCTURA!H87 -> 20 | Q87: =ROUND('Obras exteriores '!D33,2) -> 20
A88: 02.04.02.06 | B88: JUNTAS DE DILATACION E= 1" , H=0.10 | G88: m | M88: =ESTRUCTURA!H88 -> 3.21 | Q88: =ROUND('Obras exteriores '!D34,2) -> 3.21
A89: 02.04.02.07 | B89: JUNTAS DILATACION E= 1", H= 0.05 | G89: m | M89: =ESTRUCTURA!H89 -> 3.78 | Q89: =ROUND('Obras exteriores '!D35,2) -> 3.78
A90: 02.04.02.08 | B90: ESTRUCTURA METALICA P/PARANTES DE REFLECTORES | G90: m | M90: =ESTRUCTURA!H90 -> 0.15 | Q90: =ROUND('Obras exteriores '!D36,2) -> 0.15
A91: 02.04.03 | B91: VEREDAS Y RAMPAS DE CONCRETO
A92: 02.04.03.01 | B92: CONCRETO EN VEREDAS F'C= 175 KG/CM2 | G92: m2 | M92: =ESTRUCTURA!H92 -> 2.4 | Q92: =ROUND('Obras exteriores '!D47,2) -> 2.4
A93: 02.04.03.02 | B93: CONCRETO DE UÑAS = 175KG/CM2 | G93: m3 | M93: =ESTRUCTURA!H93 -> 0.28 | Q93: =ROUND('Obras exteriores '!D48,2) -> 0.28
A94: 02.04.03.03 | B94: ENCOFRADO Y DESENCOFRADO NORMAL EN LOSA | G94: m2 | M94: =ESTRUCTURA!H94 -> 4 | Q94: =ROUND('Obras exteriores '!D49,2) -> 4
A95: 02.04.03.04 | B95: CURADO DE LOSA | G95: m2 | M95: =ESTRUCTURA!H95 -> 20 | Q95: =ROUND('Obras exteriores '!D50,2) -> 20
A96: 02.04.03.05 | B96: JUNTAS DE DILATACION E= 1" , H=0.10 | G96: m | M96: =ESTRUCTURA!H96 -> 3.21 | Q96: =ROUND('Obras exteriores '!D52,2) -> 3.21
A97: 02.04.03.06 | B97: JUNTAS DILATACION E= 1", H= 0.05 | G97: m | M97: =ESTRUCTURA!H97 -> 3.78 | Q97: =ROUND('Obras exteriores '!D53,2) -> 3.78
A98: 02.04.04 | B98: PAVIMENTO RIGIDO VEHICULAR
A99: 02.04.04.01 | B99: PAVIMENTO VEHICULAR - ENCOFRADO Y DESENCOFRADO | G99: m2 | M99: =ESTRUCTURA!H99 -> 4.5 | Q99: =ROUND('Obras exteriores '!D61,2) -> 4.5
A100: 02.04.04.02 | B100: DOWELLS | G100: kg | M100: =ESTRUCTURA!H100 -> 4 | Q100: =ROUND('Obras exteriores '!D62,2) -> 4
A101: 02.04.04.03 | B101: CURADO DE LOSA | G101: m2 | M101: =ESTRUCTURA!H101 -> 20 | Q101: =ROUND('Obras exteriores '!D63,2) -> 20
...

Sheet Metrado Arquitectura
G2: Unidad | H2: Largo | I2: Ancho | J2: Alto | K2: Área | L2: Volumen | M2: Cantidad | N2: N°Elem | O2: Factor | P2: Parcial | Q2: Metrado
A3: 3 | B3: ARQUITECTURA
A4: 3.01 | B4: MUROS DE MAMPOSTERIA
A5: 03.01.01 | B5: MURO DE LADRILLO KK TIPO IV SOGA M 1:4 E=1.5 CM | G5: m2 | M5: =ARQUITECTURA!H5 -> 1048.34 | Q5: =ROUND(SUM(BIBLIOTECA:INGRESO!G6),2) -> 1048.34
A6: 03.01.02 | B6: MURO DE LADRILLO KK TIPO IV CABEZA M 1:4 E=1.5 CM | G6: m2 | M6: =ARQUITECTURA!H6 -> 345.85 | Q6: =ROUND(SUM(BIBLIOTECA:INGRESO!G7),2) -> 345.85
A7: 03.01.03 | B7: TABIQUE DE DRYWALL E=0.15m | G7: m2 | M7: =ARQUITECTURA!H7 -> 287.32 | Q7: =ROUND(SUM(BIBLIOTECA:INGRESO!G8),2) -> 287.32
A8: 03.01.04 | B8: MELAMINE | G8: m2 | M8: =ARQUITECTURA!H8 -> 156.6 | Q8: =ROUND(SUM(BIBLIOTECA:INGRESO!G9),2) -> 156.6
A9: 03.01.05 | B9: TABLERO C.A. C/CERAMICO | G9: m2 | M9: =ARQUITECTURA!H9 -> 12.3 | Q9: =ROUND(SUM(BIBLIOTECA:INGRESO!G10),2) -> 12.3
A10: 3.02 | B10: REVOQUES, ENLUCIDOS y MOLDURAS
A11: 03.02.01 | B11: TARRAJEO
A12: 03.02.01.01 | B12: TARRAJEO FROTACHADO EN MUROS INTERIORES | G12: m2 | M12: =ARQUITECTURA!H12 -> 1392.44 | Q12: =ROUND(SUM(BIBLIOTECA:INGRESO!G13),2) -> 1392.44
A13: 03.02.01.02 | B13: TARRAJEO FROTACHADO EN MUROS EXTERIORES | G13: m2 | M13: =ARQUITECTURA!H13 -> 754.77 | Q13: =ROUND(SUM(BIBLIOTECA:INGRESO!G14),2) -> 754.77
A14: 03.02.02 | B14: ZOCALO
A15: 03.02.02.01 | B15: ZOCALO DE CERAMICA 0.30x0.30 | G15: m2 | M15: =ARQUITECTURA!H15 -> 793.45 | Q15: =ROUND(SUM(BIBLIOTECA:INGRESO!G16),2) -> 793.45
A16: 03.02.03 | B16: CIELO RASO
A17: 03.02.03.01 | B17: FALSO CIELORRADOS DE BALDOSAS DE FIBRA MINERAL DE 0.61x0.61m, e:15mm, BORDE REBAJADO, CON SISTEMA DE SUSPENSION ANTISISMICO | G17: m3 | M17: =ARQUITECTURA!H17 -> 160 | Q17: =ROUND(SUM(BIBLIOTECA:INGRESO!G18),2) -> 160
A18: 03.02.03.02 | B18: TARRAJEO DE CIELO RASO MEZCLA C:A 1:5, e=0.15cm | G18: m3 | M18: =ARQUITECTURA!H18 -> 866 | Q18: =ROUND(SUM(BIBLIOTECA:INGRESO!G19),2) -> 866
A19: 3.03 | B19: PISOS Y PAVIMENTOS
A20: 03.03.01 | B20: CONTRAPISOS E=40MM C:A 1:4 | G20: m2 | M20: =ARQUITECTURA!H20 -> 1000 | Q20: =ROUND(SUM(BIBLIOTECA:INGRESO!G21),2) -> 1000
A21: 03.03.02 | B21: PISO PORCELANATO ANTIDESLIZANTE 0.60x0.6OM | G21: m2 | M21: =ARQUITECTURA!H21 -> 320 | Q21: =ROUND(SUM(BIBLIOTECA:INGRESO!G22),2) -> 320
A22: 03.03.03 | B22: PISO DE BALDOSA CERAMICA 30x30 | G22: m2 | M22: =ARQUITECTURA!H22 -> 380 | Q22: =ROUND(SUM(BIBLIOTECA:INGRESO!G23),2) -> 380
A23: 03.03.04 | B23: PISO DE CONCRETO E=4" - FC=175 KG7CM2 / ACABADO FROTACHADO | G23: m2 | M23: =ARQUITECTURA!H23 -> 100 | Q23: =ROUND(SUM(BIBLIOTECA:INGRESO!G24),2) -> 100
A24: 03.03.05 | B24: PISO DE CEMENTO PULIDO Y BRUÑADO E=2" S/ COLOREAR | G24: m2 | M24: =ARQUITECTURA!H24 -> 100 | Q24: =ROUND(SUM(BIBLIOTECA:INGRESO!G25),2) -> 100
A25: 03.03.06 | B25: PISO LAMINADO DE ALTO TRANSITO EN AULAS | G25: m2 | M25: =ARQUITECTURA!H25 -> 140 | Q25: =ROUND(SUM(BIBLIOTECA:INGRESO!G26),2) -> 140
A26: 3.04 | B26: CONTRAZOCALOS
A27: 03.04.01 | B27: CONTR. S/COLOREAR H=30cm MZ 1:2 e=1.5cm | G27: m | M27: =ARQUITECTURA!H27 -> 82.3 | Q27: =ROUND(SUM(BIBLIOTECA:INGRESO!G28),2) -> 82.3
A28: 03.04.02 | B28: CONTRAZOCALO DE CEMENTO SEMIPULIDO CON IMPERMEABILIZANTE Y ENDURECEDOR | G28: m | M28: =ARQUITECTURA!H28 -> 393.14 | Q28: =ROUND(SUM(BIBLIOTECA:INGRESO!G29),2) -> 393.14
A29: 03.04.03 | B29: CONTRAZOCALO PORCELANATO ANTIDESLIZANTE H=0.10M | G29: m | M29: =ARQUITECTURA!H29 -> 177.6 | Q29: =ROUND(SUM(BIBLIOTECA:INGRESO!G30),2) -> 177.6
A30: 03.04.04 | B30: CONTRAZOCALO LAMINADO EN AULAS | G30: m | M30: =ARQUITECTURA!H30 -> 63.91 | Q30: =ROUND(SUM(BIBLIOTECA:INGRESO!G31),2) -> 63.91
A31: 03.04.05 | B31: CONTRAZOCALO DE BALDOSA CERAMICA H=30cm | G31: m | M31: =ARQUITECTURA!H31 -> 117.83 | Q31: =ROUND(SUM(BIBLIOTECA:INGRESO!G32),2) -> 117.83
A32: 03.04.06 | B32: CONTRAZOCALO SANITARIO TERRAZO PULIDO, H=0,10M | G32: m | M32: =ARQUITECTURA!H32 -> 94.9 | Q32: =ROUND(SUM(BIBLIOTECA:INGRESO!G33),2) -> 94.9
A33: 3.05 | B33: CARPINTERIA
A34: 03.05.01 | B34: PUERTA DE MADERA ROBLE NACIONAL APANELADA TIPO MACHIMBRADA +SOBRELUZ+VIDRIO TEMPLADO DE 8MM DE 02 HOJAS+INST+ACABADO, SEGUN PLANO Y ET | G34: m2 | M34: =ARQUITECTURA!H34 -> 135.16 | Q34: =ROUND(SUM(BIBLIOTECA:INGRESO!G35),2) -> 135.16
A35: 03.05.02 | B35: VENTANA C/MARCO DE ALUMINIO SISTEMA CORREDIZO TIPO SERIE 3160 + VIDRIOS INCOLORO TEMPLADO DE 8MM+ACCESORIO + ACCESORIO+ INSTALACION, SEGUN PLANO Y ESPECIFICACIONES TECNICAS | G35: m2 | M35: =ARQUITECTURA!H35 -> 124.47 | Q35: =ROUND(SUM(BIBLIOTECA:INGRESO!G36),2) -> 124.47
A36: 03.05.03 | B36: MAMPARA DE ALUMINIO+VIDRIO INCOLORO TEMPLADO 8MM+ACCESORIOS+INSTALACION,SEGUN PLANO Y ESPECIFICACIONES TECNICAS | G36: m2 | M36: =ARQUITECTURA!H36 -> 66.35 | Q36: =ROUND(SUM(BIBLIOTECA:INGRESO!G37),2) -> 66.35
A37: 03.05.04 | B37: PARASOLES | G37: m | M37: =ARQUITECTURA!H37 -> 122.2 | Q37: =ROUND(SUM(BIBLIOTECA:INGRESO!G38),2) -> 122.2
A38: 03.05.05 | B38: PERSIANA METALICA | G38: m2 | M38: =ARQUITECTURA!H38 -> 35 | Q38: =ROUND(SUM(BIBLIOTECA:INGRESO!G39),2) -> 35
A39: 3.06 | B39: PINTURA
A40: 03.06.01 | B40: PINTURA LATEX PARA INTERIOR - 2 MANOS (MUROS, TECHOS, VIGAS Y COLUMNAS) | G40: m2 | M40: =ARQUITECTURA!H40 -> 2395.93 | Q40: =ROUND(SUM(BIBLIOTECA:INGRESO!G41),2) -> 2395.93
A41: 03.06.02 | B41: PINTURA OLEO PARA EXTERIORES - 2 MANOS | G41: m2 | M41: =ARQUITECTURA!H41 -> 707.89 | Q41: =ROUND(SUM(BIBLIOTECA:INGRESO!G42),2) -> 707.89
A43: 3.07 | B43: OBRAS EXTERIORES
A44: 03.07.01 | B44: AREAS VERDES
A45: 03.07.01.01 | B45: SUMINISTRO Y PREPARACIÓN DE TIERRA DE CHACRA | G45: m2 | M45: =ARQUITECTURA!H45 -> 30 | Q45: =ROUND('Obras exteriores '!D5,2) -> 30
A46: 03.07.01.02 | B46: SUMINISTRO Y SEMBRIO DE ARBUSTOS | G46: und | M46: =ARQUITECTURA!H46 -> 10 | Q46: =ROUND('Obras exteriores '!D6,2) -> 10
A47: 03.07.01.03 | B47: SUMINISTRO Y SEMBRIO DE ARBOLES | G47: und | M47: =ARQUITECTURA!H47 -> 3 | Q47: =ROUND('Obras exteriores '!D7,2) -> 3
A48: 03.07.02 | B48: LOSA DEPORTIVA
A49: 03.07.02.01 | B49: PINTURA DE LINEAS EN LOSA DEPORTIVA | G49: m | M49: =ARQUITECTURA!H49 -> 0.5 | Q49: =ROUND('Obras exteriores '!D21,2) -> 0.5
A50: 03.07.03 | B50: PATIO DE FORMACIÓN
A51: 03.07.03.01 | B51: PINTURA DE LINEAS EN PATIO DE INICIAL | G51: m | M51: =ARQUITECTURA!H51 -> 0.5 | Q51: =ROUND('Obras exteriores '!D37,2) -> 0.5
A52: 03.07.04 | B52: VEREDAS Y RAMPAS DE CONCRETO
A53: 03.07.04.01 | B53: ACABADO FROTACHADO Y BRUÑADO EN VEREDAS | G53: m2 | M53: =ARQUITECTURA!H53 -> 20 | Q53: =ROUND('Obras exteriores '!D51,2) -> 20
A54: 03.07.05 | B54: PAVIMENTO RIGIDO VEHICULAR
A55: 03.07.05.01 | B55: ACABADO CEPILLADO | G55: glb | M55: =ARQUITECTURA!H55 -> 20 | Q55: =ROUND('Obras exteriores '!D60,2) -> 20
A56: 03.07.06 | B56: LAMAS EN PASADIZOS
A57: 03.07.06.01 | B57: LAMAS EN PASADIZOS | G57: m2 | M57: =ARQUITECTURA!H57 -> 20 | Q57: =ROUND('Obras exteriores '!D66,2) -> 20
A58: 03.07.07 | B58: CERCO PERIMETRICO
A59: 03.07.07.01 | B59: MURO DE LADRILLO | G59: m | M59: =ARQUITECTURA!H59 -> 43.21 | Q59: =ROUND('Obras exteriores '!D86,2) -> 43.21
A60: 03.07.07.02 | B60: TARRAJEO COLUMNAS Y PLACAS | G60: m2 | M60: =ARQUITECTURA!H60 -> 7.73 | Q60: =ROUND('Obras exteriores '!D88,2) -> 7.73
A61: 03.07.07.03 | B61: TARRAJEO DE VIGAS | G61: m2 | M61: =ARQUITECTURA!H61 -> 8 | Q61: =ROUND('Obras exteriores '!D89,2) -> 8
A62: 03.07.07.04 | B62: PINTURA DE MUROS | G62: m2 | M62: =ARQUITECTURA!H62 -> 112 | Q62: =ROUND('Obras exteriores '!D90,2) -> 112
A63: 03.07.08 | B63: ASTA DE BANDERA
A64: 03.07.08.01 | B64: ASTA DE BANDERA | G64: und | M64: =ARQUITECTURA!H64 -> 2 | Q64: =ROUND('Obras exteriores '!D40,2) -> 2
A65: 03.07.09 | B65: COBERTURAS
A66: 03.07.09.01 | B66: COBERTURA LIVIANA DE LOSA DEPORTIVA | G66: m2 | M66: =ARQUITECTURA!H66 -> 20 | Q66: =ROUND('Obras exteriores '!D22,2) -> 20
A67: 03.07.09.02 | B67: COBERTURA LIVIANA DE PATIO DE INICIAL | G67: m2 | M67: =ARQUITECTURA!H67 -> 20 | Q67: =ROUND('Obras exteriores '!D38,2) -> 20

Sheet Metrado Sanitarias
G2: Unidad | H2: Largo | I2: Ancho | J2: Alto | K2: Área | L2: Volumen | M2: Cantidad | N2: N°Elem | O2: Factor | P2: Parcial | Q2: Metrado
A3: 4 | B3: INSTALACIONES SANITARIAS
A4: 4.01 | B4: APARATOS SANITARIOS
A5: 04.01.01 | B5: INODORO | G5: und | M5: =SANITARIAS!H5 -> 159 | Q5: =ROUNDUP(SUM(BIBLIOTECA:INGRESO!G44),0) -> 159
A6: 04.01.02 | B6: URINARIO | G6: und | M6: =SANITARIAS!H6 -> 91 | Q6: =ROUNDUP(SUM(BIBLIOTECA:INGRESO!G45),0) -> 91
A7: 04.01.03 | B7: LAVATORIO | G7: und | M7: =SANITARIAS!H7 -> 165 | Q7: =ROUNDUP(SUM(BIBLIOTECA:INGRESO!G46),0) -> 165
A8: 04.01.04 | B8: LAVADEROS DE LIMPIEZA DE MAMPOSTERIA DE LADRILLO REVESTIDO CON CERAMICA + GRIFERIA | G8: und | M8: =SANITARIAS!H8 -> 24 | Q8: =ROUNDUP(SUM(BIBLIOTECA:INGRESO!G47),0) -> 24
A9: 4.02 | B9: SALIDAS DE AGUA
A10: 04.02.01 | B10: SALIDA DE AGUA FRIA PVC INC. TUBERIA Y ACCESORIOS 1/2" | G10: pto | M10: =SANITARIAS!H10 -> 193 | Q10: =ROUNDUP(SUM(BIBLIOTECA:INGRESO!G48),0) -> 193
A11: 04.02.02 | B11: SALIDA DE AGUA CALIENTE, CON TUBERIA CPVC (PROMEDIO) | G11: pto | M11: =SANITARIAS!H11 -> 58 | Q11: =ROUNDUP(SUM(BIBLIOTECA:INGRESO!G49),0) -> 58
A12: 4.03 | B12: VALVULAS
A13: 04.03.01 | B13: VALVULAS COMPUERTAS, ESFERICAS Y CAJAS PARA VALVULAS | G13: und | M13: =SANITARIAS!H13 -> 192 | Q13: =ROUNDUP(SUM(BIBLIOTECA:INGRESO!G50),0) -> 192
A14: 4.04 | B14: EXTINTORES Y GABINETES
A15: 04.04.01 | B15: EXTINTORES Y GABINETES | G15: und | M15: =SANITARIAS!H15 -> 16 | Q15: =ROUNDUP(SUM(BIBLIOTECA:INGRESO!G51),0) -> 16
A16: 4.05 | B16: SALIDAS DRENAJE PLUVIAL
A17: 04.05.01 | B17: DRENAJE PLUVIAL | G17: pto | M17: =SANITARIAS!H17 -> 5 | Q17: =ROUND(1.3*'Datos iniciales '!B3/75,0) -> 5
A18: 4.06 | B18: DESAGÜE
A19: 04.06.01 | B19: SALIDA DE DESAGUE PVC-SAL 2" | G19: pto | M19: =SANITARIAS!H19 -> 202 | Q19: =ROUNDUP(SUM(BIBLIOTECA:INGRESO!G53),0) -> 202
A20: 04.06.02 | B20: SALIDA DE DESAGUE PVC-SAL 4" | G20: pto | M20: =SANITARIAS!H20 -> 202 | Q20: =ROUNDUP(SUM(BIBLIOTECA:INGRESO!G54),0) -> 202
A21: 4.07 | B21: VENTILACIÓN
A22: 04.07.01 | B22: SALIDA DE VENTILACION (PROMEDIO) | G22: pto | M22: =SANITARIAS!H22 -> 202 | Q22: =ROUNDUP(SUM(BIBLIOTECA:INGRESO!G55),0) -> 202
A23: 4.08 | B23: ACCESORIOS
A24: 04.08.01 | B24: MEZCLADORA DE DUCHA | G24: und | M24: =SANITARIAS!H24 -> 55 | Q24: =ROUNDUP(SUM(BIBLIOTECA:INGRESO!G56),0) -> 55
A25: 04.08.02 | B25: JABONERA DE LOSA PARA EMPOTRAR | G25: und | M25: =SANITARIAS!H25 -> 55 | Q25: =ROUNDUP(SUM(BIBLIOTECA:INGRESO!G57),0) -> 55
A26: 4.09 | B26: INSTALACIONES EXTERIORES
A27: 04.09.01 | B27: SISTEMA DE BOMBEO DE PRESIÓN CONSTANTE | G27: Glb | M27: =SANITARIAS!H27 -> 1 | Q27: 1
A28: 04.09.02 | B28: INSTALACIONES SANITARIAS EXTERIORES INC. CANALETAS DE EVACUACIÓN PLUVIAL | G28: Glb | M28: =SANITARIAS!H28 -> 1 | Q28: 1
A29: 04.09.03 | B29: SISTEMA DE AGUA CONTRA INCENDIOS (RED CONTRA INCENDIOS, GABINETES) | G29: Glb | M29: =SANITARIAS!H29 -> 1 | Q29: 1

Sheet Metrado Electricas
G2: Unidad | H2: Largo | I2: Ancho | J2: Alto | K2: Área | L2: Volumen | M2: Cantidad | N2: N°Elem | O2: Factor | P2: Parcial | Q2: Metrado
A3: 5 | B3: INSTALACIONES ELECTRICAS
A4: 5.01 | B4: SALIDAS
A5: 05.01.01 | B5: SALIDAS PARA ALUMBRADO, TOMACORRIENTES, FUERZA Y SEÑALES DÉBILES | G5: pto | M5: =ELECTRICAS!H5 -> 449 | Q5: =ROUNDUP(SUM(BIBLIOTECA:INGRESO!G59),0) -> 449
A6: 05.01.02 | B6: SALIDAS PARA TOMACORRIENTES | G6: pto | M6: =ELECTRICAS!H6 -> 449 | Q6: =ROUNDUP(SUM(BIBLIOTECA:INGRESO!G60),0) -> 449
A7: 05.01.03 | B7: SALIDAS PARA FUERZA Y SEÑALES DÉBILES | G7: pto | M7: =ELECTRICAS!H7 -> 449 | Q7: =ROUNDUP(SUM(BIBLIOTECA:INGRESO!G61),0) -> 449
A8: 05.01.04 | B8: SALIDAS TRIFÁSICAS | G8: pto | M8: =ELECTRICAS!H8 -> 30 | Q8: =ROUNDUP(SUM(BIBLIOTECA:INGRESO!G62),0) -> 30
A9: 5.02 | B9: LÁMPARAS
A10: 05.02.01 | B10: ARTEFACTO DE ILUMINACIÓN P = 63 W L = 8000 LM | G10: und | M10: =ELECTRICAS!H10 -> 141 | Q10: =ROUNDUP(SUM(BIBLIOTECA:INGRESO!G64),0) -> 141
A11: 05.02.02 | B11: INSTALACIÓN DE ARTEFACTO DE ILUMINACIÓN, P=63 W L=8000 LM | G11: und | M11: =ELECTRICAS!H11 -> 141 | Q11: =ROUNDUP(SUM(BIBLIOTECA:INGRESO!G65),0) -> 141
A12: 05.02.03 | B12: PROYECTOR Y PANTALLA | G12: und | M12: =ELECTRICAS!H12 -> 11 | Q12: =ROUNDUP(SUM(BIBLIOTECA:INGRESO!G66),0) -> 11
A13: 05.02.04 | B13: EXTRACTORES DE AIRE | G13: und | M13: =ELECTRICAS!H13 -> 3 | Q13: =ROUNDUP(SUM(BIBLIOTECA:INGRESO!G67),0) -> 3
A14: 05.02.05 | B14: SISTEMA DE BAJA TENSIÓN | G14: und | M14: =ELECTRICAS!H14 -> 106 | Q14: =ROUND('Datos iniciales '!B69,2) -> 106
A15: 05.02.06 | B15: SISTEMA DE MEDIA TENSIÓN | G15: und | M15: =ELECTRICAS!H15 -> 106 | Q15: =ROUND('Datos iniciales '!B69,2) -> 106

Sheet Metrado Comunicaciones
G2: Unidad | H2: Largo | I2: Ancho | J2: Alto | K2: Área | L2: Volumen | M2: Cantidad | N2: N°Elem | O2: Factor | P2: Parcial | Q2: Metrado
A3: 6 | B3: INSTALACIONES COMUNICACIONES
A4: 6.01 | B4: CANALIZACIÓN, CONDUCTOS Y/O TUBERÍAS
A5: 06.01.01 | B5: INSTALACION DE PUNTOS DE RED EN PISO | G5: und | M5: =COMUNICACIONES!H5 -> 26 | Q5: =ROUNDUP(SUM(BIBLIOTECA:INGRESO!G72),0) -> 26
A6: 06.01.02 | B6: INSTALACION DE PUNTOS DE RED EN PARED | G6: und | M6: =COMUNICACIONES!H6 -> 26 | Q6: =ROUNDUP(SUM(BIBLIOTECA:INGRESO!G73),0) -> 26
A7: 06.01.03 | B7: INSTALACION DE PUNTOS DE RED EN CIELO RASO | G7: und | M7: =COMUNICACIONES!H7 -> 26 | Q7: =ROUNDUP(SUM(BIBLIOTECA:INGRESO!G74),0) -> 26
A8: 06.01.04 | B8: TUBERIA PVC-P ELÉCTRICA Ø50mm, NTP 339.006 | G8: m | M8: =COMUNICACIONES!H8 -> 1.56 | Q8: =ROUND(SUM(BIBLIOTECA:INGRESO!G75),2) -> 1.56
A9: 06.01.05 | B9: TUBERIA PVC-P ELÉCTRICA Ø40mm, NTP 339.006 | G9: m | M9: =COMUNICACIONES!H9 -> 35.36 | Q9: =ROUND(SUM(BIBLIOTECA:INGRESO!G76),2) -> 35.36
A10: 06.01.06 | B10: TUBERIA PVC-P ELÉCTRICA Ø25mm, NTP 339.006 | G10: m | M10: =COMUNICACIONES!H10 -> 142.48 | Q10: =ROUND(SUM(BIBLIOTECA:INGRESO!G77),2) -> 142.48
A11: 06.01.07 | B11: TUBERIA PVC-P ELÉCTRICA Ø15mm, NTP 339.006 | G11: m | M11: =COMUNICACIONES!H11 -> 0.78 | Q11: =ROUND(SUM(BIBLIOTECA:INGRESO!G78),2) -> 0.78
A12: 06.01.08 | B12: CAJA DE PASE FºGº 300x300x100mm | G12: und | M12: =COMUNICACIONES!H12 -> 26 | Q12: =ROUNDUP(SUM(BIBLIOTECA:INGRESO!G79),0) -> 26
A13: 06.01.09 | B13: CAJA DE PASE FºGº 200x200x100mm | G13: und | M13: =COMUNICACIONES!H13 -> 26 | Q13: =ROUNDUP(SUM(BIBLIOTECA:INGRESO!G80),0) -> 26
A14: 06.01.10 | B14: CAJA DE PASE FºGº 100x100x100mm | G14: und | M14: =COMUNICACIONES!H14 -> 26 | Q14: =ROUNDUP(SUM(BIBLIOTECA:INGRESO!G81),0) -> 26
A15: 06.01.11 | B15: BANDEJA PORTACABLE 200x54 P/COMUNICACIÓN | G15: m | M15: =COMUNICACIONES!H15 -> 6.5 | Q15: =ROUND(SUM(BIBLIOTECA:INGRESO!G82),2) -> 6.5
A16: 6.02 | B16: SISTEMA ESTRUCTURADO Y NETWORKING
A17: 06.02.01 | B17: SUMINISTRO E INSTALACIÓN DE RECEPTOR MO ISP | G17: und | M17: =COMUNICACIONES!H17 -> 1 | Q17: 1
A18: 06.02.02 | B18: SUMINISTRO E INSTALACIÓN DE ROUTER | G18: und | M18: =COMUNICACIONES!H18 -> 1 | Q18: 1
A19: 06.02.03 | B19: SUMINISTRO E INSTALACION SWITCH GIGABIT 48 PORT | G19: und | M19: =COMUNICACIONES!H19 -> 1 | Q19: 1
A20: 06.02.04 | B20: SUMINISTRO E INSTALACION DE PATCH PANEL 48 PORT | G20: und | M20: =COMUNICACIONES!H20 -> 1 | Q20: 1
A21: 06.02.05 | B21: SUMINISTRO E INSTALACION DE SERVIDOR | G21: und | M21: =COMUNICACIONES!H21 -> 1 | Q21: 1
A22: 06.02.06 | B22: SUMINISTRO E INSTALACION DE SERVIDOR NVR | G22: und | M22: =COMUNICACIONES!H22 -> 1 | Q22: 1
A23: 06.02.07 | B23: SUMINISTRO E INSTALACION DE SWITH POE 16 PORT | G23: und | M23: =COMUNICACIONES!H23 -> 1 | Q23: 1
A24: 06.02.08 | B24: SUMINISTRO E INSTALACION DE PATCH PANEL 24 PORT | G24: und | M24: =COMUNICACIONES!H24 -> 1 | Q24: 1
A25: 06.02.09 | B25: SUMINISTRO E INSTALACION DE BANDEJA 19" | G25: und | M25: =COMUNICACIONES!H25 -> 1 | Q25: 1
A26: 06.02.10 | B26: SUMINISTRO E INSTALACION DE BANDEJA EQUIPO ALARMAS | G26: und | M26: =COMUNICACIONES!H26 -> 1 | Q26: 1
A27: 06.02.11 | B27: SUMINISTRO E INSTALACION DE BANDEJA TELEFONIA IP PBX | G27: und | M27: =COMUNICACIONES!H27 -> 1 | Q27: 1
A28: 06.02.12 | B28: SUMINISTRO E INSTALACION DE BANDEJA 19" | G28: und | M28: =COMUNICACIONES!H28 -> 1 | Q28: 1
... A31: 06.02.15 | B31: CONEXIÓN DE GABINETE 42RU Y COMPONENTES DE REDES | G31: und | M31: =COMUNICACIONES!H31 -> 1 | Q31: 1
A32: 6.03 | B32: SISTEMA CCTV
A33: 06.03.01 | B33: SERVIDOR NVR 1RU | G33: und | M33: =COMUNICACIONES!H33 -> 1 | Q33: 1
A34: 06.03.02 | B34: VIDEOCAMARA TUBULAR IP | G34: und | M34: =COMUNICACIONES!H34 -> 26 | Q34: =ROUNDUP(SUM(BIBLIOTECA:INGRESO!G85),0) -> 26
A35: 06.03.03 | B35: VIDEOCAMARA DOMO IP | G35: und | M35: =COMUNICACIONES!H35 -> 26 | Q35: =ROUNDUP(SUM(BIBLIOTECA:INGRESO!G86),0) -> 26
A36: 6.04 | B36: SISTEMA MEGAFONÍA (PERIFONEO)
A37: 06.04.01 | B37: AMPLIFICADOR DE AUDIO DE 100W | G37: und | M37: =COMUNICACIONES!H37 -> 1 | Q37: 1
A38: 06.04.02 | B38: PARLANTE IP DE TECHO | G38: und | M38: =COMUNICACIONES!H38 -> 26 | Q38: =ROUNDUP(SUM(BIBLIOTECA:INGRESO!G88),0) -> 26
A39: 6.05 | B39: SISTEMA DACI (DETECCIÓN Y ALARMA CONTRA INCENDIO)
A40: 06.05.01 | B40: EQUIPAMIENTO DE UNIDAD CENTRAL DEL SISTEMA DE ALARMA CONTRA INCENDIO | G40: und | M40: =COMUNICACIONES!H40 -> 1 | Q40: 1
A41: 06.05.02 | B41: SUMINISTRO E INSTALACION DE DETECTOR DE HUMO | G41: und | M41: =COMUNICACIONES!H41 -> 26 | Q41: =ROUNDUP(SUM(BIBLIOTECA:INGRESO!G90),0) -> 26
A42: 06.05.03 | B42: SALIDA PARA ALARMA CONTRA INCENDIO | G42: und | M42: =COMUNICACIONES!H42 -> 26 | Q42: =ROUNDUP(SUM(BIBLIOTECA:INGRESO!G91),0) -> 26

Sheet Obras provisionales
M2: Area de terreno | N2: ='Datos iniciales '!C3 -> 1000
E3: Factor | F3: Ratio | G3: Unidad | H3: Metrado | I3: C.U | J3: Parcial | K3: Total | M3: Area techada | N3: ='Datos iniciales '!B3 -> 300
M4: Plazo | N4: ='Datos iniciales '!D3 -> 12 | O4: meses
A6: OBRAS PROVISIONALES, PRELIMINARES, SEGURIDAD Y SALUD EN EL TRABAJO Y PLAN DE CONTINGENCIA | Q6: Partida | S6: OFICINAS DE RESIDENCIA Y SUPERVISIÓN
A7: OBRAS PROVISIONALES | K7: =SUM(J9:J112) -> 218222.32 | Q7: Rendimiento m2/día | R7: m2/dia | S7: M.O | T7: 25 | U7: EQ | V7: =T7 -> 25 | W7: Costo unitario directo | Y7: und | Z7: =Z14+Z26+Z29 -> 158.90001
A8: CONSTRUCCIONES PROVISIONALES | Q8: Código | R8: Descripción Recurso | V8: Unidad | W8: Cuadrilla | X8: Cantidad | Y8: Precio (S/.) | Z8: Parcial (S/.)
A9: OFICINAS DE RESIDENCIA Y SUPERVISIÓN | G9: m² | H9: 50 | I9: =Z7 -> 158.90001 | J9: =H9*I9 -> 7945.0005 | R9: Mano de Obra
A10: ALMACENES DE OBRA | G10: m² | H10: =ROUND(0.01*N3,0) -> 3 | I10: =Z32 -> 144.64563 | J10: =H10*I10 -> 433.93689
A11: CASETAS DE GUARDIANÍA | G11: m² | H11: 8 | I11: =Z56 -> 148.03953 | J11: =H11*I11 -> 1184.3162 | R11: OPERARIO | V11: hh | W11: 1 | X11: =W11*8/$T$7 -> 0.32 | Y11: 28.94 | Z11: =X11*Y11 -> 9.2608
A12: COMEDOR PARA PERSONAL DE OBRA | G12: m² | H12: 50 | I12: =Z80 -> 152.56473 | J12: =H12*I12 -> 7628.2365 | R12: OFICIAL | V12: hh | W12: 1 | X12: =W12*8/$T$7 -> 0.32 | Y12: 22.66 | Z12: =X12*Y12 -> 7.2512
A13: VESTUARIO PARA PERSONAL DE OBRA | G13: m² | H13: 25 | I13: =Z104 -> 206.19277 | J13: =H13*I13 -> 5154.8191 | R13: PEON | V13: hh | W13: 3 | X13: =W13*8/$T$7 -> 0.96 | Y13: 20.51 | Z13: =X13*Y13 -> 19.6896
A14: CERCO PERIMÉTRICO DE MALLA ARPILLERA | G14: m | H14: =ROUND(4*(N2)^0.5,2) -> 126.49 | I14: =Z128 -> 43.81136 | J14: =H14*I14 -> 5541.6989 | Z14: =SUM(Z10:Z13) -> 36.2016
A15: SERVICIOS HIGIÉNICOS | G15: m² | H15: 16 | I15: =Z144 -> 343.16159 | J15: =H15*I15 -> 5490.5854 | R15: Materiales
A16: CARTEL DE IDENTIFICACIÓN DE LA OBRA | G16: und | H16: 2 | I16: =Z173 -> 1453.7775 | J16: =H16*I16 -> 2907.555 | R16: ALAMBRE NEGRO RECOCIDO BWG N 16 | V16: kg | X16: 1.25 | Y16: 2.64 | Z16: =X16*Y16 -> 3.3
A17: INSTALACIONES PROVISIONALES | R17: CALAMINA | V17: pln | X17: 1.8 | Y17: 14.15 | Z17: =X17*Y17 -> 25.47
A18: CONEXIÓN E INSTALACIÓN DE AGUA | G18: glb | H18: 1 | I18: 251.61 | J18: =PRODUCT(H18*I18) -> 251.61 | R18: CERRADURA CLÁSICA ADOSADA BK 233 | V18: und | X18: 0.2 | Y18: 55 | Z18: =X18*Y18 -> 11
A19: CONSUMO Y MANTENIMIENTO DE AGUA PARA LA CONSTRUCCIÓN | G19: mes | H19: =N4 -> 12 | I19: 185.89 | J19: =PRODUCT(H19*I19) -> 2230.68 | R19: CLAVOS PARA CALAMINA | V19: kg | X19: 0.06 | Y19: 10.93 | Z19: =X19*Y19 -> 0.6558
A20: CONEXIÓN E INSTALACIÓN DE ENERGÍA ELÉCTRICA | G20: glb | H20: 1 | I20: 976.39 | J20: =PRODUCT(H20*I20) -> 976.39 | R20: CLAVO C/CABEZA P/CONSTRUCCION D.PROMEDIO | V20: kg | X20: 0.071 | Y20: 5.51 | Z20: =X20*Y20 -> 0.39121
A21: CONSUMO Y MANTENIMIENTO DE ENERGÍA ELÉCTRICA | G21: mes | H21: =N4 -> 12 | I21: 185.89 | J21: =PRODUCT(H21*I21) -> 2230.68 | R21: HORMIGON | V21: m3 | X21: 0.19 | Y21: 70.92 | Z21: =X21*Y21 -> 13.4748
R22: TRIPLAY ENCHAPE CEDRO 4' x 8' x 4mm | V22: pln | X22: 0.53 | Y22: 27.88 | Z22: =X22*Y22 -> 14.7764
R23: VIDRIO CLARO 4MM | V23: p2 | X23: 0.2374 | Y23: 32.2 | Z23: =X23*Y23 -> 7.64428
R24: CEMENTO PORTLAND TIPO I (42.5 kg) | V24: bls | X24: 1.092 | Y24: 24.52 | Z24: =X24*Y24 -> 26.77584
A25: TRABAJOS PRELIMINARES | R25: MADERA TORNILLO | V25: p2 | X25: 3 | Y25: 5.8 | Z25: =X25*Y25 -> 17.4
A26: LIMPIEZA DEL TERRENO | Z26: =SUM(Z16:Z25) -> 120.88833
A27: LIMPIEZA DEL TERRENO (MANUAL) | G27: m² | H27: =N2 -> 1000 | I27: =Z255 -> 1.14856 | J27: =H27*I27 -> 1148.56 | R27: Equipos
A28: ELIMINACIÓN DE OBSTRUCCIONES | G28: m² | H28: =N2 -> 1000 | I28: =Z265 -> 1.3594756 | J28: =H28*I28 -> 1359.4756 | R28: HERRAMIENTAS MANUALES | V28: %mo | X28: 5 | Y28: =Z14 -> 36.2016 | Z28: =X28%*Y28 -> 1.81008
A29: MOVILIZACIÓN DE CAMPAMENTO, MAQUINARIA Y HERRAMIENTAS | Z29: =SUM(Z28) -> 1.81008
A30: MOVILIZACIÓN DE EQUIPOS Y HERRAMIENTAS | G30: glb | H30: 1 | I30: =0.05%*'Datos iniciales '!F91 -> 1746.2404 | J30: =H30*I30 -> 1746.2404
A31: TRANSPORTE DE MATERIALES A LA OBRA | G31: glb | H31: 1 | I31: =0.2%*'Datos iniciales '!F91 -> 6984.9618 | J31: =H31*I31 -> 6984.9618 | Q31: Partida | S31: ALMACENES DE OBRA
A32: TRAZOS, NIVELES Y REPLANTEO | Q32: Rendimiento m2/día | R32: m2/dia | S32: M.O | T32: 40 | U32: EQ | V32: =T32 -> 40 | W32: Costo unitario directo | Y32: und | Z32: =Z38+Z50+Z53 -> 144.64563
A33: TRAZO Y REPLANTEO PRELIMINAR | G33: m² | H33: =N2 -> 1000 | I33: =Z290 -> 3.97626 | J33: =H33*I33 -> 3976.26 | Q33: Código | R33: Descripción Recurso | V33: Unidad | W33: Cuadrilla | X33: Cantidad | Y33: Precio (S/.) | Z33: Parcial (S/.)
A34: TRAZO NIVELACIÓN Y REPLANTEO | G34: m² | H34: =N2 -> 1000 | I34: =Z310 -> 4.26553 | J34: =H34*I34 -> 4265.53 | R34: Mano de Obra
A35: PLAN DE SEGURIDAD Y SALUD EN EL TRABAJO | R35: OPERARIO | V35: hh | W35: 1 | X35: =W35*8/$T$32 -> 0.2 | Y35: 28.94 | Z35: =X35*Y35 -> 5.788
A36: Equipo de seguridad y salud | R36: OFICIAL | V36: hh | W36: 1 | X36: =W36*8/$T$32 -> 0.2 | Y36: 22.66 | Z36: =X36*Y36 -> 4.532
A37: Equipos de protección individual | G37: glb | H37: 1 | I37: =Z352 -> 41043.35 | J37: =H37*I37 -> 41043.35 | R37: PEON | V37: hh | W37: 3 | X37: =W37*8/$T$32 -> 0.6 | Y37: 20.51 | Z37: =X37*Y37 -> 12.306
A38: Equipos de protección colectiva | G38: glb | H38: 1 | I38: =Z355 -> 3824.87 | J38: =H38*I38 -> 3824.87 | Z38: =SUM(Z35:Z37) -> 22.626
A39: Señalización temporal de seguridad | G39: glb | H39: 1 | I39: =Z378 -> 6076.5 | J39: =H39*I39 -> 6076.5 | R39: Materiales
A40: Programa de capacitaciones | G40: glb | H40: 1 | I40: =Z387 -> 18386.64 | J40: =H40*I40 -> 18386.64 | R40: ALAMBRE NEGRO RECOCIDO BWG N 16 | V40: kg | X40: 1.25 | Y40: 2.64 | Z40: =X40*Y40 -> 3.3
A41: Recursos para respuesta ante emergencias | G41: glb | H41: 1 | I41: =Z390 -> 1478.8 | J41: =H41*I41 -> 1478.8 | R41: CALAMINA | V41: pln | X41: 1.8 | Y41: 14.15 | Z41: =X41*Y41 -> 25.47
A42: Programa de prevención y control | G42: und | H42: 1 | I42: =Z402 -> 8515.8 | J42: =H42*I42 -> 8515.8 | R42: CERRADURA CLÁSICA ADOSADA BK 233 | V42: und | X42: 0.2 | Y42: 55 | Z42: =X42*Y42 -> 11
A43: Examen médico general | G43: und | H43: 1 | I43: =Z410 -> 29152.28 | J43: =H43*I43 -> 29152.28 | R43: CLAVOS PARA CALAMINA | V43: kg | X43: 0.06 | Y43: 10.93 | Z43: =X43*Y43 -> 0.6558
A44: PLAN DE MANEJO AMBIENTAL | R44: CLAVO C/CABEZA P/CONSTRUCCION D.PROMEDIO | V44: kg | X44: 0.071 | Y44: 5.51 | Z44: =X44*Y44 -> 0.39121
A45: PROGRAMA DE PREVENCIÓN Y MITIGACIÓN AMBIENTAL | R45: HORMIGON | V45: m3 | X45: 0.19 | Y45: 70.92 | Z45: =X45*Y45 -> 13.4748
A46: Prevención y mitigación de impactos | G46: m³ | H46: 609.6 | I46: =Z418 -> 32.55584 | J46: =H46*I46 -> 19846.04 | R46: TRIPLAY ENCHAPE CEDRO 4' x 8' x 4mm | V46: pln | X46: 0.53 | Y46: 27.88 | Z46: =X46*Y46 -> 14.7764
A47: Implementación de área de señalización | G47: und | H47: 16 | I47: =Z431 -> 115.47972 | J47: =H47*I47 -> 1847.6755 | R47: VIDRIO CLARO 4MM | V47: p2 | X47: 0.2374 | Y47: 32.2 | Z47: =X47*Y47 -> 7.64428
A48: PROGRAMA DE EDUCACIÓN Y CAPACITACIÓN AMBIENTAL | R48: CEMENTO PORTLAND TIPO I (42.5 kg) | V48: bls | X48: 1.092 | Y48: 24.52 | Z48: =X48*Y48 -> 26.77584
A49: Charlas de sensibilización ambiental | G49: glb | H49: 12 | I49: =Z454 -> 135.964 | J49: =H49*I49 -> 1631.568 | R49: MADERA TORNILLO | V49: p2 | X49: 3 | Y49: 5.8 | Z49: =X49*Y49 -> 17.4
A50: PROGRAMA DE SEGUIMIENTO, CONTROL Y VIGILANCIA AMBIENTAL | Z50: =SUM(Z40:Z49) -> 120.88833
A51: Monitoreo de calidad ambiental | G51: pto | H51: 6 | I51: =Z457 -> 1915.25 | J51: =H51*I51 -> 11491.5 | R51: Equipos
A52: PROGRAMA DE MANEJO DE RESIDUOS SÓLIDOS | R52: HERRAMIENTAS MANUALES | V52: %mo | X52: 5 | Y52: =Z38 -> 22.626 | Z52: =X52%*Y52 -> 1.1313
A53: Manejo de residuos peligrosos | Z53: =SUM(Z52) -> 1.1313
A54: Adquisición de contenedores | G54: und | H54: 3 | I54: =Z464 -> 167.0412 | J54: =H54*I54 -> 501.1236
A55: Recolección de residuos peligrosos | G55: m³ | H55: =0.75*$N$4 -> 9 | I55: =Z477 -> 163.19213 | J55: =H55*I55 -> 1468.7292 | Q55: Partida | S55: CASETAS DE GUARDIANÍA
A56: Eliminación y transporte | G56: m³ | H56: =0.75*$N$4 -> 9 | I56: =Z495 -> 406.78 | J56: =H56*I56 -> 3661.02 | Q56: Rendimiento m2/día | R56: m2/dia | S56: M.O | T56: 35 | U56: EQ | V56: =T56 -> 35 | W56: Costo unitario directo | Y56: und | Z56: =Z62+Z74+Z77 -> 148.03953
A57: Manejo de residuos no peligrosos | Q57: Código | R57: Descripción Recurso | V57: Unidad | W57: Cuadrilla | X57: Cantidad | Y57: Precio (S/.) | Z57: Parcial (S/.)
A58: Acondicionamiento | G58: m² | H58: =ROUND(0.001*N2,2) -> 1 | I58: =Z506 -> 80.19009 | J58: =H58*I58 -> 80.19009 | R58: Mano de Obra
A59: Adquisición de contenedores | G59: und | H59: 15 | I59: =Z526 -> 148.27205 | J59: =H59*I59 -> 2224.0807 | R59: OPERARIO | V59: hh | W59: 1 | X59: =W59*8/$T$56 -> 0.22857143 | Y59: 28.94 | Z59: =X59*Y59 -> 6.6148571
A60: Recolección de residuos | G60: m³ | H60: =ROUND(2*$N$4,2) -> 24 | I60: =Z539 -> 43.208133 | J60: =H60*I60 -> 1036.9952 | R60: OFICIAL | V60: hh | W60: 1 | X60: =W60*8/$T$56 -> 0.22857143 | Y60: 22.66 | Z60: =X60*Y60 -> 5.1794286
A61: Disposición final | G61: m³ | H61: =ROUND(3*$N$4,2) -> 36 | I61: =Z557 -> 13.786064 | J61: =H61*I61 -> 496.2983 | R61: PEON | V61: hh | W61: 3 | X61: =W61*8/$T$56 -> 0.68571429 | Y61: 20.51 | Z61: =X61*Y61 -> 14.064
A62: Manejo de residuos valorizables | Z62: =SUM(Z59:Z61) -> 25.858286
A63: Clasificación de residuos | G63: mes | H63: =N4 -> 12 | I63: =Z572 -> 68.271 | J63: =H63*I63 -> 819.252 | R63: Materiales
A64: Disposición final | G64: m³ | H64: =ROUND(0.8*$N$4,2) -> 9.6 | I64: =Z586 -> 13.786064 | J64: =H64*I64 -> 132.34621 | R64: ALAMBRE NEGRO RECOCIDO BWG N 16 | V64: kg | X64: 1.25 | Y64: 2.64 | Z64: =X64*Y64 -> 3.3
A65: PROGRAMA DE CONTINGENCIA | R65: CALAMINA | V65: pln | X65: 1.8 | Y65: 14.15 | Z65: =X65*Y65 -> 25.47
A66: Contingencia ante derrames | G66: und | H66: 1 | I66: =Z601 -> 402.0068 | J66: =H66*I66 -> 402.0068 | R66: CERRADURA CLÁSICA ADOSADA BK 233 | V66: und | X66: 0.2 | Y66: 55 | Z66: =X66*Y66 -> 11
A67: PROGRAMA DE CIERRE Y ABANDONO | R67: CLAVOS PARA CALAMINA | V67: kg | X67: 0.06 | Y67: 10.93 | Z67: =X67*Y67 -> 0.6558
A68: Manejo de residuos de desinstalación | G68: m² | H68: =ROUND(0.02*$N$2,2) -> 20 | I68: =Z617 -> 6.9493067 | J68: =H68*I68 -> 138.98613 | R68: CLAVO C/CABEZA P/CONSTRUCCION D.PROMEDIO | V68: kg | X68: 0.071 | Y68: 5.51 | Z68: =X68*Y68 -> 0.39121
A69: Traslado y disposición final | G69: m³ | H69: =ROUND(0.0015*$N$2,2) -> 1.5 | I69: =Z629 -> 24.086838 | J69: =H69*I69 -> 36.130257 | R69: HORMIGON | V69: m3 | X69: 0.19 | Y69: 70.92 | Z69: =X69*Y69 -> 13.4748
A70: Rehabilitación de suelos afectados | G70: m² | H70: =ROUND(0.003*$N$2,2) -> 3 | I70: =Z645 -> 7.69136 | J70: =H70*I70 -> 23.07408 | R70: TRIPLAY ENCHAPE CEDRO 4' x 8' x 4mm | V70: pln | X70: 0.53 | Y70: 27.88 | Z70: =X70*Y70 -> 14.7764
A71: Nivelación y compactación | G71: m² | H71: =ROUND(0.004*$N$2,2) -> 4 | I71: =Z659 -> 8.03264 | J71: =H71*I71 -> 32.13056 | R71: VIDRIO CLARO 4MM | V71: p2 | X71: 0.2374 | Y71: 32.2 | Z71: =X71*Y71 -> 7.64428
A72: DEMOLICIONES | R72: CEMENTO PORTLAND TIPO I (42.5 kg) | V72: bls | X72: 1.092 | Y72: 24.52 | Z72: =X72*Y72 -> 26.77584
A73: DESMONTAJE | R73: MADERA TORNILLO | V73: p2 | X73: 3 | Y73: 5.8 | Z73: =X73*Y73 -> 17.4
A74: DESMONTAJE DE TECHO DE TEJA ANDINA + ESTRUCTURA DE MADERA | G74: m² | H74: =ROUND(0.034*$N$3,2) -> 10.2 | I74: 16.07 | J74: =H74*I74 -> 163.914 | Z74: =SUM(Z64:Z73) -> 120.88833
A75: DESMONTAJE DE TECHO DE CALAMINA + ESTRUCTURA DE MADERA | G75: m² | H75: =ROUND(0.052*$N$3,2) -> 15.6 | I75: 20.09 | J75: =H75*I75 -> 313.404 | R75: Equipos
A76: DESMONTAJE DE CIELORRASO EXISTENTE | G76: m² | H76: =ROUND(0.047*$N$3,2) -> 14.1 | I76: 20.09 | J76: =H76*I76 -> 283.269 | R76: HERRAMIENTAS MANUALES | V76: %mo | X76: 5 | Y76: =Z62 -> 25.858286 | Z76: =X76%*Y76 -> 1.2929143
A77: DESMONTAJE DE PUERTAS METÁLICAS EXISTENTES | G77: m² | H77: =ROUND(0.001*$N$3,2) -> 0.3 | I77: 20.09 | J77: =H77*I77 -> 6.027 | Z77: =SUM(Z76) -> 1.2929143
A78: DESMONTAJE DE PUERTAS DE MADERA EXISTENTES | G78: m² | H78: =ROUND(0.0023*$N$3,2) -> 0.69 | I78: 20.09 | J78: =H78*I78 -> 13.8621
A79: DESMONTAJE DE VENTANAS EXISTENTES | G79: m² | H79: =ROUND(0.0038*$N$3,2) -> 1.14 | I79: 20.09 | J79: =H79*I79 -> 22.9026 | Q79: Partida | S79: COMEDOR PARA PERSONAL DE OBRA
A80: DESMONTAJE DE PISO DE MADERA | G80: m² | H80: =ROUND(0.037*$N$3,2) -> 11.1 | I80: 20.09 | J80: =H80*I80 -> 222.999 | Q80: Rendimiento m2/día | R80: m2/dia | S80: M.O | T80: 30 | U80: EQ | V80: =T80 -> 30 | W80: Costo unitario directo | Y80: und | Z80: =Z86+Z98+Z101 -> 152.56473
A81: DEMOLICIONES | Q81: Código | R81: Descripción Recurso | V81: Unidad | W81: Cuadrilla | X81: Cantidad | Y81: Precio (S/.) | Z81: Parcial (S/.)
A82: DEMOLICIÓN MANUAL DE PISO DE CONCRETO | G82: m² | H82: =ROUND(0.053*$N$3,2) -> 15.9 | I82: 54.2 | J82: =H82*I82 -> 861.78 | R82: Mano de Obra
A83: DEMOLICIÓN MANUAL DE MURO DE TAPIAL | G83: m³ | H83: =ROUND(0.044*$N$3,2) -> 13.2 | I83: 40.17 | J83: =H83*I83 -> 530.244 | R83: OPERARIO | V83: hh | W83: 1 | X83: =W83*8/$T$80 -> 0.26666667 | Y83: 28.94 | Z83: =X83*Y83 -> 7.7173333
R84: OFICIAL | V84: hh | W84: 1 | X84: =W84*8/$T$80 -> 0.26666667 | Y84: 22.66 | Z84: =X84*Y84 -> 6.0426667
R85: PEON | V85: hh | W85: 3 | X85: =W85*8/$T$80 -> 0.8 | Y85: 20.51 | Z85: =X85*Y85 -> 16.408
Z86: =SUM(Z83:Z85) -> 30.168
R87: Materiales
R88: ALAMBRE NEGRO RECOCIDO BWG N 16 | V88: kg | X88: 1.25 | Y88: 2.64 | Z88: =X88*Y88 -> 3.3
R89: CALAMINA | V89: pln | X89: 1.8 | Y89: 14.15 | Z89: =X89*Y89 -> 25.47
R90: CERRADURA CLÁSICA ADOSADA BK 233 | V90: und | X90: 0.2 | Y90: 55 | Z90: =X90*Y90 -> 11
R91: CLAVOS PARA CALAMINA | V91: kg | X91: 0.06 | Y91: 10.93 | Z91: =X91*Y91 -> 0.6558
R92: CLAVO C/CABEZA P/CONSTRUCCION D.PROMEDIO | V92: kg | X92: 0.071 | Y92: 5.51 | Z92: =X92*Y92 -> 0.39121
R93: HORMIGON | V93: m3 | X93: 0.19 | Y93: 70.92 | Z93: =X93*Y93 -> 13.4748
R94: TRIPLAY ENCHAPE CEDRO 4' x 8' x 4mm | V94: pln | X94: 0.53 | Y94: 27.88 | Z94: =X94*Y94 -> 14.7764
R95: VIDRIO CLARO 4MM | V95: p2 | X95: 0.2374 | Y95: 32.2 | Z95: =X95*Y95 -> 7.64428
R96: CEMENTO PORTLAND TIPO I (42.5 kg) | V96: bls | X96: 1.092 | Y96: 24.52 | Z96: =X96*Y96 -> 26.77584
R97: MADERA TORNILLO | V97: p2 | X97: 3 | Y97: 5.8 | Z97: =X97*Y97 -> 17.4
Z98: =SUM(Z88:Z97) -> 120.88833
R99: Equipos
R100: HERRAMIENTAS MANUALES | V100: %mo | X100: 5 | Y100: =Z86 -> 30.168 | Z100: =X100%*Y100 -> 1.5084
Z101: =SUM(Z100) -> 1.5084
Q103: Partida | S103: VESTUARIO PARA PERSONAL DE OBRA
...

Sheet Obras exteriores 
B1: Ratio | C1: Unidad | D1: Metrado | E1: C.U | F1: Parcial | G1: Total
I2: Areas verdes | J2: ='Datos iniciales '!E72 -> 20
A3: OBRAS EXTERIORES | I3: Losa DEPORTIVA | J3: ='Datos iniciales '!E73 -> 20
A4: Áreas Verdes | G4: =SUM(F5:F7) -> 1499.1221 | I4: cobertura | J4: ='Datos iniciales '!E74 -> 20 | M4: Partida | O4: AREA VERDES
A5: SUMINISTRO Y PREPARACIÓN DE TIERRA DE CHACRA | B5: 1.5 | C5: m2 | D5: =B5*$J$2 -> 30 | E5: =U8 -> 13.478589 | F5: =D5*E5 -> 404.35766 | I5: Patio de INICIAL | J5: ='Datos iniciales '!E75 -> 20 | M5: Rendimiento m2/día | N5: m2/dia | O5: M.O | P5: 1 | Q5: EQ | R5: =P5 -> 1 | S5: Costo unitario directo | U5: m2 | V5: =V11 -> 74.956105 | X5: SubPartida | Z5: SUMINISTRO Y PREPARACIÓN DE TIERRA DE CHACRA
A6: SUMINISTRO Y SEMBRIO DE ARBUSTOS | B6: 0.5 | C6: und | D6: =B6*$J$2 -> 10 | E6: =U9 -> 73.852121 | F6: =D6*E6 -> 738.52121 | I6: cobertura | J6: ='Datos iniciales '!E76 -> 20 | M6: Código | N6: Descripción Recurso | R6: Unidad | S6: Cuadrilla | T6: Cantidad | U6: Precio (S/.) | V6: Parcial (S/.) | X6: Rendimiento m2/día | Y6: m2/dia | Z6: M.O | AA6: 100 | AB6: EQ | AC6: =AA6 -> 100 | AD6: Costo unitario directo | AF6: m2 | AG6: =AG12+AG16+AG19 -> 13.478589
A7: SUMINISTRO Y SEMBRIO DE ARBOLES | B7: 0.15 | C7: und | D7: =B7*$J$2 -> 3 | E7: =U10 -> 118.74774 | F7: =D7*E7 -> 356.24322 | I7: asta de bandera | J7: ='Datos iniciales '!E77 -> 2 | N7: Subpartidas | X7: Código | Y7: Descripción Recurso | AC7: Unidad | AD7: Cuadrilla | AE7: Cantidad | AF7: Precio (S/.) | AG7: Parcial (S/.)
A8: Losa DEPORTIVA | C8: m2 | G8: =SUM(F9:F21) -> 3254.2781 | I8: veredas y rampas | J8: ='Datos iniciales '!E78 -> 20 | N8: SUMINISTRO Y PREPARACIÓN DE TIERRA DE CHACRA | R8: m2 | T8: 1.5 | U8: =AG6 -> 13.478589 | V8: =T8*U8 -> 20.217883 | Y8: Mano de Obra
I9: pavimento | J9: ='Datos iniciales '!E79 -> 20 | N9: SUMINISTRO Y SEMBRIO DE ARBUSTOS | R9: und | T9: 0.5 | U9: =AG22 -> 73.852121 | V9: =T9*U9 -> 36.926061 | Y9: CAPATAZ | AC9: hh | AD9: 0.1 | AE9: =AD9*8/$AA$6 -> 0.008 | AF9: 34.73 | AG9: =AE9*AF9 -> 0.27784
I10: LAMAS | J10: ='Datos iniciales '!E80 -> 20 | N10: SUMINISTRO Y SEMBRIO DE ARBOLES | R10: und | T10: 0.15 | U10: =AG39 -> 118.74774 | V10: =T10*U10 -> 17.812161 | Y10: OFICIAL | AC10: hh | AD10: 1 | AE10: =AD10*8/$AA$6 -> 0.08 | AF10: 22.66 | AG10: =AE10*AF10 -> 1.8128
A11: COMPACTACION DE SUBRASANTE | B11: 1 | C11: m3 | D11: =B11*$J$3 -> 20 | E11: =U61 -> 7.930344 | F11: =D11*E11 -> 158.60688 | I11: bicicletas | J11: ='Datos iniciales '!E81 -> 2 | V11: =SUM(V8:V10) -> 74.956105 | Y11: PEON | AC11: hh | AD11: 1 | AE11: =AD11*8/$AA$6 -> 0.08 | AF11: 20.51 | AG11: =AE11*AF11 -> 1.6408
A12: AFIRMADO DE e=0.30m PARA LOSA | B12: 0.33 | C12: m3 | D12: =B12*$J$3 -> 6.6 | E12: =U62 -> 77.227705 | F12: =D12*E12 -> 509.70285 | I12: Cerco perimetrico | J12: ='Datos iniciales '!E82 -> 20 | AG12: =SUM(AG9:AG11) -> 3.73144
A13: CONCRETO EN LOSA DEPORTIVA F'C= 210 KG/CM2 | B13: 0.22 | C13: m2 | D13: =B13*$J$3 -> 4.4 | E13: =U63 -> 445.66922 | F13: =D13*E13 -> 1960.9446 | I13: Area construida | J13: ='Datos iniciales '!B3 -> 300 | Y13: Materiales
A14: CONCRETO DE UÑAS = 210KG/CM2 | B14: 0.0144 | C14: m3 | D14: =B14*$J$3 -> 0.288 | E14: =U64 -> 445.66922 | F14: =D14*E14 -> 128.35274 | I14: Area terreno | J14: ='Datos iniciales '!C3 -> 1000 | Y14: AGUA | AC14: m3 | AE14: 0.033 | AF14: 6.14 | AG14: =AE14*AF14 -> 0.20262
A15: ENCOFRADO Y DESENCOFRADO NORMAL EN LOSA | B15: 0.0766 | C15: m2 | D15: =B15*$J$3 -> 1.532 | E15: =U65 -> 118.01356 | F15: =D15*E15 -> 180.79678 | I15: Altura | J15: =INDEX('Datos iniciales '!C5:C8,MATCH(MAX('Datos iniciales '!B5:B8),'Datos iniciales '!B5:B8,0)) -> 1 | Y15: TIERRA DE CHACRA | AC15: m3 | AE15: 0.15 | AF15: 62.883903 | AG15: =AE15*AF15 -> 9.4325855
A16: DADOS DE CONCRETO PARA SOPORTE, f'c=210 kg/cm2 | B16: 0.0008 | C16: m3 | D16: =B16*$J$3 -> 0.016 | E16: =U66 -> 358 | F16: =D16*E16 -> 5.728 | AG16: =SUM(AG14:AG15) -> 9.6352055
A17: CURADO DE LOSA | B17: 1 | C17: m2 | D17: =B17*$J$3 -> 20 | E17: =U67 -> 2.9418736 | F17: =D17*E17 -> 58.837472 | Y17: Equipos
A18: JUNTAS DE DILATACION E= 1" , H=0.10 | B18: 0.1607 | C18: m | D18: =B18*$J$3 -> 3.214 | E18: =U68 -> 19.238683 | F18: =D18*E18 -> 61.833128 | Y18: HERRAMIENTAS MANUALES | AC18: %mo | AE18: 3 | AF18: =AG12 -> 3.73144 | AG18: =AE18%*AF18 -> 0.1119432
A19: JUNTAS DILATACION E= 1", H= 0.05 | B19: 0.1889 | C19: m | D19: =B19*$J$3 -> 3.778 | E19: =U69 -> 19.238683 | F19: =D19*E19 -> 72.683745 | AG19: =SUM(AG18) -> 0.1119432
A20: ESTRUCTURA METALICA P/PARANTES DE REFLECTORES | B20: 0.0074 | C20: m | D20: =B20*$J$3 -> 0.148 | E20: =U70 -> 616.64 | F20: =D20*E20 -> 91.26272
A21: PINTURA DE LINEASEN LOSA DEPORTIVA | B21: 0.025 | C21: m | D21: =B21*$J$3 -> 0.5 | E21: =U71 -> 51.058432 | F21: =D21*E21 -> 25.529216 | X21: SubPartida | Z21: SUMINISTRO Y SEMBRIO DE ARBUSTOS
A22: Cobertura Liviana de Losa DEPORTIVA | C22: m2 | D22: =J4 -> 20 | E22: =V236 -> 169.49 | G22: =D22*E22 -> 3389.8 | X22: Rendimiento m2/día | Y22: m2/dia | Z22: M.O | AA22: 20 | AB22: EQ | AC22: =AA22 -> 20 | AD22: Costo unitario directo | AF22: m2 | AG22: =AG28+AG33+AG36 -> 73.852121
X23: Código | Y23: Descripción Recurso | AC23: Unidad | AD23: Cuadrilla | AE23: Cantidad | AF23: Precio (S/.) | AG23: Parcial (S/.)
A24: PATIO DE INICIAL | C24: m2 | G24: =SUM(F25:F37) -> 3254.2781 | Y24: Mano de Obra
Y25: CAPATAZ | AC25: hh | AD25: 0.1 | AE25: =AD25*8/$AA$22 -> 0.04 | AF25: 34.73 | AG25: =AE25*AF25 -> 1.3892
Y26: OFICIAL | AC26: hh | AD26: 1 | AE26: =AD26*8/$AA$22 -> 0.4 | AF26: 22.66 | AG26: =AE26*AF26 -> 9.064
A27: COMPACTACION DE SUBRASANTE | B27: 1 | C27: m3 | D27: =B27*$J$5 -> 20 | E27: =U61 -> 7.930344 | F27: =D27*E27 -> 158.60688 | Y27: PEON | AC27: hh | AD27: 1 | AE27: =AD27*8/$AA$22 -> 0.4 | AF27: 20.51 | AG27: =AE27*AF27 -> 8.204
A28: AFIRMADO DE e=0.30m PARA LOSA | B28: 0.33 | C28: m3 | D28: =B28*$J$5 -> 6.6 | E28: =U62 -> 77.227705 | F28: =D28*E28 -> 509.70285 | AG28: =SUM(AG25:AG27) -> 18.6572
A29: CONCRETO EN LOSA DEPORTIVA F'C= 210 KG/CM2 | B29: 0.22 | C29: m2 | D29: =B29*$J$5 -> 4.4 | E29: =U63 -> 445.66922 | F29: =D29*E29 -> 1960.9446 | Y29: Materiales
A30: CONCRETO DE UÑAS = 210KG/CM2 | B30: 0.0144 | C30: m3 | D30: =B30*$J$5 -> 0.288 | E30: =U64 -> 445.66922 | F30: =D30*E30 -> 128.35274 | Y30: AGUA | AC30: m3 | AE30: 0.033 | AF30: 6.14 | AG30: =AE30*AF30 -> 0.20262
A31: ENCOFRADO Y DESENCOFRADO NORMAL EN LOSA | B31: 0.0766 | C31: m2 | D31: =B31*$J$5 -> 1.532 | E31: =U65 -> 118.01356 | F31: =D31*E31 -> 180.79678 | Y31: TIERRA DE CHACRA | AC31: m3 | AE31: 0.15 | AF31: 62.883903 | AG31: =AE31*AF31 -> 9.4325855
A32: DADOS DE CONCRETO PARA SOPORTE, f'c=210 kg/cm2 | B32: 0.0008 | C32: m3 | D32: =B32*$J$5 -> 0.016 | E32: =U66 -> 358 | F32: =D32*E32 -> 5.728 | Y32: ARBUSTOS LOCALES | AC32: und | AE32: 1 | AF32: 45 | AG32: =AE32*AF32 -> 45
A33: CURADO DE LOSA | B33: 1 | C33: m2 | D33: =B33*$J$5 -> 20 | E33: =U67 -> 2.9418736 | F33: =D33*E33 -> 58.837472 | AG33: =SUM(AG30:AG32) -> 54.635205
A34: JUNTAS DE DILATACION E= 1" , H=0.10 | B34: 0.1607 | C34: m | D34: =B34*$J$5 -> 3.214 | E34: =U68 -> 19.238683 | F34: =D34*E34 -> 61.833128 | Y34: Equipos
A35: JUNTAS DILATACION E= 1", H= 0.05 | B35: 0.1889 | C35: m | D35: =B35*$J$5 -> 3.778 | E35: =U69 -> 19.238683 | F35: =D35*E35 -> 72.683745 | Y35: HERRAMIENTAS MANUALES | AC35: %mo | AE35: 3 | AF35: =AG28 -> 18.6572 | AG35: =AE35%*AF35 -> 0.559716
A36: ESTRUCTURA METALICA P/PARANTES DE REFLECTORES | B36: 0.0074 | C36: m | D36: =B36*$J$5 -> 0.148 | E36: =U70 -> 616.64 | F36: =D36*E36 -> 91.26272 | AG36: =SUM(AG35) -> 0.559716
A37: PINTURA DE LINEASEN LOSA DEPORTIVA | B37: 0.025 | C37: m | D37: =B37*$J$5 -> 0.5 | E37: =U71 -> 51.058432 | F37: =D37*E37 -> 25.529216
A38: Cobertura Liviana de PATIO DE INICIAL | C38: m2 | D38: =J6 -> 20 | E38: =V236 -> 169.49 | G38: =D38*E38 -> 3389.8 | X38: SubPartida | Z38: SUMINISTRO Y SEMBRIO DE ARBOLES
X39: Rendimiento m2/día | Y39: m2/dia | Z39: M.O | AA39: 20 | AB39: EQ | AC39: =AA39 -> 20 | AD39: Costo unitario directo | AF39: m2 | AG39: =AG45+AG50+AG53 -> 118.74774
A40: ASTA DE BANDERA | C40: und | D40: =J7 -> 2 | E40: =V243 -> 2147.2003 | G40: =D40*E40 -> 4294.4007 | X40: Código | Y40: Descripción Recurso | AC40: Unidad | AD40: Cuadrilla | AE40: Cantidad | AF40: Precio (S/.) | AG40: Parcial (S/.)
Y41: Mano de Obra
A42: VEREDAS Y RAMPAS DE CONCRETO | C42: m2 | E42: =V289 -> 136.5856 | G42: =SUM(F45:F53) -> 2731.712 | Y42: CAPATAZ | AC42: hh | AD42: 0.1 | AE42: =AD42*8/$AA$39 -> 0.04 | AF42: 34.73 | AG42: =AE42*AF42 -> 1.3892
Y43: OFICIAL | AC43: hh | AD43: 1 | AE43: =AD43*8/$AA$39 -> 0.4 | AF43: 22.66 | AG43: =AE43*AF43 -> 9.064
Y44: PEON | AC44: hh | AD44: 1 | AE44: =AD44*8/$AA$39 -> 0.4 | AF44: 20.51 | AG44: =AE44*AF44 -> 8.204
A45: COMPACTACION DE SUBRASANTE | B45: 1 | C45: m2 | D45: =B45*$J$8 -> 20 | E45: =U280 -> 7.930344 | F45: =D45*E45 -> 158.60688 | AG45: =SUM(AG42:AG44) -> 18.6572
A46: AFIRMADO DE e=0.30m PARA LOSA | B46: 0.33 | C46: m2 | D46: =B46*$J$8 -> 6.6 | E46: =U281 -> 77.227705 | F46: =D46*E46 -> 509.70285 | Y46: Materiales
A47: CONCRETO EN VEREDAS F'C= 175 KG/CM2 | B47: 0.12 | C47: m2 | D47: =B47*$J$8 -> 2.4 | E47: =U282 -> 447.90067 | F47: =D47*E47 -> 1074.9616 | Y47: AGUA | AC47: m3 | AE47: 0.016 | AF47: 6.14 | AG47: =AE47*AF47 -> 0.09824
A48: CONCRETO DE UÑAS = 175KG/CM2 | B48: 0.014 | C48: m3 | D48: =B48*$J$8 -> 0.28 | E48: =U283 -> 447.90067 | F48: =D48*E48 -> 125.41219 | Y48: TIERRA DE CHACRA | AC48: m3 | AE48: 0.15 | AF48: 62.883903 | AG48: =AE48*AF48 -> 9.4325855
A49: ENCOFRADO Y DESENCOFRADO NORMAL EN LOSA | B49: 0.2 | C49: m2 | D49: =B49*$J$8 -> 4 | E49: =U284 -> 118.01356 | F49: =D49*E49 -> 472.05426 | Y49: ARBOL | AC49: und | AE49: 1 | AF49: 90 | AG49: =AE49*AF49 -> 90
A50: CURADO DE LOSA | B50: 1 | C50: m2 | D50: =B50*$J$8 -> 20 | E50: =U285 -> 2.9418736 | F50: =D50*E50 -> 58.837472 | AG50: =SUM(AG47:AG49) -> 99.530825
A51: ACABADO FROTACHADO Y BRUÑADO EN VEREDAS | B51: 1 | C51: m2 | D51: =B51*$J$8 -> 20 | E51: =U286 -> 9.880996 | F51: =D51*E51 -> 197.61992 | Y51: Equipos
A52: JUNTAS DE DILATACION E= 1" , H=0.10 | B52: 0.1607 | C52: m | D52: =B52*$J$8 -> 3.214 | E52: =U287 -> 19.238683 | F52: =D52*E52 -> 61.833128 | Y52: HERRAMIENTAS MANUALES | AC52: %mo | AE52: 3 | AF52: =AG45 -> 18.6572 | AG52: =AE52%*AF52 -> 0.559716
A53: JUNTAS DILATACION E= 1", H= 0.05 | B53: 0.1889 | C53: m | D53: =B53*$J$8 -> 3.778 | E53: =U288 -> 19.238683 | F53: =D53*E53 -> 72.683745 | AG53: =SUM(AG52) -> 0.559716
A55: PAVIMENTO RIGIDO VEHICULAR | C55: m2 | E55: =V325 -> 171.72584 | G55: =SUM(F58:F65) -> 3434.5168 | M55: Partida | O55: LOSA DEPORTIVA (44 x 22: 968) F'C=210 kg/cm² DE 20 CM DE ESPESOR | X55: Partida | Z55: LIMPIEZA DE TERRENO MANUAL
M56: Rendimiento m2/día | N56: und/dia | O56: M.O | P56: 1 | Q56: EQ | R56: =P56 -> 1 | S56: Costo unitario directo | U56: und | V56: =V72 -> 162.71391 | X56: Rendimiento m2/día | Y56: m2/dia | Z56: M.O | AA56: 90 | AB56: EQ | AC56: =AA56 -> 90 | AD56: Costo unitario directo | AF56: m2 | AG56: =AG61+AG64 -> 2.1957769
M57: Código | N57: Descripción Recurso | R57: Unidad | S57: Cuadrilla | T57: Cantidad | U57: Precio (S/.) | V57: Parcial (S/.) | X57: Código | Y57: Descripción Recurso | AC57: Unidad | AD57: Cuadrilla | AE57: Cantidad | AF57: Precio (S/.) | AG57: Parcial (S/.)
A58: COMPACTACION DE SUBRASANTE | B58: 1 | C58: m3 | D58: =B58*$J$9 -> 20 | E58: =U330 -> 7.930344 | F58: =D58*E58 -> 158.60688 | N58: Subpartidas | Y58: Mano de Obra
A59: AFIRMADO DE e=0.30m PARA LOSA | B59: 0.33 | C59: m2 | D59: =B59*$J$9 -> 6.6 | E59: =U331 -> 77.227705 | F59: =D59*E59 -> 509.70285 | Y59: CAPATAZ | AC59: hh | AD59: 0.1 | AE59: =AD59*8/$AA$56 -> 0.0088888889 | AF59: 34.73 | AG59: =AE59*AF59 -> 0.30871111
A60: ACABADO CEPILLADO | B60: 1 | C60: glb | D60: =B60*$J$9 -> 20 | E60: =U332 -> 22 | F60: =D60*E60 -> 440 | Y60: PEON | AC60: hh | AD60: 1 | AE60: =AD60*8/$AA$56 -> 0.088888889 | AF60: 20.51 | AG60: =AE60*AF60 -> 1.8231111
A61: PAVIMENTO VEHICULAR - ENCOFRADO Y DESENCOFRADO | B61: 0.225 | C61: m2 | D61: =B61*$J$9 -> 4.5 | E61: =U333 -> 84.674043 | F61: =D61*E61 -> 381.0332 | N61: COMPACTACION DE SUBRASANTE DE LOSA | R61: m3 | T61: 1 | U61: =AG74 -> 7.930344 | V61: =T61*U61 -> 7.930344 | AG61: =SUM(AG59:AG60) -> 2.1318222
A62: DOWELLS | B62: 0.2 | C62: kg | D62: =B62*$J$9 -> 4 | E62: =U334 -> 7.5057997 | F62: =D62*E62 -> 30.023199 | N62: AFIRMADO DE e=0.30m PARA LOSA | R62: m3 | T62: 0.33 | U62: =AG89 -> 77.227705 | V62: =T62*U62 -> 25.485143 | Y62: Equipos
A63: CURADO DE CONCRETO | B63: 1 | C63: m2 | D63: =B63*$J$9 -> 20 | E63: =U335 -> 2.9418736 | F63: =D63*E63 -> 58.837472 | N63: CONCRETO EN LOSA DEPORTIVA F'C= 210 KG/CM2 | R63: m2 | T63: 0.22 | U63: =AG106 -> 445.66922 | V63: =T63*U63 -> 98.047229 | Y63: HERRAMIENTAS MANUALES | AC63: %mo | AE63: 3 | AF63: =AG61 -> 2.1318222 | AG63: =AE63%*AF63 -> 0.063954667
A64: PAVIMENTO VEHICULAR - CONCRETO F'C=210 kg/cm2 | B64: 0.2 | C64: m3 | D64: =B64*$J$9 -> 4 | E64: =U336 -> 445.90736 | F64: =D64*E64 -> 1783.6294 | N64: CONCRETO DE UÑAS = 210KG/CM2 | R64: m3 | T64: 0.0144 | U64: =AG125 -> 445.66922 | V64: =T64*U64 -> 6.4176368 | AG64: =SUM(AG63) -> 0.063954667
A65: JUNTAS DILATACION E= 1", H= 0.05 | B65: 0.1889 | C65: m | D65: =B65*$J$9 -> 3.778 | E65: =U337 -> 19.238683 | F65: =D65*E65 -> 72.683745 | N65: ENCOFRADO Y DESENCOFRADO NORMAL EN LOSA | R65: m2 | T65: 0.0766 | U65: =AG144 -> 118.01356 | V65: =T65*U65 -> 9.0398391
A66: LAMAS EN PASADIZOS | C66: m2 | D66: =J10 -> 20 | E66: =V390 -> 75.46 | F66: =D66*E66 -> 1509.2 | N66: DADOS DE CONCRETO PARA SOPORTE, f'c=210 kg/cm2 | R66: m3 | T66: 0.0008 | U66: =AG163 -> 358 | V66: =T66*U66 -> 0.2864 | X66: Partida | Z66: TRAZO, NIVELES Y REPLANTEO PRELIMINAR
N67: CURADO DE LOSA | R67: m2 | T67: 1 | U67: =AG170 -> 2.9418736 | V67: =T67*U67 -> 2.9418736 | X67: Rendimiento m2/día | Y67: m2/dia | Z67: M.O | AA67: 1 | AB67: EQ | AC67: =AA67 -> 1 | AD67: Costo unitario directo | AF67: m2 | AG67: =AG71 -> 10.5
A68: ESTACIONAMIENTO DE BICICLETAS | C68: und | D68: =J11 -> 2 | E68: =V397 -> 69.41 | G68: =D68*E68 -> 138.82 | N68: JUNTAS DE DILATACION E= 1" , H=0.10 | R68: m | T68: 0.1607 | U68: =AG183 -> 19.238683 | V68: =T68*U68 -> 3.0916564 | X68: Código | Y68: Descripción Recurso | AC68: Unidad | AD68: Cuadrilla | AE68: Cantidad | AF68: Precio (S/.) | AG68: Parcial (S/.)
N69: JUNTAS DILATACION E= 1", H= 0.05 | R69: m | T69: 0.1889 | U69: =AG198 -> 19.238683 | V69: =T69*U69 -> 3.6341873 | Y69: Materiales
N70: ESTRUCTURA METALICA P/PARANTES DE REFLECTORES | R70: m | T70: 0.0074 | U70: =AG213 -> 616.64 | V70: =T70*U70 -> 4.563136 | Y70: TRAZO, NIVELES Y REPLANTEO PRELIMINAR | AE70: 1 | AF70: 10.5 | AG70: =AE70*AF70 -> 10.5
A71: INSTALACIONES EXTERIORES | N71: PINTURA DE LINEASEN LOSA DEPORTIVA | R71: m | T71: 0.025 | U71: =AG220 -> 51.058432 | V71: =T71*U71 -> 1.2764608 | AG71: =SUM(AG70) -> 10.5
A72: Sistema de Bombeo de Presión Constante | B72: 17.15 | C72: Glb | D72: 1 | E72: =V400 -> 2867.4 | F72: =D72*E72 -> 2867.4 | V72: =SUM(V59:V71) -> 162.71391
A73: Instalaciones sanitarias exteriores inc. Canaletas de evacuación pluvial | B73: 12.75 | C73: Glb | D73: 1 | E73: =V407 -> 6500 | F73: =D73*E73 -> 6500 | X73: SubPartida | Z73: CONINICIAL Y COMPACTACION DE SUBRASANTE
A74: Sistema de agua contra incendios (RED CONTRA INCENDIOS, GABINETES) | B74: 28.63 | C74: Glb | D74: 1 | E74: =V414 -> 6600 | F74: =D74*E74 -> 6600 | X74: Rendimiento m2/día | Y74: m2/dia | Z74: M.O | AA74: 500 | AB74: EQ | AC74: =AA74 -> 500 | AD74: Costo unitario directo | AF74: m2 | AG74: =AG80+AG86 -> 7.930344
A75: Suministro y Montaje de Montacarga | C75: Glb | D75: 1 | E75: =V421 -> 95160 | F75: =D75*E75 -> 95160 | X75: Código | Y75: Descripción Recurso | AC75: Unidad | AD75: Cuadrilla | AE75: Cantidad | AF75: Precio (S/.) | AG75: Parcial (S/.)
A76: CERCO PERIMETRICO E INGRESOS | Y76: Mano de Obra
A77: Cerco Perimetrico H=3.00m | C77: ml | D77: =J12 -> 20 | E77: =V428 -> 3770.8389 | G77: =SUM(F78:F90) -> 74870.039 | Y77: CAPATAZ | AC77: hh | AD77: 1 | AE77: =AD77*8/$AA$74 -> 0.016 | AF77: 34.73 | AG77: =AE77*AF77 -> 0.55568
A78: EXCAVACION MANUAL PARA CIMENTACIONES | C78: m3 | D78: =1.98*$J$12 -> 39.6 | E78: =U431 -> 56.462834 | F78: =D78*E78 -> 2235.9282 | Y78: OFICIAL | AC78: hh | AD78: 1 | AE78: =AD78*8/$AA$74 -> 0.016 | AF78: 23.6 | AG78: =AE78*AF78 -> 0.3776
